Workbook
Name BU: #REF!
Name cc: #REF!
Name CLIENTE: #REF!
Name DELIVERY: #REF!
Name STATUS: #REF!

Sheet CC
A1: CENTRO_CUSTOS | B1: CONTRATO | C1: CLIENTE | D1: STATUS | E1: BU | F1: VERTICAL | G1: EXECUTIVO | H1: Dr_OPE | I1: SETOR
A2: 1101 | B2: DIRETORIA (1101) | C2: ADM/FIN | D2: ATIVO | E2: TX_ADM | F2: ALL | G2: PAULO MARCELO | H2: OP | I2: CORPORATIVO
A3: 1102 | B3: DIRETOR MARIO BRITO (1102) | C3: DESATIVADO | D3: INATIVO | I3: CORPORATIVO
A4: 1103 | B4: FINANCEIRO (1103) | C4: ADM/FIN | D4: ATIVO | E4: TX_ADM | F4: ALL | G4: ANDRÉ MOTA | H4: OP | I4: CORPORATIVO
A5: 1104 | B5: ADMINISTRATIVO (1104) | C5: ADM/FIN | D5: ATIVO | E5: TX_ADM | F5: ALL | G5: ANDRÉ MOTA | H5: OP | I5: CORPORATIVO
A6: 1105 | B6: DEPARTAMENTO PESSOAL (DP) (1105) | C6: RH | D6: ATIVO | E6: TX_ADM | F6: ALL | G6: VIVIANE SANTOS | H6: OP | I6: CORPORATIVO
A7: 1109 | B7: QUALIDADE (1109) | C7: QUALIDADE | D7: ATIVO | E7: TX_ADM | F7: ALL | G7: EVANDRO BRAGA | H7: OP | I7: CORPORATIVO
A8: 1110 | B8: APOIO COMERCIAL (1110) | C8: COMERCIAL | D8: ATIVO | E8: TX_ADM | F8: ALL | G8: ANDRÉ MOTA | H8: OP | I8: CORPORATIVO
A9: 1111 | B9: AQUISIÇÕES PT SOLUTIS (1111) | C9: AQUIS_ESTACAO | D9: ATIVO | E9: TX_ADM | F9: ALL | G9: ANDRÉ MOTA | H9: OP | I9: CORPORATIVO
A10: 1114 | B10: TALENT ACQUISITION (1114) | C10: RH | D10: ATIVO | E10: TX_ADM | F10: ALL | G10: VIVIANE SANTOS | H10: OP | I10: CORPORATIVO
A11: 1116 | B11: MARKETING (1116) | C11: MKT | D11: ATIVO | E11: TX_ADM | F11: ALL | G11: DEBORA LIMA | H11: OP | I11: CORPORATIVO
A12: 1117 | B12: RECURSO INTERNO (1117) | C12: ADM/FIN | D12: ATIVO | E12: TX_ADM | F12: ALL | G12: VIVIANE SANTOS | H12: OP | I12: CORPORATIVO
A13: 1118 | B13: TI INTERNA CORPORATIVA (1118) | C13: TI_PLAT_CORP | D13: ATIVO | E13: TX_ADM | F13: ALL | G13: ANDRÉ MOTA | H13: OP | I13: CORPORATIVO
A14: 1119 | B14: CDO – PRÉ VENDA (1119) | C14: DESATIVADO | D14: INATIVO | I14: CORPORATIVO
A15: 1136 | B15: CDO (1136) | C15: DESATIVADO | D15: INATIVO | I15: CORPORATIVO
A16: 1139 | B16: PSU (1139) | C16: COMERCIAL | D16: ATIVO | E16: TX_ADM | F16: ALL | G16: MARIO AMERICO | H16: OP | I16: CORPORATIVO
A17: 1140 | B17: FS (1140) | C17: COMERCIAL | D17: ATIVO | E17: TX_ADM | F17: ALL | G17: LUIS RICARDO MARTORELLI | H17: OP | I17: CORPORATIVO
A18: 1141 | B18: MS (1141) | C18: COMERCIAL | D18: ATIVO | E18: TX_ADM | F18: ALL | G18: PAULO MARCELO | H18: OP | I18: CORPORATIVO
A19: 1142 | B19: DCX (1142) | C19: DESATIVADO | D19: INATIVO | I19: CORPORATIVO
A20: 1143 | B20: ADS (1143) | C20: DESATIVADO | D20: INATIVO | I20: CORPORATIVO
A21: 1144 | B21: CPS (1144) | C21: DESATIVADO | D21: INATIVO | I21: CORPORATIVO
A22: 1145 | B22: CSA (1145) | C22: COMERCIAL | D22: INATIVO | I22: CORPORATIVO
A23: 1146 | B23: SALESFORCE (1146) | C23: PORT_FORMACAO | D23: ATIVO | E23: TX_ADM | F23: ALL | G23: NIVALDO AMORIM | H23: OP | I23: CORPORATIVO
A24: 1147 | B24: TM Telecom/Mídia (1147) | C24: DESATIVADO | D24: INATIVO | I24: CORPORATIVO
A25: 1149 | B25: INFRA DIGITAL (1149) | C25: DESATIVADO | D25: INATIVO | I25: CORPORATIVO
A26: 1150 | B26: DPO - Proteção de Dados (1150) | C26: ADM/FIN | D26: ATIVO | E26: TX_ADM | F26: ALL | G26: ANDRÉ MOTA | H26: OP | I26: CORPORATIVO
A27: 1151 | B27: RPA (1151) | C27: DESATIVADO | D27: INATIVO | I27: CORPORATIVO
A28: 1152 | B28: D&A (1152) | C28: DESATIVADO | D28: INATIVO | I28: CORPORATIVO
A29: 1153 | B29: BUSINESS PARTNER (BP) (1153) | C29: RH | D29: ATIVO | E29: TX_ADM | F29: ALL | G29: VIVIANE SANTOS | H29: OP | I29: CORPORATIVO
A30: 1154 | B30: REMUNERAÇÃO & BENEFÍCIOS (R&B) (1154) | C30: DESATIVADO | D30: INATIVO | I30: CORPORATIVO
A31: 1155 | B31: PEOPLE ENGAGEMENT (1155) | C31: MKT | D31: ATIVO | E31: TX_ADM | F31: ALL | G31: DEBORA LIMA | H31: OP | I31: CORPORATIVO
A32: 1156 | B32: TIC (1156) | C32: TIC | D32: ATIVO | E32: TX_ADM | F32: ALL | G32: ANDRÉ MOTA | H32: OP | I32: CORPORATIVO
A33: 1157 | B33: ACADEMY (1157) | C33: PORT_FORMACAO | D33: ATIVO | E33: TX_ADM | F33: ALL | G33: MANOEL NETO | H33: OP | I33: CORPORATIVO
A34: 1158 | B34: GESTÃO DE RH | C34: RH | D34: ATIVO | E34: TX_ADM | F34: ALL | G34: VIVIANE SANTOS | H34: OP | I34: CORPORATIVO
A35: 1159 | B35: SOLUTIS LABS (1159) | C35: PORT_FORMACAO | D35: ATIVO | E35: TX_ADM | F35: ALL | G35: ANA PAULA BRAUN | H35: OP | I35: CORPORATIVO
A36: 1160 | B36: IV (1160) | C36: COMERCIAL | D36: ATIVO | E36: TX_ADM | F36: ALL | G36: PAULO MARCELO | H36: OP | I36: CORPORATIVO
A37: 1161 | B37: ESTRUTURAÇÃO FINANCIAL SERVICES (1161) | C37: COMERCIAL | D37: INATIVO | I37: CORPORATIVO
A38: 1162 | B38: CONSELHO (1162) | C38: CONSELHO | D38: ATIVO | E38: TX_ADM | F38: ALL | G38: ANDRÉ MOTA | H38: OP | I38: CORPORATIVO
A39: 1163 | B39: PLATAFORMA CORPORATIVA (1163) | C39: TI_PLAT_CORP | D39: ATIVO | E39: TX_ADM | F39: ALL | G39: ANDRÉ MOTA | H39: OP | I39: CORPORATIVO
A40: 1164 | B40: PRODUTOS DIGITAIS (1164) | C40: PORT_FORMACAO | D40: ATIVO | E40: TX_ADM | F40: ALL | G40: NIVALDO AMORIM | H40: OP | I40: CORPORATIVO
A41: 1167 | B41: PRÁTICA IA (1167) | C41: PORT_FORMACAO | D41: ATIVO | E41: TX_ADM | F41: ALL | G41: ANA PAULA BRAUN | H41: OP | I41: CORPORATIVO
A42: 1170 | B42: DESENVOLVIMENTO HUMANO ORGANIZACIONAL (DHO) (1170) | C42: RH | D42: ATIVO | E42: TX_ADM | F42: ALL | G42: VIVIANE SANTOS | H42: OP | I42: CORPORATIVO
A43: 1171 | B43: UTILITIES (1171) | C43: COMERCIAL | D43: ATIVO | E43: TX_ADM | F43: ALL | G43: MARIO AMERICO | H43: OP | I43: CORPORATIVO
A44: 1172 | B44: CONVÊNIO UFBA (1172) | C44: PORT_FORMACAO | D44: ATIVO | E44: TX_ADM | F44: ALL | G44: NIVALDO AMORIM | H44: OP | I44: CORPORATIVO
A45: 1173 | B45: DIRETORIA OPERAÇÕES – OP02 (1173) | C45: DIR_OPE | D45: ATIVO | E45: ADS | F45: ALL | G45: RODRIGO CORUMBA | H45: OP | I45: CORPORATIVO
A46: 1199 | B46: DESPESAS GERAIS ESCRITÓRIO (1199) | C46: ADM/FIN | D46: ATIVO | E46: TX_ADM | F46: ALL | G46: ANDRÉ MOTA | H46: OP | I46: CORPORATIVO
A47: 6102 | B47: RECEITA TAXA ADMINISTRAÇÃO (6102) | C47: CRÉDITO | D47: ATIVO | E47: TX_ADM | F47: ALL | G47: ANDRÉ MOTA | H47: OP | I47: CORPORATIVO
A48: 6103 | B48: RECEITA POSTO DE TRABALHO (6103) | C48: CRÉDITO | D48: ATIVO | E48: TX_ADM | F48: ALL | G48: ANDRÉ MOTA | H48: OP | I48: CORPORATIVO
A49: 6118 | B49: REPASSE P/DESP. OPERACIONAIS - PJ (6118) | C49: COMERCIAL | D49: INATIVO | I49: CORPORATIVO
A50: 6119 | B50: TRANSF. IMPOSTO S/FATURAMENTO (6119) | C50: ADM/FIN | D50: ATIVO | E50: TX_ADM | F50: ALL | G50: ANDRÉ MOTA | H50: OP | I50: CORPORATIVO
A51: 6120 | B51: PROCESSOS TRABALHISTAS (6120) | C51: ADM/FIN | D51: ATIVO | E51: TX_ADM | F51: ALL | G51: VIVIANE SANTOS | H51: OP | I51: CORPORATIVO
A52: 9900 | B52: CENTROS_CSA | C52: CUSTO_INDIRETO | D52: ATIVO | E52: CSA | F52: ALL | G52: EVANDRO BRAGA | H52: OP | I52: OPERAÇÕES
A53: 1201 | B53: OVERHEAD DE OPERAÇÕES (1201) | C53: CUSTO_INDIRETO | D53: INATIVO | I53: OPERAÇÕES
A54: 1202 | B54: COMERCIAL APLIC (1202) | C54: DESATIVADO | D54: INATIVO | I54: OPERAÇÕES
A55: 1203 | B55: CENTRO DE COMPETÊNCIA APLICAÇÕES (1203) | C55: DESATIVADO | D55: INATIVO | I55: OPERAÇÕES
A56: 1204 | B56: CENTRO DE DESENVOLVIMENTO (1204) | C56: DESATIVADO | D56: INATIVO | I56: OPERAÇÕES
A57: 1205 | B57: SEFAZ - PMS Outsourcing (1205) | C57: DESATIVADO | D57: INATIVO | I57: OPERAÇÕES
A58: 1206 | B58: EBAL APLICAÇÃO (1206) | C58: DESATIVADO | D58: INATIVO | I58: OPERAÇÕES
A59: 1207 | B59: TJ - BA SUSTENTAÇÃO (1207) | C59: TJ_BA | D59: INATIVO | I59: OPERAÇÕES
A60: 1208 | B60: SECULT (1208) | C60: DESATIVADO | D60: INATIVO | I60: OPERAÇÕES
A61: 1209 | B61: INVESTIMENTOS (1209) | C61: DESATIVADO | D61: INATIVO | I61: OPERAÇÕES
A62: 1210 | B62: SEFAZ - PMS FSW (1210) | C62: DESATIVADO | D62: INATIVO | I62: OPERAÇÕES
A63: 1211 | B63: SISTEMAS INTERNOS (1211) | C63: DESATIVADO | D63: INATIVO | I63: OPERAÇÕES
A64: 1212 | B64: MANUTENÇÃO GIROWEB (1212) | C64: DESATIVADO | D64: INATIVO | I64: OPERAÇÕES
... A72: 1220 | B72: TJ - BA FSW (1220) | C72: TJ_BA | D72: INATIVO | I72: OPERAÇÕES
A73: 1221 | B73: SABESP - MONITORAMENTO (1221) | C73: SABESP | D73: ATIVO | E73: CSA | F73: UT | G73: CYRO SALVATORE | H73: OP1 | I73: OPERAÇÕES
A74: 1222 | B74: AGILE DEV STUDIO (1222) | C74: CUSTO_INDIRETO | D74: ATIVO | E74: ADS | F74: ALL | G74: KARINA MELO | H74: OP | I74: OPERAÇÕES
A75: 1223 | B75: TJ - BA GOVERNANÇA (1223) | C75: TJ_BA | D75: INATIVO | I75: OPERAÇÕES
A76: 1224 | B76: UFBA FSW (1224) | C76: DESATIVADO | D76: INATIVO | I76: OPERAÇÕES
A77: 1225 | B77: LE BISCUIT (1225) | C77: LE_BISCUIT | D77: INATIVO | I77: OPERAÇÕES
A78: 1226 | B78: UFBA CENTRAL DE SERVIÇOS (1226) | C78: UFBA | D78: INATIVO | I78: OPERAÇÕES
A79: 1227 | B79: SEC CENTRAL DE SERVIÇOS (1227) | C79: SEC-BA | D79: INATIVO | I79: OPERAÇÕES
A80: 1228 | B80: ENSEADA INDUSTRIA NAVAL (1228) | C80: DESATIVADO | D80: INATIVO | I80: OPERAÇÕES
A81: 1229 | B81: ELETRONUCLEAR (1229) | C81: AXIA | D81: INATIVO | I81: OPERAÇÕES
A82: 1230 | B82: FAPESB (1230) | C82: FAPESB | D82: ATIVO | E82: ADS | F82: PS | G82: LIZANDRA PIMENTA | H82: OP3 | I82: OPERAÇÕES
A83: 1231 | B83: CONSULTECH - MOURA DUBEAX (1231) | C83: DESATIVADO | D83: INATIVO | I83: OPERAÇÕES
A84: 1233 | B84: AXIA N1 - MONITORAMENTO (1233) | C84: AXIA | D84: ATIVO | E84: CSA | F84: UT | G84: JOSÉ NETO | H84: OP2 | I84: OPERAÇÕES
A85: 1234 | B85: AERONAUTICA (1234) | C85: DESATIVADO | D85: INATIVO | I85: OPERAÇÕES
A86: 1235 | B86: STUDIO RJ (1235) | C86: IPLAN | D86: INATIVO | E86: ADS | F86: PS | I86: OPERAÇÕES
A87: 1236 | B87: SEFAZ - MT (1236) | C87: DESATIVADO | D87: INATIVO | I87: OPERAÇÕES
A88: 1237 | B88: SEC SISTEMAS (1237) | C88: SEC-BA | D88: INATIVO | I88: OPERAÇÕES
A89: 1238 | B89: DETRAN - BA (1238) | C89: DETRAN-BA | D89: INATIVO | I89: OPERAÇÕES
A90: 1239 | B90: SEC N3 (1239) | C90: SEC-BA | D90: INATIVO | I90: OPERAÇÕES
A91: 1240 | B91: TRF RJ (1240) | C91: TRF | D91: INATIVO | I91: OPERAÇÕES
A92: 1241 | B92: TJ - BA SERVICE DESK (1241) | C92: TJ_BA | D92: INATIVO | I92: OPERAÇÕES
A93: 1242 | B93: BAHIA GÁS (1242) | C93: BAHIA GÁS | D93: INATIVO | I93: OPERAÇÕES
A94: 1243 | B94: TRF - RJ Apoio (1243) | C94: TRF | D94: INATIVO | I94: OPERAÇÕES
A95: 1244 | B95: SEBRAE-SP Sistemas (1244) | C95: SEBRAE | D95: INATIVO | I95: OPERAÇÕES
A96: 1245 | B96: EMBASA - Aplicações (1245) | C96: EMBASA | D96: INATIVO | I96: OPERAÇÕES
A97: 1246 | B97: EBAL SD N1 e N2 (1246) | C97: DESATIVADO | D97: INATIVO | I97: OPERAÇÕES
A98: 1247 | B98: IBAMETRO (1247) | C98: IBAMETRO | D98: ATIVO | E98: CSA | F98: PS | G98: ROGERIO GORDILHO | H98: OP4 | I98: OPERAÇÕES
A99: 1248 | B99: SEBRAE-SP Service Desk (1248) | C99: SEBRAE | D99: ATIVO | E99: CSA | F99: PS | G99: JOSÉ NETO | H99: OP2 | I99: OPERAÇÕES
A100: 1250 | B100: FURNAS - CONSULTORIA (1250) | C100: DESATIVADO | D100: INATIVO | I100: OPERAÇÕES
A101: 1251 | B101: EUROP ASSISTANCE - ADS (1251) | C101: EUROP | D101: INATIVO | I101: OPERAÇÕES
A102: 1252 | B102: SUBVISA (1252) | C102: IPLAN | D102: INATIVO | I102: OPERAÇÕES
A103: 1253 | B103: SEOP (1253) | C103: IPLAN | D103: INATIVO | I103: OPERAÇÕES
A104: 1254 | B104: SME (1254) | C104: IPLAN | D104: INATIVO | I104: OPERAÇÕES
A105: 1255 | B105: SMS (1255) | C105: IPLAN | D105: INATIVO | I105: OPERAÇÕES
A106: 1256 | B106: SMASDH (1256) | C106: IPLAN | D106: INATIVO | I106: OPERAÇÕES
A107: 1257 | B107: PROCON (1257) | C107: IPLAN | D107: INATIVO | I107: OPERAÇÕES
...

Sheet CT A RECEBER
A1: CC | B1: Local | C1: Excecutivo | D1: Grupo Cliente | E1: CLIENTE | F1: TIPO | G1: NFE | H1: MÊS SERVIÇO | I1: VL. FATURADO | J1: VL. LIQ. PRV. | K1: EMISSÃO | L1: PREV . PAG | M1: DATA PAG. | N1: STATUS | O1: Risco | P1: NIVEL RISCO | Q1: BU | R1: Vertical | S1: Diretor de Operações | T1: A RECEBER | U1: SATUS 2 | V1: META | W1: Vencimento
A2: 1390 | B2: =IFERROR(VLOOKUP(Tabela1[[#This Row],[CC]],#REF!,5,0),"") | C2: JOSÉ NETO COELHO | D2: OI | E2: OI - DIGITAL SUPORT (1390) | F2: SERVIÇO | G2: 652 | H2: 44927 | I2: 33803.85 | J2: 32301.82 | K2: 44973 | L2: 45677 | M2: 45678 | N2: PAGO | O2: 0 | Q2: CSA | R2: UT | S2: =IFERROR(VLOOKUP(Tabela1[[#This Row],[CC]],CC!$A$1:$H$403,8,0),"") -> OP2 | T2: SIM | U2: RECUPERAÇÃO JUDICIAL
A3: 1390 | B3: =IFERROR(VLOOKUP(Tabela1[[#This Row],[CC]],#REF!,5,0),"") | C3: JOSÉ NETO COELHO | D3: OI | E3: OI - DIGITAL SUPORT (1390) | F3: SERVIÇO | G3: 1168 | H3: 45536 | I3: 185487.39 | J3: 163878.11 | K3: 45581 | L3: 45677 | M3: 45679 | N3: PAGO | O3: 0 | Q3: CSA | R3: UT | S3: =IFERROR(VLOOKUP(Tabela1[[#This Row],[CC]],CC!$A$1:$H$403,8,0),"") -> OP2
A4: 1390 | B4: =IFERROR(VLOOKUP(Tabela1[[#This Row],[CC]],#REF!,5,0),"") | C4: JOSÉ NETO COELHO | D4: OI | E4: OI - DIGITAL SUPORT (1390) | F4: SERVIÇO | G4: 1179 | H4: 45566 | I4: 184286.01 | J4: 162816.69 | K4: 45609 | L4: 45677 | M4: 45679 | N4: PAGO | O4: 0 | Q4: CSA | R4: UT | S4: =IFERROR(VLOOKUP(Tabela1[[#This Row],[CC]],CC!$A$1:$H$403,8,0),"") -> OP2
A5: 1390 | B5: =IFERROR(VLOOKUP(Tabela1[[#This Row],[CC]],#REF!,5,0),"") | C5: JOSÉ NETO COELHO | D5: OI | E5: OI - DIGITAL SUPORT (1390) | F5: SERVIÇO | G5: 1195 | H5: 45597 | I5: 184286.01 | J5: 162816.69 | K5: 45637 | L5: 45698 | M5: 45698 | N5: PAGO | O5: 0 | Q5: CSA | R5: UT | S5: =IFERROR(VLOOKUP(Tabela1[[#This Row],[CC]],CC!$A$1:$H$403,8,0),"") -> OP2
A6: 1390 | B6: =IFERROR(VLOOKUP(Tabela1[[#This Row],[CC]],#REF!,5,0),"") | C6: JOSÉ NETO COELHO | D6: OI | E6: OI - DIGITAL SUPORT (1390) | F6: SERVIÇO | G6: 652 | H6: 44927 | I6: 33803.85 | J6: 32301.82 | K6: 44973 | L6: 45705 | M6: 45709 | N6: PAGO | O6: 0 | Q6: CSA | R6: UT | S6: =IFERROR(VLOOKUP(Tabela1[[#This Row],[CC]],CC!$A$1:$H$403,8,0),"") -> OP2 | T6: SIM | U6: RECUPERAÇÃO JUDICIAL
A7: 1390 | B7: =IFERROR(VLOOKUP(Tabela1[[#This Row],[CC]],#REF!,5,0),"") | C7: JOSÉ NETO COELHO | D7: OI | E7: OI - DIGITAL SUPORT (1390) | F7: SERVIÇO | G7: 652 | H7: 44927 | I7: 33803.85 | J7: 32301.82 | K7: 44973 | L7: 45733 | M7: 45736 | N7: PAGO | O7: 0 | Q7: CSA | R7: UT | S7: =IFERROR(VLOOKUP(Tabela1[[#This Row],[CC]],CC!$A$1:$H$403,8,0),"") -> OP2 | T7: SIM | U7: RECUPERAÇÃO JUDICIAL
A8: 1390 | B8: =IFERROR(VLOOKUP(Tabela1[[#This Row],[CC]],#REF!,5,0),"") | C8: JOSÉ NETO COELHO | D8: OI | E8: OI - DIGITAL SUPORT (1390) | F8: SERVIÇO | G8: 652 | H8: 44927 | I8: 33803.85 | J8: 32301.82 | K8: 44973 | L8: 45768 | M8: 45769 | N8: PAGO | O8: 0 | Q8: CSA | R8: UT | S8: =IFERROR(VLOOKUP(Tabela1[[#This Row],[CC]],CC!$A$1:$H$403,8,0),"") -> OP2 | T8: SIM | U8: RECUPERAÇÃO JUDICIAL
A9: 1390 | B9: =IFERROR(VLOOKUP(Tabela1[[#This Row],[CC]],#REF!,5,0),"") | C9: JOSÉ NETO COELHO | D9: OI | E9: OI - DIGITAL SUPORT (1390) | F9: SERVIÇO | G9: 652 | H9: 44927 | I9: 33803.85 | J9: 32301.82 | K9: 44973 | L9: 45796 | M9: 45798 | N9: PAGO | Q9: CSA | R9: UT | S9: =IFERROR(VLOOKUP(Tabela1[[#This Row],[CC]],CC!$A$1:$H$403,8,0),"") -> OP2 | T9: SIM | U9: RECUPERAÇÃO JUDICIAL
A10: 1398 | B10: =IFERROR(VLOOKUP(Tabela1[[#This Row],[CC]],#REF!,5,0),"") | C10: EVANDRO BRAGA | D10: COMPASS | E10: COMPASS (1398) | F10: SERVIÇO | G10: 8397 | H10: 45778 | I10: 275.56 | J10: 258.62 | K10: 45835 | L10: 45964 | M10: 45968 | N10: PAGO | O10: 0 | Q10: CSA | R10: UT | S10: =IFERROR(VLOOKUP(Tabela1[[#This Row],[CC]],CC!$A$1:$H$403,8,0),"") -> OP2
A11: 1398 | B11: =IFERROR(VLOOKUP(Tabela1[[#This Row],[CC]],#REF!,5,0),"") | C11: EVANDRO BRAGA | D11: COMPASS | E11: COMPASS (1398) | F11: SERVIÇO | G11: 8506 | H11: 45839 | I11: 75919.81 | J11: 71250.74 | K11: 45909 | L11: 45971 | M11: 45971 | N11: PAGO | O11: 0 | Q11: CSA | R11: UT | S11: =IFERROR(VLOOKUP(Tabela1[[#This Row],[CC]],CC!$A$1:$H$403,8,0),"") -> OP2
A12: 1398 | B12: =IFERROR(VLOOKUP(Tabela1[[#This Row],[CC]],#REF!,5,0),"") | C12: EVANDRO BRAGA | D12: COMPASS | E12: COMPASS (1398) | F12: SERVIÇO | G12: 8566 | H12: 45839 | I12: 22241.65 | J12: 20873.79 | K12: 45945 | L12: 45999 | M12: 46003 | N12: PAGO | O12: 0 | Q12: CSA | R12: UT | S12: =IFERROR(VLOOKUP(Tabela1[[#This Row],[CC]],CC!$A$1:$H$403,8,0),"") -> OP2
A13: 1398 | B13: =IFERROR(VLOOKUP(Tabela1[[#This Row],[CC]],#REF!,5,0),"") | C13: EVANDRO BRAGA | D13: COMPASS | E13: COMPASS (1398) | F13: SERVIÇO | G13: 8488 | H13: 45870 | I13: 48000 | J13: 45048 | K13: 45903 | L13: 45971 | M13: 45973 | N13: PAGO | O13: 0 | Q13: CSA | R13: UT | S13: =IFERROR(VLOOKUP(Tabela1[[#This Row],[CC]],CC!$A$1:$H$403,8,0),"") -> OP2
A14: 1398 | B14: =IFERROR(VLOOKUP(Tabela1[[#This Row],[CC]],#REF!,5,0),"") | C14: EVANDRO BRAGA | D14: COMPASS | E14: COMPASS (1398) | F14: SERVIÇO | G14: 8524 | H14: 45870 | I14: 75919.81 | J14: 71250.74 | K14: 45924 | L14: 45985 | M14: 45985 | N14: PAGO | O14: 0 | Q14: CSA | R14: UT | S14: =IFERROR(VLOOKUP(Tabela1[[#This Row],[CC]],CC!$A$1:$H$403,8,0),"") -> OP2
A15: 1398 | B15: =IFERROR(VLOOKUP(Tabela1[[#This Row],[CC]],#REF!,5,0),"") | C15: EVANDRO BRAGA | D15: COMPASS | E15: COMPASS (1398) | F15: SERVIÇO | G15: 8529 | H15: 45901 | I15: 48000 | J15: 45048 | K15: 45931 | L15: 45985 | M15: 45989 | N15: PAGO | O15: 0 | Q15: CSA | R15: UT | S15: =IFERROR(VLOOKUP(Tabela1[[#This Row],[CC]],CC!$A$1:$H$403,8,0),"") -> OP2
A16: 1390 | B16: =IFERROR(VLOOKUP(Tabela1[[#This Row],[CC]],#REF!,5,0),"") | C16: JOSÉ NETO COELHO | D16: OI | E16: OI - DIGITAL SUPORT (1390) | F16: SERVIÇO | G16: 1235 | H16: 45658 | I16: 191510.84 | J16: 169199.83 | K16: 45742 | L16: 45817 | M16: 45821 | N16: PAGO | O16: 0 | Q16: CSA | R16: UT | S16: =IFERROR(VLOOKUP(Tabela1[[#This Row],[CC]],CC!$A$1:$H$403,8,0),"") -> OP2
A17: 1455 | B17: =IFERROR(VLOOKUP(Tabela1[[#This Row],[CC]],#REF!,5,0),"") | C17: ROGERIO GORDILHO | D17: ATAKAREJO | E17: ATAKAREJO N3 (1455) | F17: SERVIÇO | G17: 1193 | H17: 45566 | I17: 3744 | J17: 3307.82 | K17: 45635 | L17: 45663 | M17: 45667 | N17: PAGO | O17: 0 | Q17: CSA | R17: MS | S17: =IFERROR(VLOOKUP(Tabela1[[#This Row],[CC]],CC!$A$1:$H$403,8,0),"") -> OP4
A18: 1398 | B18: =IFERROR(VLOOKUP(Tabela1[[#This Row],[CC]],#REF!,5,0),"") | C18: EVANDRO BRAGA | D18: COMPASS | E18: COMPASS (1398) | F18: SERVIÇO | G18: 8081 | H18: 45566 | I18: 36914.53 | J18: 34726.4 | K18: 45602 | L18: 45663 | M18: 45663 | N18: PAGO | O18: 0 | Q18: CSA | R18: UT | S18: =IFERROR(VLOOKUP(Tabela1[[#This Row],[CC]],CC!$A$1:$H$403,8,0),"") -> OP2
A19: 1398 | B19: =IFERROR(VLOOKUP(Tabela1[[#This Row],[CC]],#REF!,5,0),"") | C19: EVANDRO BRAGA | D19: COMPASS | E19: COMPASS (1398) | F19: SERVIÇO | G19: 8082 | H19: 45566 | I19: 11210.79 | J19: 10521.33 | K19: 45602 | L19: 45663 | M19: 45663 | N19: PAGO | O19: 0 | Q19: CSA | R19: UT | S19: =IFERROR(VLOOKUP(Tabela1[[#This Row],[CC]],CC!$A$1:$H$403,8,0),"") -> OP2
A20: 1398 | B20: =IFERROR(VLOOKUP(Tabela1[[#This Row],[CC]],#REF!,5,0),"") | C20: EVANDRO BRAGA | D20: COMPASS | E20: COMPASS (1398) | F20: SERVIÇO | G20: 8117 | H20: 45566 | I20: 13110.33 | J20: 12304.05 | K20: 45631 | L20: 45684 | M20: 45687 | N20: PAGO | O20: 0 | Q20: CSA | R20: UT | S20: =IFERROR(VLOOKUP(Tabela1[[#This Row],[CC]],CC!$A$1:$H$403,8,0),"") -> OP2
A21: 1398 | B21: =IFERROR(VLOOKUP(Tabela1[[#This Row],[CC]],#REF!,5,0),"") | C21: EVANDRO BRAGA | D21: COMPASS | E21: COMPASS (1398) | F21: SERVIÇO | G21: 8537 | H21: 45901 | I21: 26093.54 | J21: 24488.79 | K21: 45932 | L21: 45964 | M21: 45964 | N21: PAGO | O21: 0 | Q21: CSA | R21: UT | S21: =IFERROR(VLOOKUP(Tabela1[[#This Row],[CC]],CC!$A$1:$H$403,8,0),"") -> OP2
... A30: 1300 | B30: =IFERROR(VLOOKUP(Tabela1[[#This Row],[CC]],#REF!,5,0),"") | C30: JOSÉ NETO COELHO | D30: AXIA | E30: ELETROBRAS RS NOVO (1300) | F30: SERVIÇO | G30: 1200 | H30: 45597 | I30: 305213.15 | J30: 275760.08 | K30: 45642 | L30: 45670 | M30: 45672 | N30: PAGO | O30: 0 | Q30: CSA | R30: UT | S30: =IFERROR(VLOOKUP(Tabela1[[#This Row],[CC]],CC!$A$1:$H$403,8,0),"") -> OP2
A31: 1378 | B31: =IFERROR(VLOOKUP(Tabela1[[#This Row],[CC]],#REF!,5,0),"") | C31: RODRIGO CORUMBA | D31: FUNCEF | E31: SF – FUNCEF (1378) | F31: SERVIÇO | G31: 8160 | H31: 45597 | I31: 4281.29 | J31: 4017.99 | K31: 45643 | L31: 45663 | M31: 45666 | N31: PAGO | O31: 0 | Q31: BPS | R31: FS | S31: =IFERROR(VLOOKUP(Tabela1[[#This Row],[CC]],CC!$A$1:$H$403,8,0),"") -> OP2 | T31: SIM | U31: FATURADO - A RECEBER
A32: 1390 | B32: =IFERROR(VLOOKUP(Tabela1[[#This Row],[CC]],#REF!,5,0),"") | C32: JOSÉ NETO COELHO | D32: OI | E32: OI - DIGITAL SUPORT (1390) | F32: SERVIÇO | G32: 1252 | H32: 45689 | I32: 8840 | J32: 7810.14 | K32: 45791 | L32: 45852 | M32: 45855 | N32: PAGO | O32: 0 | Q32: CSA | R32: UT | S32: =IFERROR(VLOOKUP(Tabela1[[#This Row],[CC]],CC!$A$1:$H$403,8,0),"") -> OP2
A33: 1481 | B33: =IFERROR(VLOOKUP(Tabela1[[#This Row],[CC]],#REF!,5,0),"") | C33: RODRIGO CORUMBA | D33: SANTANDER | E33: SANTANDER ESFERA (1481) | F33: SERVIÇO | G33: 3728 | H33: 45597 | I33: 75283.92 | J33: 70653.96 | K33: 45642 | L33: 45663 | M33: 45667 | N33: PAGO | O33: 0 | Q33: ADS | R33: FS | S33: =IFERROR(VLOOKUP(Tabela1[[#This Row],[CC]],CC!$A$1:$H$403,8,0),"") -> OP2
A34: 1394 | B34: =IFERROR(VLOOKUP(Tabela1[[#This Row],[CC]],#REF!,5,0),"") | C34: ANTONIO ALVES | D34: SEFAZ_BA | E34: SEFAZ - BA DIGITAL CENTER (1394) | F34: SERVIÇO | G34: 8394 | H34: 45597 | I34: 52020 | J34: 48482.64 | K34: 45834 | L34: 45859 | M34: 45863 | N34: PAGO | Q34: CSA | R34: PS | S34: =IFERROR(VLOOKUP(Tabela1[[#This Row],[CC]],CC!$A$1:$H$403,8,0),"") -> OP4 | T34: Não existe
A35: 1394 | B35: =IFERROR(VLOOKUP(Tabela1[[#This Row],[CC]],#REF!,5,0),"") | C35: ANTONIO ALVES | D35: SEFAZ_BA | E35: SEFAZ - BA DIGITAL CENTER (1394) | F35: SERVIÇO | G35: 8395 | H35: 45597 | I35: 173413.32 | J35: 161621.21 | K35: 45834 | L35: 45873 | M35: 45875 | N35: PAGO | Q35: CSA | R35: PS | S35: =IFERROR(VLOOKUP(Tabela1[[#This Row],[CC]],CC!$A$1:$H$403,8,0),"") -> OP4 | T35: Não existe
A36: 1394 | B36: =IFERROR(VLOOKUP(Tabela1[[#This Row],[CC]],#REF!,5,0),"") | C36: ANTONIO ALVES | D36: SEFAZ_BA | E36: SEFAZ - BA DIGITAL CENTER (1394) | F36: SERVIÇO | G36: 8402 | H36: 45597 | I36: 77551.97 | J36: 72278.44 | K36: 45839 | L36: 45859 | M36: 45861 | N36: PAGO | Q36: CSA | R36: PS | S36: =IFERROR(VLOOKUP(Tabela1[[#This Row],[CC]],CC!$A$1:$H$403,8,0),"") -> OP4 | T36: Não existe
A37: 1394 | B37: =IFERROR(VLOOKUP(Tabela1[[#This Row],[CC]],#REF!,5,0),"") | C37: ANTONIO ALVES | D37: SEFAZ_BA | E37: SEFAZ - BA DIGITAL CENTER (1394) | F37: SERVIÇO | G37: 8404 | H37: 45597 | I37: 123.48 | J37: 115.08 | K37: 45839 | L37: 45866 | M37: 45867 | N37: PAGO | Q37: CSA | R37: PS | S37: =IFERROR(VLOOKUP(Tabela1[[#This Row],[CC]],CC!$A$1:$H$403,8,0),"") -> OP4 | T37: Não existe
A38: 1394 | B38: =IFERROR(VLOOKUP(Tabela1[[#This Row],[CC]],#REF!,5,0),"") | C38: ANTONIO ALVES | D38: SEFAZ_BA | E38: SEFAZ - BA DIGITAL CENTER (1394) | F38: SERVIÇO | G38: 8420 | H38: 45597 | I38: 47838.29 | J38: 44585.28 | K38: 45848 | L38: 45866 | M38: 45868 | N38: PAGO | Q38: CSA | R38: PS | S38: =IFERROR(VLOOKUP(Tabela1[[#This Row],[CC]],CC!$A$1:$H$403,8,0),"") -> OP4 | T38: Não existe
A39: 1394 | B39: =IFERROR(VLOOKUP(Tabela1[[#This Row],[CC]],#REF!,5,0),"") | C39: ANTONIO ALVES | D39: SEFAZ_BA | E39: SEFAZ - BA DIGITAL CENTER (1394) | F39: SERVIÇO | G39: 8421 | H39: 45597 | I39: 68299.32 | J39: 63654.96 | K39: 45849 | L39: 45870 | M39: 45870 | N39: PAGO | Q39: CSA | R39: PS | S39: =IFERROR(VLOOKUP(Tabela1[[#This Row],[CC]],CC!$A$1:$H$403,8,0),"") -> OP4 | T39: Não existe
A40: 1394 | B40: =IFERROR(VLOOKUP(Tabela1[[#This Row],[CC]],#REF!,5,0),"") | C40: ANTONIO ALVES | D40: SEFAZ_BA | E40: SEFAZ - BA DIGITAL CENTER (1394) | F40: SERVIÇO | G40: 8434 | H40: 45597 | I40: 96756.27 | J40: 90176.84 | K40: 45855 | L40: 45866 | M40: 45869 | N40: PAGO | Q40: CSA | R40: PS | S40: =IFERROR(VLOOKUP(Tabela1[[#This Row],[CC]],CC!$A$1:$H$403,8,0),"") -> OP4 | T40: Não existe
A41: 1394 | B41: =IFERROR(VLOOKUP(Tabela1[[#This Row],[CC]],#REF!,5,0),"") | C41: ANTONIO ALVES | D41: SEFAZ_BA | E41: SEFAZ - BA DIGITAL CENTER (1394) | F41: SERVIÇO | G41: 8438 | H41: 45597 | I41: 135430.28 | J41: 126221.02 | K41: 45859 | L41: 45887 | M41: 45887 | N41: PAGO | Q41: CSA | R41: PS | S41: =IFERROR(VLOOKUP(Tabela1[[#This Row],[CC]],CC!$A$1:$H$403,8,0),"") -> OP4 | T41: Não existe
A42: 1394 | B42: =IFERROR(VLOOKUP(Tabela1[[#This Row],[CC]],#REF!,5,0),"") | C42: ANTONIO ALVES | D42: SEFAZ_BA | E42: SEFAZ - BA DIGITAL CENTER (1394) | F42: SERVIÇO | G42: 8436 | H42: 45597 | I42: 10692.26 | J42: 9965.18 | K42: 45856 | L42: 45873 | M42: 45875 | N42: PAGO | O42: 0 | Q42: CSA | R42: PS | S42: =IFERROR(VLOOKUP(Tabela1[[#This Row],[CC]],CC!$A$1:$H$403,8,0),"") -> OP4
A43: 1360 | B43: =IFERROR(VLOOKUP(Tabela1[[#This Row],[CC]],#REF!,5,0),"") | C43: RITA ANDRADE | D43: SERASA | E43: SERASA EXPERIAN (1360) | F43: SERVIÇO | G43: 3731 | H43: 45597 | I43: 24312.4 | J43: 22817.19 | K43: 45644 | L43: 45698 | M43: 45700 | N43: PAGO | Q43: ADS | R43: FS | S43: =IFERROR(VLOOKUP(Tabela1[[#This Row],[CC]],CC!$A$1:$H$403,8,0),"") -> OP1
A44: 1483 | B44: =IFERROR(VLOOKUP(Tabela1[[#This Row],[CC]],#REF!,5,0),"") | C44: EVANDRO BRAGA | D44: UNIPAR | E44: UNIPAR (1483) | F44: SERVIÇO | G44: 8164 | H44: 45597 | I44: 28856.8 | J44: 26062.11 | K44: 45645 | L44: 45719 | M44: 45722 | N44: PAGO | O44: 0 | Q44: CSA | R44: UT | S44: =IFERROR(VLOOKUP(Tabela1[[#This Row],[CC]],CC!$A$1:$H$403,8,0),"") -> OP2
A45: 1483 | B45: =IFERROR(VLOOKUP(Tabela1[[#This Row],[CC]],#REF!,5,0),"") | C45: EVANDRO BRAGA | D45: UNIPAR | E45: UNIPAR (1483) | F45: SERVIÇO | G45: 8165 | H45: 45597 | I45: 53591.2 | J45: 48300.35 | K45: 45646 | L45: 45719 | M45: 45722 | N45: PAGO | O45: 0 | Q45: CSA | R45: UT | S45: =IFERROR(VLOOKUP(Tabela1[[#This Row],[CC]],CC!$A$1:$H$403,8,0),"") -> OP2
A46: 1455 | B46: =IFERROR(VLOOKUP(Tabela1[[#This Row],[CC]],#REF!,5,0),"") | C46: ROGERIO GORDILHO | D46: ATAKAREJO | E46: ATAKAREJO N3 (1455) | F46: SERVIÇO | G46: 1203 | H46: 45627 | I46: 54003.39 | J46: 47712 | K46: 45659 | L46: 45684 | M46: 45688 | N46: PAGO | Q46: CSA | R46: MS | S46: =IFERROR(VLOOKUP(Tabela1[[#This Row],[CC]],CC!$A$1:$H$403,8,0),"") -> OP4
A47: 1455 | B47: =IFERROR(VLOOKUP(Tabela1[[#This Row],[CC]],#REF!,5,0),"") | C47: ROGERIO GORDILHO | D47: ATAKAREJO | E47: ATAKAREJO N3 (1455) | F47: SERVIÇO | G47: 1205 | H47: 45627 | I47: 2857.25 | J47: 2524.38 | K47: 45663 | L47: 45684 | M47: 45688 | N47: PAGO | Q47: CSA | R47: MS | S47: =IFERROR(VLOOKUP(Tabela1[[#This Row],[CC]],CC!$A$1:$H$403,8,0),"") -> OP4
A48: 1455 | B48: =IFERROR(VLOOKUP(Tabela1[[#This Row],[CC]],#REF!,5,0),"") | C48: ROGERIO GORDILHO | D48: ATAKAREJO | E48: ATAKAREJO N3 (1455) | F48: SERVIÇO | G48: 1204 | H48: 45627 | I48: 2418 | J48: 2136.3 | K48: 45663 | L48: 45684 | M48: 45688 | N48: PAGO | Q48: CSA | R48: MS | S48: =IFERROR(VLOOKUP(Tabela1[[#This Row],[CC]],CC!$A$1:$H$403,8,0),"") -> OP4
A49: 1455 | B49: =IFERROR(VLOOKUP(Tabela1[[#This Row],[CC]],#REF!,5,0),"") | C49: ROGERIO GORDILHO | D49: ATAKAREJO | E49: ATAKAREJO N3 (1455) | F49: SERVIÇO | G49: 8273 | H49: 45627 | I49: 54003.39 | J49: 47712 | K49: 45748 | L49: 45775 | M49: 45777 | N49: PAGO | Q49: CSA | R49: MS | S49: =IFERROR(VLOOKUP(Tabela1[[#This Row],[CC]],CC!$A$1:$H$403,8,0),"") -> OP4
A50: 1478 | B50: =IFERROR(VLOOKUP(Tabela1[[#This Row],[CC]],#REF!,5,0),"") | C50: RITA ANDRADE | D50: VOTORANTIM | E50: BANKLY (ADS) (1478) | F50: SERVIÇO | G50: 8167 | H50: 45627 | I50: 231360 | J50: 217131.36 | K50: 45659 | L50: 45663 | M50: 45667 | N50: PAGO | Q50: ADS | R50: FS | S50: =IFERROR(VLOOKUP(Tabela1[[#This Row],[CC]],CC!$A$1:$H$403,8,0),"") -> OP1
A51: 1391 | B51: =IFERROR(VLOOKUP(Tabela1[[#This Row],[CC]],#REF!,5,0),"") | C51: RITA ANDRADE | D51: BRADESCO | E51: BRADESCO - DS (1391) | F51: SERVIÇO | G51: 3740 | H51: 45627 | I51: 125126.52 | J51: 117431.24 | K51: 45665 | L51: 45677 | M51: 45680 | N51: PAGO | Q51: ADS | R51: FS | S51: =IFERROR(VLOOKUP(Tabela1[[#This Row],[CC]],CC!$A$1:$H$403,8,0),"") -> OP1
A52: 1391 | B52: =IFERROR(VLOOKUP(Tabela1[[#This Row],[CC]],#REF!,5,0),"") | C52: RITA ANDRADE | D52: BRADESCO | E52: BRADESCO - DS (1391) | F52: SERVIÇO | G52: 3742 | H52: 45627 | I52: 101943.56 | J52: 95674.03 | K52: 45665 | L52: 45677 | M52: 45680 | N52: PAGO | Q52: ADS | R52: FS | S52: =IFERROR(VLOOKUP(Tabela1[[#This Row],[CC]],CC!$A$1:$H$403,8,0),"") -> OP1
A53: 1391 | B53: =IFERROR(VLOOKUP(Tabela1[[#This Row],[CC]],#REF!,5,0),"") | C53: RITA ANDRADE | D53: BRADESCO | E53: BRADESCO - DS (1391) | F53: SERVIÇO | G53: 3743 | H53: 45627 | I53: 221873.85 | J53: 208228.61 | K53: 45665 | L53: 45677 | M53: 45680 | N53: PAGO | Q53: ADS | R53: FS | S53: =IFERROR(VLOOKUP(Tabela1[[#This Row],[CC]],CC!$A$1:$H$403,8,0),"") -> OP1
A54: 1391 | B54: =IFERROR(VLOOKUP(Tabela1[[#This Row],[CC]],#REF!,5,0),"") | C54: RITA ANDRADE | D54: BRADESCO | E54: BRADESCO - DS (1391) | F54: SERVIÇO | G54: 3744 | H54: 45627 | I54: 73997.55 | J54: 69446.7 | K54: 45665 | L54: 45677 | M54: 45680 | N54: PAGO | Q54: ADS | R54: FS | S54: =IFERROR(VLOOKUP(Tabela1[[#This Row],[CC]],CC!$A$1:$H$403,8,0),"") -> OP1
A55: 1294 | B55: =IFERROR(VLOOKUP(Tabela1[[#This Row],[CC]],#REF!,5,0),"") | C55: RITA ANDRADE | D55: BRADESCO | E55: BRADESCO - DS 2 (1294) | F55: SERVIÇO | G55: 3741 | H55: 45627 | I55: 32371.04 | J55: 30380.22 | K55: 45665 | L55: 45677 | M55: 45680 | N55: PAGO | O55: 0 | Q55: ADS | R55: FS | S55: =IFERROR(VLOOKUP(Tabela1[[#This Row],[CC]],CC!$A$1:$H$403,8,0),"") -> OP1
A56: 1294 | B56: =IFERROR(VLOOKUP(Tabela1[[#This Row],[CC]],#REF!,5,0),"") | C56: RITA ANDRADE | D56: BRADESCO | E56: BRADESCO - DS 2 (1294) | F56: SERVIÇO | G56: 3747 | H56: 45627 | I56: 106153.74 | J56: 99625.28 | K56: 45667 | L56: 45684 | M56: 45684 | N56: PAGO | O56: 0 | Q56: ADS | R56: FS | S56: =IFERROR(VLOOKUP(Tabela1[[#This Row],[CC]],CC!$A$1:$H$403,8,0),"") -> OP1
A57: 1294 | B57: =IFERROR(VLOOKUP(Tabela1[[#This Row],[CC]],#REF!,5,0),"") | C57: RITA ANDRADE | D57: BRADESCO | E57: BRADESCO - DS 2 (1294) | F57: SERVIÇO | G57: 3746 | H57: 45627 | I57: 232263.03 | J57: 217978.85 | K57: 45667 | L57: 45684 | M57: 45684 | N57: PAGO | O57: 0 | Q57: ADS | R57: FS | S57: =IFERROR(VLOOKUP(Tabela1[[#This Row],[CC]],CC!$A$1:$H$403,8,0),"") -> OP1
A58: 1474 | B58: =IFERROR(VLOOKUP(Tabela1[[#This Row],[CC]],#REF!,5,0),"") | C58: RITA ANDRADE | D58: BRADESCO | E58: BRADESCO DS2 (CSA) (1474) | F58: SERVIÇO | G58: 3748 | H58: 45627 | I58: 18741.33 | J58: 17588.74 | K58: 45667 | L58: 45684 | M58: 45684 | N58: PAGO | Q58: CSA | R58: FS | S58: =IFERROR(VLOOKUP(Tabela1[[#This Row],[CC]],CC!$A$1:$H$403,8,0),"") -> OP1
A59: 1285 | B59: =IFERROR(VLOOKUP(Tabela1[[#This Row],[CC]],#REF!,5,0),"") | C59: RITA ANDRADE | D59: BRADESCO | E59: BRADESCO - EXPERIENCE (1285) | F59: SERVIÇO | G59: 3733 | H59: 45627 | I59: 24926.36 | J59: 23393.38 | K59: 45652 | L59: 45684 | M59: 45684 | N59: PAGO | O59: 0 | Q59: ADS | R59: FS | S59: =IFERROR(VLOOKUP(Tabela1[[#This Row],[CC]],CC!$A$1:$H$403,8,0),"") -> OP1
A60: 1285 | B60: =IFERROR(VLOOKUP(Tabela1[[#This Row],[CC]],#REF!,5,0),"") | C60: RITA ANDRADE | D60: BRADESCO | E60: BRADESCO - EXPERIENCE (1285) | F60: SERVIÇO | G60: 3734 | H60: 45627 | I60: 18108.12 | J60: 16994.47 | K60: 45653 | L60: 45684 | M60: 45684 | N60: PAGO | O60: 0 | Q60: ADS | R60: FS | S60: =IFERROR(VLOOKUP(Tabela1[[#This Row],[CC]],CC!$A$1:$H$403,8,0),"") -> OP1
A61: 1285 | B61: =IFERROR(VLOOKUP(Tabela1[[#This Row],[CC]],#REF!,5,0),"") | C61: RITA ANDRADE | D61: BRADESCO | E61: BRADESCO - EXPERIENCE (1285) | F61: SERVIÇO | G61: 3735 | H61: 45627 | I61: 5998.84 | J61: 5629.91 | K61: 45653 | L61: 45684 | M61: 45684 | N61: PAGO | O61: 0 | Q61: ADS | R61: FS | S61: =IFERROR(VLOOKUP(Tabela1[[#This Row],[CC]],CC!$A$1:$H$403,8,0),"") -> OP1
A62: 1292 | B62: =IFERROR(VLOOKUP(Tabela1[[#This Row],[CC]],#REF!,5,0),"") | C62: RITA ANDRADE | D62: BRADESCO_SEGUROS | E62: BRADESCO - SEGUROS (1292) | F62: SERVIÇO | G62: 3750 | H62: 45627 | I62: 21201.52 | J62: 19897.63 | K62: 45678 | L62: 45691 | M62: 45693 | N62: PAGO | O62: 0 | Q62: ADS | R62: FS | S62: =IFERROR(VLOOKUP(Tabela1[[#This Row],[CC]],CC!$A$1:$H$403,8,0),"") -> OP1
A63: 1292 | B63: =IFERROR(VLOOKUP(Tabela1[[#This Row],[CC]],#REF!,5,0),"") | C63: RITA ANDRADE | D63: BRADESCO_SEGUROS | E63: BRADESCO - SEGUROS (1292) | F63: SERVIÇO | G63: 3749 | H63: 45627 | I63: 27461.04 | J63: 25772.18 | K63: 45678 | L63: 45691 | M63: 45693 | N63: PAGO | O63: 0 | Q63: ADS | R63: FS | S63: =IFERROR(VLOOKUP(Tabela1[[#This Row],[CC]],CC!$A$1:$H$403,8,0),"") -> OP1
A64: 1292 | B64: =IFERROR(VLOOKUP(Tabela1[[#This Row],[CC]],#REF!,5,0),"") | C64: RITA ANDRADE | D64: BRADESCO_SEGUROS | E64: BRADESCO - SEGUROS (1292) | F64: SERVIÇO | G64: 3793 | H64: 45627 | I64: 88281.31 | J64: 82852.01 | K64: 45694 | L64: 45712 | M64: 45714 | N64: PAGO | O64: 0 | Q64: ADS | R64: FS | S64: =IFERROR(VLOOKUP(Tabela1[[#This Row],[CC]],CC!$A$1:$H$403,8,0),"") -> OP1
A65: 1398 | B65: =IFERROR(VLOOKUP(Tabela1[[#This Row],[CC]],#REF!,5,0),"") | C65: EVANDRO BRAGA | D65: COMPASS | E65: COMPASS (1398) | F65: SERVIÇO | G65: 8170 | H65: 45627 | I65: 48000 | J65: 45048 | K65: 45663 | L65: 45684 | M65: 45688 | N65: PAGO | O65: 0 | Q65: CSA | R65: UT | S65: =IFERROR(VLOOKUP(Tabela1[[#This Row],[CC]],CC!$A$1:$H$403,8,0),"") -> OP2
A66: 1398 | B66: =IFERROR(VLOOKUP(Tabela1[[#This Row],[CC]],#REF!,5,0),"") | C66: EVANDRO BRAGA | D66: COMPASS | E66: COMPASS (1398) | F66: SERVIÇO | G66: 8148 | H66: 45627 | I66: 14880 | J66: 13964.88 | K66: 45637 | L66: 45698 | M66: 45698 | N66: PAGO | O66: 0 | Q66: CSA | R66: UT | S66: =IFERROR(VLOOKUP(Tabela1[[#This Row],[CC]],CC!$A$1:$H$403,8,0),"") -> OP2
A67: 1398 | B67: =IFERROR(VLOOKUP(Tabela1[[#This Row],[CC]],#REF!,5,0),"") | C67: EVANDRO BRAGA | D67: COMPASS | E67: COMPASS (1398) | F67: SERVIÇO | G67: 8182 | H67: 45627 | I67: 11210.79 | J67: 10521.33 | K67: 45673 | L67: 45733 | M67: 45733 | N67: PAGO | O67: 0 | Q67: CSA | R67: UT | S67: =IFERROR(VLOOKUP(Tabela1[[#This Row],[CC]],CC!$A$1:$H$403,8,0),"") -> OP2
A68: 1398 | B68: =IFERROR(VLOOKUP(Tabela1[[#This Row],[CC]],#REF!,5,0),"") | C68: EVANDRO BRAGA | D68: COMPASS | E68: COMPASS (1398) | F68: SERVIÇO | G68: 8184 | H68: 45627 | I68: 36914.53 | J68: 34726.4 | K68: 45674 | L68: 45733 | M68: 45734 | N68: PAGO | O68: 0 | Q68: CSA | R68: UT | S68: =IFERROR(VLOOKUP(Tabela1[[#This Row],[CC]],CC!$A$1:$H$403,8,0),"") -> OP2
A69: 1398 | B69: =IFERROR(VLOOKUP(Tabela1[[#This Row],[CC]],#REF!,5,0),"") | C69: EVANDRO BRAGA | D69: COMPASS | E69: COMPASS (1398) | F69: SERVIÇO | G69: 8185 | H69: 45627 | I69: 23241.33 | J69: 21811.99 | K69: 45674 | L69: 45733 | M69: 45734 | N69: PAGO | O69: 0 | Q69: CSA | R69: UT | S69: =IFERROR(VLOOKUP(Tabela1[[#This Row],[CC]],CC!$A$1:$H$403,8,0),"") -> OP2
A70: 1393 | B70: =IFERROR(VLOOKUP(Tabela1[[#This Row],[CC]],#REF!,5,0),"") | C70: ROGERIO GORDILHO | D70: DETRAN | E70: DETRAN - N3 (1393) | F70: SERVIÇO | G70: 8181 | H70: 45627 | I70: 432751.13 | J70: 388177.77 | K70: 45671 | L70: 45684 | M70: 45686 | N70: PAGO | O70: 0 | Q70: CSA | R70: PS | S70: =IFERROR(VLOOKUP(Tabela1[[#This Row],[CC]],CC!$A$1:$H$403,8,0),"") -> OP4
A71: 1476 | B71: =IFERROR(VLOOKUP(Tabela1[[#This Row],[CC]],#REF!,5,0),"") | C71: ROGERIO GORDILHO | D71: DPE | E71: DPE - BA Digital Center (1476) | F71: SERVIÇO | G71: 8173 | H71: 45627 | I71: 318628.4 | J71: 285809.68 | K71: 45665 | L71: 45691 | M71: 45694 | N71: PAGO | Q71: CSA | R71: PS | S71: =IFERROR(VLOOKUP(Tabela1[[#This Row],[CC]],CC!$A$1:$H$403,8,0),"") -> OP4
A72: 1300 | B72: =IFERROR(VLOOKUP(Tabela1[[#This Row],[CC]],#REF!,5,0),"") | C72: JOSÉ NETO COELHO | D72: AXIA | E72: ELETROBRAS RS NOVO (1300) | F72: SERVIÇO | G72: 1206 | H72: 45627 | I72: 269370.35 | J72: 243376.11 | K72: 45670 | L72: 45719 | M72: 45723 | N72: PAGO | O72: 0 | Q72: CSA | R72: UT | S72: =IFERROR(VLOOKUP(Tabela1[[#This Row],[CC]],CC!$A$1:$H$403,8,0),"") -> OP2
A73: 1300 | B73: =IFERROR(VLOOKUP(Tabela1[[#This Row],[CC]],#REF!,5,0),"") | C73: JOSÉ NETO COELHO | D73: AXIA | E73: ELETROBRAS RS NOVO (1300) | F73: SERVIÇO | G73: 8178 | H73: 45627 | I73: 35127.12 | J73: 31737.35 | K73: 45670 | L73: 45698 | M73: 45700 | N73: PAGO | O73: 0 | Q73: CSA | R73: UT | S73: =IFERROR(VLOOKUP(Tabela1[[#This Row],[CC]],CC!$A$1:$H$403,8,0),"") -> OP2
A74: 1290 | B74: =IFERROR(VLOOKUP(Tabela1[[#This Row],[CC]],#REF!,5,0),"") | C74: ROGERIO GORDILHO | D74: EMBASA | E74: EMBASA - NOVO (1290) | F74: SERVIÇO | G74: 8172 | H74: 45627 | I74: 53175.27 | J74: 46980.35 | K74: 45663 | L74: 45691 | M74: 45694 | N74: PAGO | O74: 0 | Q74: CSA | R74: UT | S74: =IFERROR(VLOOKUP(Tabela1[[#This Row],[CC]],CC!$A$1:$H$403,8,0),"") -> OP4
A75: 1475 | B75: =IFERROR(VLOOKUP(Tabela1[[#This Row],[CC]],#REF!,5,0),"") | C75: LIZANDRA PIMENTA | D75: FAPESB | E75: FAPESB Sustentação (1475) | F75: SERVIÇO | G75: 8179 | H75: 45627 | I75: 67387.39 | J75: 60446.49 | K75: 45670 | L75: 45684 | M75: 45687 | N75: PAGO | O75: 0 | Q75: ADS | R75: PS | S75: =IFERROR(VLOOKUP(Tabela1[[#This Row],[CC]],CC!$A$1:$H$403,8,0),"") -> OP3
A76: 1378 | B76: =IFERROR(VLOOKUP(Tabela1[[#This Row],[CC]],#REF!,5,0),"") | C76: RODRIGO CORUMBA | D76: FUNCEF | E76: SF – FUNCEF (1378) | F76: SERVIÇO | G76: 8183 | H76: 45627 | I76: 4281.29 | J76: 4017.99 | K76: 45674 | L76: 45691 | M76: 45695 | N76: PAGO | O76: 0 | Q76: BPS | R76: FS | S76: =IFERROR(VLOOKUP(Tabela1[[#This Row],[CC]],CC!$A$1:$H$403,8,0),"") -> OP2 | T76: SIM | U76: FATURADO - A RECEBER
A77: 1358 | B77: =IFERROR(VLOOKUP(Tabela1[[#This Row],[CC]],#REF!,5,0),"") | C77: ROGERIO GORDILHO | D77: INEMA | E77: INEMA N3 (1358) | F77: SERVIÇO | G77: 8174 | H77: 45627 | I77: 85164.92 | J77: 76392.93 | K77: 45667 | L77: 45698 | M77: 45702 | N77: PAGO | O77: 0 | Q77: CSA | R77: PS | S77: =IFERROR(VLOOKUP(Tabela1[[#This Row],[CC]],CC!$A$1:$H$403,8,0),"") -> OP4
A78: 1358 | B78: =IFERROR(VLOOKUP(Tabela1[[#This Row],[CC]],#REF!,5,0),"") | C78: ROGERIO GORDILHO | D78: INEMA | E78: INEMA N3 (1358) | F78: SERVIÇO | G78: 8175 | H78: 45627 | I78: 8209.93 | J78: 7364.3 | K78: 45670 | L78: 45705 | M78: 45709 | N78: PAGO | O78: 0 | Q78: CSA | R78: PS | S78: =IFERROR(VLOOKUP(Tabela1[[#This Row],[CC]],CC!$A$1:$H$403,8,0),"") -> OP4
A79: 1473 | B79: =IFERROR(VLOOKUP(Tabela1[[#This Row],[CC]],#REF!,5,0),"") | C79: ROGERIO GORDILHO | D79: MP_BA | E79: MP - BA I (1473) | F79: SERVIÇO | G79: 8217 | H79: 45627 | I79: 225527.76 | J79: 209685.41 | K79: 45702 | L79: 45712 | M79: 45716 | N79: PAGO | O79: 0 | Q79: CSA | R79: PS | S79: =IFERROR(VLOOKUP(Tabela1[[#This Row],[CC]],CC!$A$1:$H$403,8,0),"") -> OP4
A80: 1462 | B80: =IFERROR(VLOOKUP(Tabela1[[#This Row],[CC]],#REF!,5,0),"") | C80: EVANDRO BRAGA | D80: GAS_BRASILIANO | E80: GAS BRASILIANO (1462) | F80: SERVIÇO | G80: 8188 | H80: 45627 | I80: 800 | J80: 750.8 | K80: 45680 | L80: 45684 | M80: 45688 | N80: PAGO | O80: 0 | Q80: CSA | R80: MS | S80: =IFERROR(VLOOKUP(Tabela1[[#This Row],[CC]],CC!$A$1:$H$403,8,0),"") -> OP2
A81: 1390 | B81: =IFERROR(VLOOKUP(Tabela1[[#This Row],[CC]],#REF!,5,0),"") | C81: JOSÉ NETO COELHO | D81: OI | E81: OI - DIGITAL SUPORT (1390) | F81: SERVIÇO | G81: 1245 | H81: 45717 | I81: 156264.84 | J81: 138059.98 | K81: 45769 | L81: 45852 | M81: 45855 | N81: PAGO | O81: 0 | Q81: CSA | R81: UT | S81: =IFERROR(VLOOKUP(Tabela1[[#This Row],[CC]],CC!$A$1:$H$403,8,0),"") -> OP2
A82: 1260 | B82: =IFERROR(VLOOKUP(Tabela1[[#This Row],[CC]],#REF!,5,0),"") | C82: RODRIGO CORUMBA | D82: PETZ | E82: PETZ - ADS (1260) | F82: SERVIÇO | G82: 3745 | H82: 45627 | I82: 10395 | J82: 9755.7 | K82: 45667 | L82: 45684 | M82: 45686 | N82: PAGO | O82: 0 | Q82: ADS | R82: MS | S82: =IFERROR(VLOOKUP(Tabela1[[#This Row],[CC]],CC!$A$1:$H$403,8,0),"") -> OP2
A83: 1482 | B83: =IFERROR(VLOOKUP(Tabela1[[#This Row],[CC]],#REF!,5,0),"") | C83: JOSÉ NETO COELHO | D83: AXIA | E83: REAL GRANDEZA (1482) | F83: SERVIÇO | G83: 8168 | H83: 45627 | I83: 39000 | J83: 35236.5 | K83: 45660 | L83: 45677 | M83: 45680 | N83: PAGO | Q83: CSA | R83: UT | S83: =IFERROR(VLOOKUP(Tabela1[[#This Row],[CC]],CC!$A$1:$H$403,8,0),"") -> OP2
A84: 1262 | B84: =IFERROR(VLOOKUP(Tabela1[[#This Row],[CC]],#REF!,5,0),"") | C84: RODRIGO CORUMBA | D84: RENDIMENTO | E84: BANCO RENDIMENTO ADS (1262) | F84: SERVIÇO | G84: 3767 | H84: 45627 | I84: 8517.22 | J84: 7993.41 | K84: 45681 | L84: 45684 | M84: 45688 | N84: PAGO | O84: 0 | Q84: ADS | R84: FS | S84: =IFERROR(VLOOKUP(Tabela1[[#This Row],[CC]],CC!$A$1:$H$403,8,0),"") -> OP2
A85: 1262 | B85: =IFERROR(VLOOKUP(Tabela1[[#This Row],[CC]],#REF!,5,0),"") | C85: RODRIGO CORUMBA | D85: RENDIMENTO | E85: BANCO RENDIMENTO ADS (1262) | F85: SERVIÇO | G85: 3766 | H85: 45627 | I85: 19873.51 | J85: 18651.29 | K85: 45681 | L85: 45684 | M85: 45688 | N85: PAGO | O85: 0 | Q85: ADS | R85: FS | S85: =IFERROR(VLOOKUP(Tabela1[[#This Row],[CC]],CC!$A$1:$H$403,8,0),"") -> OP2
A86: 1262 | B86: =IFERROR(VLOOKUP(Tabela1[[#This Row],[CC]],#REF!,5,0),"") | C86: RODRIGO CORUMBA | D86: RENDIMENTO | E86: BANCO RENDIMENTO ADS (1262) | F86: SERVIÇO | G86: 3765 | H86: 45627 | I86: 57982.34 | J86: 54416.42 | K86: 45681 | L86: 45684 | M86: 45688 | N86: PAGO | O86: 0 | Q86: ADS | R86: FS | S86: =IFERROR(VLOOKUP(Tabela1[[#This Row],[CC]],CC!$A$1:$H$403,8,0),"") -> OP2
A87: 1269 | B87: =IFERROR(VLOOKUP(Tabela1[[#This Row],[CC]],#REF!,5,0),"") | C87: RODRIGO CORUMBA | D87: RENDIMENTO | E87: BANCO RENDIMENTO MONITORING CSA (1269) | F87: SERVIÇO | G87: 3763 | H87: 45627 | I87: 198578.23 | J87: 186365.67 | K87: 45681 | L87: 45684 | M87: 45688 | N87: PAGO | O87: 0 | Q87: CSA | R87: FS | S87: =IFERROR(VLOOKUP(Tabela1[[#This Row],[CC]],CC!$A$1:$H$403,8,0),"") -> OP2
A88: 1262 | B88: =IFERROR(VLOOKUP(Tabela1[[#This Row],[CC]],#REF!,5,0),"") | C88: RODRIGO CORUMBA | D88: RENDIMENTO | E88: BANCO RENDIMENTO ADS (1262) | F88: SERVIÇO | G88: 3762 | H88: 45627 | I88: 26442.98 | J88: 24816.74 | K88: 45681 | L88: 45684 | M88: 45688 | N88: PAGO | O88: 0 | Q88: ADS | R88: FS | S88: =IFERROR(VLOOKUP(Tabela1[[#This Row],[CC]],CC!$A$1:$H$403,8,0),"") -> OP2
A89: 1269 | B89: =IFERROR(VLOOKUP(Tabela1[[#This Row],[CC]],#REF!,5,0),"") | C89: RODRIGO CORUMBA | D89: RENDIMENTO | E89: BANCO RENDIMENTO MONITORING CSA (1269) | F89: SERVIÇO | G89: 3769 | H89: 45627 | I89: 6310.36 | J89: 5922.27 | K89: 45681 | L89: 45684 | M89: 45688 | N89: PAGO | O89: 0 | Q89: CSA | R89: FS | S89: =IFERROR(VLOOKUP(Tabela1[[#This Row],[CC]],CC!$A$1:$H$403,8,0),"") -> OP2
A90: 1269 | B90: =IFERROR(VLOOKUP(Tabela1[[#This Row],[CC]],#REF!,5,0),"") | C90: RODRIGO CORUMBA | D90: RENDIMENTO | E90: BANCO RENDIMENTO MONITORING CSA (1269) | F90: SERVIÇO | G90: 3768 | H90: 45627 | I90: 17033.4 | J90: 15985.85 | K90: 45681 | L90: 45684 | M90: 45688 | N90: PAGO | O90: 0 | Q90: CSA | R90: FS | S90: =IFERROR(VLOOKUP(Tabela1[[#This Row],[CC]],CC!$A$1:$H$403,8,0),"") -> OP2
A91: 1269 | B91: =IFERROR(VLOOKUP(Tabela1[[#This Row],[CC]],#REF!,5,0),"") | C91: RODRIGO CORUMBA | D91: RENDIMENTO | E91: BANCO RENDIMENTO MONITORING CSA (1269) | F91: SERVIÇO | G91: 3770 | H91: 45627 | I91: 22383.29 | J91: 21006.72 | K91: 45681 | L91: 45684 | M91: 45688 | N91: PAGO | O91: 0 | Q91: CSA | R91: FS | S91: =IFERROR(VLOOKUP(Tabela1[[#This Row],[CC]],CC!$A$1:$H$403,8,0),"") -> OP2
A92: 1269 | B92: =IFERROR(VLOOKUP(Tabela1[[#This Row],[CC]],#REF!,5,0),"") | C92: RODRIGO CORUMBA | D92: RENDIMENTO | E92: BANCO RENDIMENTO MONITORING CSA (1269) | F92: SERVIÇO | G92: 3764 | H92: 45627 | I92: 18775.89 | J92: 17621.17 | K92: 45681 | L92: 45684 | M92: 45688 | N92: PAGO | O92: 0 | Q92: CSA | R92: FS | S92: =IFERROR(VLOOKUP(Tabela1[[#This Row],[CC]],CC!$A$1:$H$403,8,0),"") -> OP2
A93: 1400 | B93: =IFERROR(VLOOKUP(Tabela1[[#This Row],[CC]],#REF!,5,0),"") | C93: CYRO SALVATORE | D93: SABESP | E93: SABESP - MICROSOFT NOVO (1400) | F93: SERVIÇO | G93: 8198 | H93: 45627 | I93: 77751.44 | J93: 70248.43 | K93: 45691 | L93: 45705 | M93: 45708 | N93: PAGO | O93: 0 | Q93: ADS | R93: UT | S93: =IFERROR(VLOOKUP(Tabela1[[#This Row],[CC]],CC!$A$1:$H$403,8,0),"") -> OP1
A94: 1400 | B94: =IFERROR(VLOOKUP(Tabela1[[#This Row],[CC]],#REF!,5,0),"") | C94: CYRO SALVATORE | D94: SABESP | E94: SABESP - MICROSOFT NOVO (1400) | F94: SERVIÇO | G94: 8197 | H94: 45627 | I94: 765030.98 | J94: 691205.5 | K94: 45691 | L94: 45705 | M94: 45708 | N94: PAGO | O94: 0 | Q94: ADS | R94: UT | S94: =IFERROR(VLOOKUP(Tabela1[[#This Row],[CC]],CC!$A$1:$H$403,8,0),"") -> OP1
A95: 1366 | B95: =IFERROR(VLOOKUP(Tabela1[[#This Row],[CC]],#REF!,5,0),"") | C95: CYRO SALVATORE | D95: SABESP | E95: SABESP - SD (1366) | F95: SERVIÇO | G95: 1208 | H95: 45627 | I95: 347182.07 | J95: 313678.94 | K95: 45677 | L95: 45684 | M95: 45688 | N95: PAGO | O95: 0 | Q95: CSA | R95: UT | S95: =IFERROR(VLOOKUP(Tabela1[[#This Row],[CC]],CC!$A$1:$H$403,8,0),"") -> OP1
... A98: 1481 | B98: =IFERROR(VLOOKUP(Tabela1[[#This Row],[CC]],#REF!,5,0),"") | C98: RODRIGO CORUMBA | D98: SANTANDER | E98: SANTANDER ESFERA (1481) | F98: SERVIÇO | G98: 3822 | H98: 45627 | I98: 107000 | J98: 100419.5 | K98: 45702 | L98: 45726 | M98: 45727 | N98: PAGO | O98: 0 | Q98: ADS | R98: FS | S98: =IFERROR(VLOOKUP(Tabela1[[#This Row],[CC]],CC!$A$1:$H$403,8,0),"") -> OP2
A99: 1298 | B99: =IFERROR(VLOOKUP(Tabela1[[#This Row],[CC]],#REF!,5,0),"") | C99: =IFERROR(VLOOKUP(Tabela1[[#This Row],[CC]],CC!$A$1:$H$389,7,0),"") -> JOSÉ NETO | D99: SEBRAE | E99: SEBRAE-SP DC NOVO (1298) | F99: SERVIÇO | G99: 1207 | H99: 45627 | I99: 275594.29 | J99: 258645.25 | K99: 45674 | L99: 45684 | M99: 45688 | N99: PAGO | O99: 0 | Q99: CSA | R99: PS | S99: =IFERROR(VLOOKUP(Tabela1[[#This Row],[CC]],CC!$A$1:$H$403,8,0),"") -> OP2
A100: 1289 | B100: =IFERROR(VLOOKUP(Tabela1[[#This Row],[CC]],#REF!,5,0),"") | C100: LIZANDRA PIMENTA | D100: SEC-BA | E100: SEC N3 NOVO (1289) | F100: SERVIÇO | G100: 8187 | H100: 45627 | I100: 176197.18 | J100: 164215.78 | K100: 45680 | L100: 45691 | M100: 45693 | N100: PAGO | O100: 0 | Q100: CSA | R100: PS | S100: =IFERROR(VLOOKUP(Tabela1[[#This Row],[CC]],CC!$A$1:$H$403,8,0),"") -> OP3
A101: 1288 | B101: =IFERROR(VLOOKUP(Tabela1[[#This Row],[CC]],#REF!,5,0),"") | C101: LIZANDRA PIMENTA | D101: SEC-BA | E101: SEC BA SISTEMAS (1288) | F101: SERVIÇO | G101: 8186 | H101: 45627 | I101: 240212.72 | J101: 223878.26 | K101: 45680 | L101: 45698 | M101: 45698 | N101: PAGO | O101: 0 | Q101: ADS | R101: PS | S101: =IFERROR(VLOOKUP(Tabela1[[#This Row],[CC]],CC!$A$1:$H$403,8,0),"") -> OP3
A102: 1271 | B102: =IFERROR(VLOOKUP(Tabela1[[#This Row],[CC]],#REF!,5,0),"") | C102: LIZANDRA PIMENTA | D102: SEC-BA | E102: SEC SD (1271) | F102: SERVIÇO | G102: 8189 | H102: 45627 | I102: 255597.54 | J102: 238216.91 | K102: 45681 | L102: 45698 | M102: 45700 | N102: PAGO | O102: 0 | Q102: CSA | R102: PS | S102: =IFERROR(VLOOKUP(Tabela1[[#This Row],[CC]],CC!$A$1:$H$403,8,0),"") -> OP3
A103: 1288 | B103: =IFERROR(VLOOKUP(Tabela1[[#This Row],[CC]],#REF!,5,0),"") | C103: LIZANDRA PIMENTA | D103: SEC-BA | E103: SEC BA SISTEMAS (1288) | F103: SERVIÇO | G103: 8623 | H103: 45931 | I103: 393007.28 | J103: 366282.78 | K103: 45985 | L103: 45992 | M103: 45995 | N103: PAGO | Q103: ADS | R103: PS | S103: =IFERROR(VLOOKUP(Tabela1[[#This Row],[CC]],CC!$A$1:$H$403,8,0),"") -> OP3
A104: 1299 | B104: =IFERROR(VLOOKUP(Tabela1[[#This Row],[CC]],#REF!,5,0),"") | C104: LIZANDRA PIMENTA | D104: SEC-BA | E104: SEC SIGEDUC (1299) | F104: SERVIÇO | G104: 8190 | H104: 45627 | I104: 816076.8 | J104: 760583.57 | K104: 45681 | L104: 45698 | M104: 45698 | N104: PAGO | Q104: ADS | R104: PS | S104: =IFERROR(VLOOKUP(Tabela1[[#This Row],[CC]],CC!$A$1:$H$403,8,0),"") -> OP3
A105: 1394 | B105: =IFERROR(VLOOKUP(Tabela1[[#This Row],[CC]],#REF!,5,0),"") | C105: ANTONIO ALVES | D105: SEFAZ_BA | E105: SEFAZ - BA DIGITAL CENTER (1394) | F105: SERVIÇO | G105: 8180 | H105: 45627 | I105: 15768.3 | J105: 14696.05 | K105: 45670 | L105: 45677 | M105: 45681 | N105: PAGO | O105: 0 | Q105: CSA | R105: PS | S105: =IFERROR(VLOOKUP(Tabela1[[#This Row],[CC]],CC!$A$1:$H$403,8,0),"") -> OP4
A106: 1394 | B106: =IFERROR(VLOOKUP(Tabela1[[#This Row],[CC]],#REF!,5,0),"") | C106: ANTONIO ALVES | D106: SEFAZ_BA | E106: SEFAZ - BA DIGITAL CENTER (1394) | F106: SERVIÇO | G106: 8177 | H106: 45627 | I106: 111600.22 | J106: 104011.41 | K106: 45670 | L106: 45677 | M106: 45681 | N106: PAGO | O106: 0 | Q106: CSA | R106: PS | S106: =IFERROR(VLOOKUP(Tabela1[[#This Row],[CC]],CC!$A$1:$H$403,8,0),"") -> OP4
A107: 1394 | B107: =IFERROR(VLOOKUP(Tabela1[[#This Row],[CC]],#REF!,5,0),"") | C107: ANTONIO ALVES | D107: SEFAZ_BA | E107: SEFAZ - BA DIGITAL CENTER (1394) | F107: SERVIÇO | G107: 8176 | H107: 45627 | I107: 62325.11 | J107: 58087 | K107: 45670 | L107: 45684 | M107: 45686 | N107: PAGO | O107: 0 | Q107: CSA | R107: PS | S107: =IFERROR(VLOOKUP(Tabela1[[#This Row],[CC]],CC!$A$1:$H$403,8,0),"") -> OP4
A108: 1394 | B108: =IFERROR(VLOOKUP(Tabela1[[#This Row],[CC]],#REF!,5,0),"") | C108: ANTONIO ALVES | D108: SEFAZ_BA | E108: SEFAZ - BA DIGITAL CENTER (1394) | F108: SERVIÇO | G108: 8192 | H108: 45627 | I108: 127355.8 | J108: 118695.6 | K108: 45686 | L108: 45691 | M108: 45695 | N108: PAGO | O108: 0 | Q108: CSA | R108: PS | S108: =IFERROR(VLOOKUP(Tabela1[[#This Row],[CC]],CC!$A$1:$H$403,8,0),"") -> OP4
A109: 1394 | B109: =IFERROR(VLOOKUP(Tabela1[[#This Row],[CC]],#REF!,5,0),"") | C109: ANTONIO ALVES | D109: SEFAZ_BA | E109: SEFAZ - BA DIGITAL CENTER (1394) | F109: SERVIÇO | G109: 8191 | H109: 45627 | I109: 138077.03 | J109: 128687.79 | K109: 45686 | L109: 45691 | M109: 45695 | N109: PAGO | O109: 0 | Q109: CSA | R109: PS | S109: =IFERROR(VLOOKUP(Tabela1[[#This Row],[CC]],CC!$A$1:$H$403,8,0),"") -> OP4
A110: 1296 | B110: =IFERROR(VLOOKUP(Tabela1[[#This Row],[CC]],#REF!,5,0),"") | C110: =IFERROR(VLOOKUP(Tabela1[[#This Row],[CC]],CC!$A$1:$H$389,7,0),"") -> JOSÉ NETO | D110: =IFERROR(VLOOKUP(Tabela1[[#This Row],[CC]],CC!$A$1:$I$3869,3,0),"") -> AXIA | E110: =IFERROR(VLOOKUP(Tabela1[[#This Row],[CC]],CC!$A$1:$H$389,2,0),"") -> ELETROBRAS DIGITAL SUPORT (1296) | F110: SERVIÇO | G110: 1296 | H110: 45870 | I110: 853192.83 | J110: 783657.62 | K110: 45916 | L110: 45931 | M110: 45931 | N110: PAGO | Q110: =IFERROR(VLOOKUP(Tabela1[[#This Row],[CC]],CC!$A$1:$H$389,5,0),"") -> CSA | R110: =IFERROR(VLOOKUP(Tabela1[[#This Row],[CC]],CC!$A$1:$H$389,6,0),"") -> UT | S110: =IFERROR(VLOOKUP(Tabela1[[#This Row],[CC]],CC!$A$1:$H$403,8,0),"") -> OP2
...

Sheet Planilha1
B1: IR | C1: CSL
B2: 0.015 | C2: 0.0465
A3: 36666 | B3: =A3*$B$2 -> 549.99 | C3: =A3*$C$2 -> 1704.969
A4: 49671.04 | B4: =A4*$B$2 -> 745.0656 | C4: =A4*$C$2 -> 2309.7034
A5: 41449.6 | B5: =A5*$B$2 -> 621.744 | C5: =A5*$C$2 -> 1927.4064
