Workbook
Name DNOPE: 'PLANO DE CONTA'!$P$4:$P$14
Name DOPE: 'PLANO DE CONTA'!$N$4:$N$14
Name DRH: 'PLANO DE CONTA'!$R$4:$R$14
Name IMP: 'PLANO DE CONTA'!$T$4:$T$14
Name RNOP: 'PLANO DE CONTA'!$L$4:$L$11
Name RPROD: 'PLANO DE CONTA'!$H$4:$H$42
Name RSERV: 'PLANO DE CONTA'!$J$4:$J$42

Sheet PLANO DE CONTA
F2: BANCO | H2: RECEITA COM PRODUTO | J2: RECEITA COM SERVIÇO | L2: RECEITA NÃO OPERACIONAL | N2: DESPESAS OPERACIONAL | P2: DESPESAS NÃO OPERACIONAL | R2: DESPESAS COM RH | T2: IMPOSTOS
B3: COD | C3: CLASSIFICAÇÃO | D3: TIPO | H3: RPROD | J3: RSERV | L3: RNOPE | N3: DOPE | P3: DNOPE | R3: DRH | T3: IMP
H4: ANP | J4: ANP | L4: JUROS | N4: FACILITIES - FIXO | P4: MKT | R4: RH - VA/ VR - ALELO | T4: ICMS
B5: RPROD | C5: RECEITA COM PRODUTO | D5: RECEITA | F5: BRADESCO | H5: Arenas | J5: Arenas | L5: VENDA PRODUTOS | N5: REVENDA | P5: GESTÃO DE PESSOAS | R5: RH - PLANO DE SAÚDE | T5: IRRF
B6: RSERV | C6: RECEITA COM SERVIÇO | D6: RECEITA | F6: BB | H6: B. GAS | J6: B. GAS | N6: SERVIÇOS CONTÁBEIS | P6: TARIFA BANCÁRIA | R6: RH - TRANSPORTE | T6: ISS
B7: RNOPE | C7: RECEITA NÃO OPERACIONAL | D7: RECEITA | F7: BB -SP | H7: Bradesco | J7: Bradesco | N7: APORTE DE CAIXA | R7: RH - SALÁRIO | T7: IPTU
B8: DOPE | C8: DESPESAS OPERACIONAL | D8: DESPESAS | F8: SANTANDER | H8: BV Rendimento | J8: BV Rendimento | N8: LICENÇA DE SOFTWARE | R8: PAGAMENTO PJ | T8: FGTS
B9: DNOPE | C9: DESPESAS NÃO OPERACIONAIS | D9: DESPESAS | F9: ITAU | H9: CEABS | J9: CEABS | N9: FACILITIES - VARIÁVEL | R9: RH - FÉRIAS | T9: PIS
B10: DRH | C10: DESPESAS COM RH | D10: DESPESAS | H10: DG Cogel | J10: DG Cogel | R10: RH - DESLIGAMENTO | T10: COFINS
B11: IMP | C11: IMPOSTOS | D11: DESPESAS | H11: Ebal | J11: Ebal | R11: RH- BENEFÍCIOS
H12: Eletronuclear | J12: Eletronuclear
H13: EMBASA | J13: EMBASA
C14: DESPESAS COM RH | H14: Europ | J14: Europ
C15: DESPESAS NÃO OPERACIONAIS | H15: Fapesb | J15: Fapesb
H16: Furnas | J16: Furnas
H17: IBAMETRO | J17: IBAMETRO
H18: IBAMETRO | J18: IBAMETRO
H19: INEMA | J19: INEMA
H20: INEMA | J20: INEMA
H21: IPLAN | J21: IPLAN
H22: Irdeb | J22: Irdeb
H23: LE BISCUIT | J23: LE BISCUIT
H24: MP-BA | J24: MP-BA
H25: Nextia | J25: Nextia
H26: OI | J26: OI
H27: PETZ | J27: PETZ
... H42: UFBA | J42: UFBA

Sheet RELATÓRIO
A2: =TODAY() -> 46219
A4: BANCO | B4: SALDO
A5: Bradesco | B5: ='Fluxo do Banco'!G1467 -> 766908.08
A6: Santander | B6: ='Fluxo do Banco'!AK1467+'Fluxo do Banco'!AE1467 -> 18678.12
A7: Safra | B7: ='Fluxo do Banco'!AQ1467 -> 282.67
A8: Brasil | B8: ='Fluxo do Banco'!S1467 -> 267.78
A9: Brasil SP | B9: ='Fluxo do Banco'!Y1467 -> 58.41
A10: Itaú | B10: ='Fluxo do Banco'!M1467 -> -2921513.5
A11: ="Saldo Bancário em " & TEXT(TODAY(),"dd/mm/aaaa") -> Saldo Bancário em 16/07/2026 | B11: =SUM(B5:B10) -> -2135318.5
A12: Saldo Crédito INSS | B12: 5024000 | W12: 631770
A13: ="Saldo Operacional em " & TEXT(TODAY(),"dd/mm/aaaa") -> Saldo Operacional em 16/07/2026 | B13: =B11-B12 -> -7159318.5
A15: ="Recebimento " & TEXT(WORKDAY(TODAY(),-1),"dd/mm/aaaa") -> Recebimento 15/07/2026 | B15: =SUM(B16:B23) -> 1721472.9 | C15: ='Fluxo do Banco'!AT1467 -> 1721472.9 | D15: =C15-B15 -> 0 | W15: 89032
A16: SEC - BA | B16: 1555781.9
A17: FAPESB | B17: 80766.17
A18: INEMA | B18: 79968.13
A19: UNIPAR | B19: 4956.69
A24: ="Pagamento " & TEXT(WORKDAY(TODAY(),-1),"dd/mm/aaaa") -> Pagamento 15/07/2026 | B24: =SUM(B25:B37) -> 242432.41
A25: Despesas | B25: 242432.41
C27: ='Fluxo do Banco'!AV1467 -> -242432.41 | D27: =C27+B24 -> 0

Sheet Fluxo do Banco
BA1: =2.5%/30 -> 0.00083333333
C2: BRADESCO | I2: ITAÚ | O2: BB | U2: BB - SP | AA2: SANTANDER | AG2: SANTANDER SP | AM2: SAFRA | AS2: RESUMO | BD2: Soma de VALOR | BE2: Rótulos de Coluna
B3: DATA | C3: BRADESCO - SALDO INÍCIO | D3: BRADESCO - RECEBIMENTO | E3: BRADESCO - TRANSF ENTRE CONTAS | F3: BRADESCO - PAG | G3: BRADESCO - SALDO FINAL | H3: BRADESCO - LIMITES | I3: ITAÚ - SALDO | J3: ITAÚ - RECEBIMENTO | K3: ITAÚ -TRANSFENTRE CONTAS | L3: ITAÚ - PAG | M3: ITAÚ - SALDO FINAL | N3: ITAÚ- LIMITES | O3: BB - SALDO | P3: BB- RECEBIMENTO | Q3: BB - TRANSFENTRE CONTAS | R3: BB- PAG | S3: BB - SALDO FINAL | T3: BB- LIMITES | U3: BB -SP - SALDO | V3: BB-SP RECEBIMENTO | W3: BB - SP TRANSFENTRE CONTAS | X3: BB- SP - PAG | Y3: BB - SP - SALDO FINAL | Z3: BB- SP- LIMITES | AA3: SANTANDER - SALDO | AB3: SANTANDER - RECEBIMENTO | AC3: SANTANDER -TRANSFENTRE CONTAS | AD3: SANTANDER - PAGAMENTO | AE3: SANTANDER - SALDO FINAL | AF3: SANTANDER -LIMITES | AG3: SANTANDER - SALDO | AH3: SANTANDER - RECEBIMENTO | AI3: SANTANDER -TRANSFENTRE CONTAS | AJ3: SANTANDER - PAGAMENTO | AK3: SANTANDER - SALDO FINAL | AL3: SANTANDER -LIMITES | AM3: SAFRA - SALDO | AN3: SAFRA - RECEBIMENTO | AO3: SAFRA -TRANSFENTRE CONTAS | AP3: SAFRA - PAGAMENTO | AQ3: SAFRA - SALDO FINAL | AR3: SAFRA -LIMITES | AS3: BANCOS -SALDO | AT3: BANCOS -RECEBIMENTO | AU3: BANCOS -TRANSFENTRE CONTAS | AV3: BANCOS -PAGAMENTO | AW3: APLICAÇÃO | AX3: BANCOS - SALDO FINAL | AY3: BANCOS - LIMITES | AZ3: DISPONIVEL PARA PROX | BA3: Juros Diário | BB3: Acumulado Mês | BC3: Saldo médio | BD3: Rótulos de Linha | BE3: (vazio) | BF3: 30/nov | BG3: 01/dez | BH3: Total Geral
B4: 44165 | C4: 1655274.9 | D4: 369779.22 | F4: -157086.26 | G4: =SUM(C4:F4) -> 1867967.8 | H4: 3800000 | I4: 1335209.8 | J4: 663301.19 | L4: -11131.65 | M4: =SUM(I4:L4) -> 1987379.3 | N4: 2500000 | O4: 89001.46 | P4: 565656 | R4: -1654.8 | S4: =SUM(O4:R4) -> 653002.66 | U4: 915.97 | Y4: =SUM(U4:X4) -> 915.97 | AA4: 7904.2 | AD4: -1094.4 | AE4: =SUM(AA4:AD4) -> 6809.8 | AS4: =SUM(C4,I4,O4,U4,AA4,) -> 3088306.2 | AT4: =SUM(D4,J4,P4,V4,AB4,) -> 1598736.4 | AU4: =SUM(E4,K4,Q4,W4,AC4,) -> 0 | AV4: =SUM(F4,L4,R4,X4,AD4,) -> -170967.11 | AX4: =SUM(G4,M4,S4,Y4,AE4,) -> 4516075.5 | AY4: =SUM(H4,N4,T4,Z4,AF4,) -> 6300000 | AZ4: =AX4+AY4 -> 10816076 | BD4: BB | BF4: 653482.89 | BH4: 653482.89
B5: 44166 | C5: =G4 -> 1867967.8 | F5: -1126468 | G5: =SUM(C5:F5) -> 741499.82 | H5: 3800000 | I5: =M4 -> 1987379.3 | J5: 3.99 | L5: -1814471.9 | M5: =SUM(I5:L5) -> 172911.42 | N5: 2500000 | O5: =S4 -> 653002.66 | R5: -4579.51 | S5: =SUM(O5:R5) -> 648423.15 | U5: =Y4 -> 915.97 | V5: 401723.05 | Y5: =SUM(U5:X5) -> 402639.02 | AA5: =AE4 -> 6809.8 | AE5: =SUM(AA5:AD5) -> 6809.8 | AS5: =SUM(C5,I5,O5,U5,AA5,) -> 4516075.5 | AT5: =SUM(D5,J5,P5,V5,AB5,) -> 401727.04 | AU5: =SUM(E5,K5,Q5,W5,AC5,) -> 0 | AV5: =SUM(F5,L5,R5,X5,AD5,) -> -2945519.4 | AX5: =SUM(G5,M5,S5,Y5,AE5,) -> 1972283.2 | AY5: =SUM(H5,N5,T5,Z5,AF5,) -> 6300000 | AZ5: =AX5+AY5 -> 8272283.2 | BD5: DESPESAS | BF5: -1167.8 | BH5: -1167.8
B6: =B5+1 -> 44167 | C6: =G5 -> 741499.82 | D6: 387668.08 | E6: 450000 | F6: -126941.67 | G6: =SUM(C6:F6) -> 1452226.2 | H6: 3800000 | I6: =M5 -> 172911.42 | J6: 50542.57 | K6: 500000 | L6: -242377.01 | M6: =SUM(I6:L6) -> 481076.98 | N6: 2500000 | O6: =S5 -> 648423.15 | Q6: -600000 | R6: -21264.63 | S6: =SUM(O6:R6) -> 27158.52 | U6: =Y5 -> 402639.02 | W6: -400000 | X6: -54.95 | Y6: =SUM(U6:X6) -> 2584.07 | AA6: =AE5 -> 6809.8 | AC6: 50000 | AD6: -40790.98 | AE6: =SUM(AA6:AD6) -> 16018.82 | AS6: =SUM(C6,I6,O6,U6,AA6,) -> 1972283.2 | AT6: =SUM(D6,J6,P6,V6,AB6,) -> 438210.65 | AU6: =SUM(E6,K6,Q6,W6,AC6,) -> 0 | AV6: =SUM(F6,L6,R6,X6,AD6,) -> -431429.24 | AX6: =SUM(G6,M6,S6,Y6,AE6,) -> 1979064.6 | AY6: =SUM(H6,N6,T6,Z6,AF6,) -> 6300000 | AZ6: =AX6+AY6 -> 8279064.6 | BD6: RECEITA | BF6: 565649.23 | BH6: 565649.23
B7: =B6+1 -> 44168 | C7: =G6 -> 1452226.2 | D7: 275383.59 | F7: -88369.16 | G7: =SUM(C7:F7) -> 1639240.7 | H7: 3800000 | I7: =M6 -> 481076.98 | J7: 198.54 | L7: -104507.89 | M7: =SUM(I7:L7) -> 376767.63 | N7: 2500000 | O7: =S6 -> 27158.52 | S7: =SUM(O7:R7) -> 27158.52 | U7: =Y6 -> 2584.07 | X7: -1.2 | Y7: =SUM(U7:X7) -> 2582.87 | AA7: =AE6 -> 16018.82 | AB7: 35890.9 | AE7: =SUM(AA7:AD7) -> 51909.72 | AS7: =SUM(C7,I7,O7,U7,AA7,) -> 1979064.6 | AT7: =SUM(D7,J7,P7,V7,AB7,) -> 311473.03 | AU7: =SUM(E7,K7,Q7,W7,AC7,) -> 0 | AV7: =SUM(F7,L7,R7,X7,AD7,) -> -192878.25 | AX7: =SUM(G7,M7,S7,Y7,AE7,) -> 2097659.4 | AY7: =SUM(H7,N7,T7,Z7,AF7,) -> 6300000 | AZ7: =AX7+AY7 -> 8397659.4 | BD7: SALDO INICIAL | BF7: 89001.46 | BH7: 89001.46
B8: =B7+1 -> 44169 | C8: =G7 -> 1639240.7 | D8: 3.7 | F8: -10400 | G8: =SUM(C8:F8) -> 1628844.4 | H8: 3800000 | I8: =M7 -> 376767.63 | J8: 533835.99 | L8: -537 | M8: =SUM(I8:L8) -> 910066.62 | N8: 2500000 | O8: =S7 -> 27158.52 | P8: 174.42 | S8: =SUM(O8:R8) -> 27332.94 | U8: =Y7 -> 2582.87 | V8: 2760.29 | Y8: =SUM(U8:X8) -> 5343.16 | AA8: =AE7 -> 51909.72 | AE8: =SUM(AA8:AD8) -> 51909.72 | AS8: =SUM(C8,I8,O8,U8,AA8,) -> 2097659.4 | AT8: =SUM(D8,J8,P8,V8,AB8,) -> 536774.4 | AU8: =SUM(E8,K8,Q8,W8,AC8,) -> 0 | AV8: =SUM(F8,L8,R8,X8,AD8,) -> -10937 | AX8: =SUM(G8,M8,S8,Y8,AE8,) -> 2623496.8 | AY8: =SUM(H8,N8,T8,Z8,AF8,) -> 6300000 | AZ8: =AX8+AY8 -> 8923496.8 | BD8: BB -SP | BF8: 915.97 | BH8: 915.97
B9: =B8+3 -> 44172 | C9: =G8 -> 1628844.4 | F9: -747261.36 | G9: =SUM(C9:F9) -> 881583 | H9: 3800000 | I9: =M8 -> 910066.62 | J9: 193376.16 | L9: -35486.68 | M9: =SUM(I9:L9) -> 1067956.1 | N9: 2500000 | O9: =S8 -> 27332.94 | P9: 399.32 | Q9: 46000 | S9: =SUM(O9:R9) -> 73732.26 | U9: =Y8 -> 5343.16 | V9: 40993.68 | W9: -46000 | Y9: =SUM(U9:X9) -> 336.84 | AA9: =AE8 -> 51909.72 | AE9: =SUM(AA9:AD9) -> 51909.72 | AS9: =SUM(C9,I9,O9,U9,AA9,) -> 2623496.8 | AT9: =SUM(D9,J9,P9,V9,AB9,) -> 234769.16 | AU9: =SUM(E9,K9,Q9,W9,AC9,) -> 0 | AV9: =SUM(F9,L9,R9,X9,AD9,) -> -782748.04 | AX9: =SUM(G9,M9,S9,Y9,AE9,) -> 2075517.9 | AY9: =SUM(H9,N9,T9,Z9,AF9,) -> 6300000 | AZ9: =AX9+AY9 -> 8375517.9 | BD9: SALDO INICIAL | BF9: 915.97 | BH9: 915.97
B10: =B9+1 -> 44173 | C10: =G9 -> 881583 | D10: 131444 | F10: -93006.46 | G10: =SUM(C10:F10) -> 920020.54 | H10: 3800000 | I10: =M9 -> 1067956.1 | L10: -20112.33 | M10: =SUM(I10:L10) -> 1047843.8 | N10: 2500000 | O10: =S9 -> 73732.26 | S10: =SUM(O10:R10) -> 73732.26 | U10: =Y9 -> 336.84 | X10: -1.2 | Y10: =SUM(U10:X10) -> 335.64 | AA10: =AE9 -> 51909.72 | AE10: =SUM(AA10:AD10) -> 51909.72 | AS10: =SUM(C10,I10,O10,U10,AA10,) -> 2075517.9 | AT10: =SUM(D10,J10,P10,V10,AB10,) -> 131444 | AU10: =SUM(E10,K10,Q10,W10,AC10,) -> 0 | AV10: =SUM(F10,L10,R10,X10,AD10,) -> -113119.99 | AX10: =SUM(G10,M10,S10,Y10,AE10,) -> 2093841.9 | AY10: =SUM(H10,N10,T10,Z10,AF10,) -> 6300000 | AZ10: =AX10+AY10 -> 8393841.9 | BD10: BRADESCO | BF10: 1892167.6 | BH10: 1892167.6
B11: =B10+1 -> 44174 | C11: =G10 -> 920020.54 | D11: 45287.3 | F11: -26944.48 | G11: =SUM(C11:F11) -> 938363.36 | H11: 3800000 | I11: =M10 -> 1047843.8 | L11: -58597.6 | M11: =SUM(I11:L11) -> 989246.17 | N11: 2500000 | O11: =S10 -> 73732.26 | R11: -2062.9 | S11: =SUM(O11:R11) -> 71669.36 | U11: =Y10 -> 335.64 | Y11: =SUM(U11:X11) -> 335.64 | AA11: =AE10 -> 51909.72 | AE11: =SUM(AA11:AD11) -> 51909.72 | AS11: =SUM(C11,I11,O11,U11,AA11,) -> 2093841.9 | AT11: =SUM(D11,J11,P11,V11,AB11,) -> 45287.3 | AU11: =SUM(E11,K11,Q11,W11,AC11,) -> 0 | AV11: =SUM(F11,L11,R11,X11,AD11,) -> -87604.98 | AX11: =SUM(G11,M11,S11,Y11,AE11,) -> 2051524.3 | AY11: =SUM(H11,N11,T11,Z11,AF11,) -> 6300000 | AZ11: =AX11+AY11 -> 8351524.2 | BD11: DESPESAS | BF11: -132886.48 | BH11: -132886.48
B12: =B11+1 -> 44175 | C12: =G11 -> 938363.36 | D12: 478312.63 | F12: -178349.06 | G12: =SUM(C12:F12) -> 1238326.9 | H12: 3800000 | I12: =M11 -> 989246.17 | L12: -182658.69 | M12: =SUM(I12:L12) -> 806587.48 | N12: 2500000 | O12: =S11 -> 71669.36 | P12: 30325.1 | R12: -4001.94 | S12: =SUM(O12:R12) -> 97992.52 | U12: =Y11 -> 335.64 | Y12: =SUM(U12:X12) -> 335.64 | AA12: =AE11 -> 51909.72 | AD12: -221.25 | AE12: =SUM(AA12:AD12) -> 51688.47 | AS12: =SUM(C12,I12,O12,U12,AA12,) -> 2051524.3 | AT12: =SUM(D12,J12,P12,V12,AB12,) -> 508637.73 | AU12: =SUM(E12,K12,Q12,W12,AC12,) -> 0 | AV12: =SUM(F12,L12,R12,X12,AD12,) -> -365230.94 | AX12: =SUM(G12,M12,S12,Y12,AE12,) -> 2194931 | AY12: =SUM(H12,N12,T12,Z12,AF12,) -> 6300000 | AZ12: =AX12+AY12 -> 8494931 | BD12: RECEITA | BF12: 369779.22 | BH12: 369779.22
B13: =B12+1 -> 44176 | C13: =G12 -> 1238326.9 | F13: -10703.71 | G13: =SUM(C13:F13) -> 1227623.2 | H13: 3800000 | I13: =M12 -> 806587.48 | M13: =SUM(I13:L13) -> 806587.48 | N13: 2500000 | O13: =S12 -> 97992.52 | S13: =SUM(O13:R13) -> 97992.52 | U13: =Y12 -> 335.64 | Y13: =SUM(U13:X13) -> 335.64 | AA13: =AE12 -> 51688.47 | AE13: =SUM(AA13:AD13) -> 51688.47 | AS13: =SUM(C13,I13,O13,U13,AA13,) -> 2194931 | AT13: =SUM(D13,J13,P13,V13,AB13,) -> 0 | AU13: =SUM(E13,K13,Q13,W13,AC13,) -> 0 | AV13: =SUM(F13,L13,R13,X13,AD13,) -> -10703.71 | AX13: =SUM(G13,M13,S13,Y13,AE13,) -> 2184227.3 | AY13: =SUM(H13,N13,T13,Z13,AF13,) -> 6300000 | AZ13: =AX13+AY13 -> 8484227.3 | BD13: SALDO INICIAL | BF13: 1655274.9 | BH13: 1655274.9
B14: =B13+3 -> 44179 | C14: =G13 -> 1227623.2 | D14: 50628 | F14: -39041.48 | G14: =SUM(C14:F14) -> 1239209.7 | H14: 3800000 | I14: =M13 -> 806587.48 | J14: 1718696.3 | L14: -77055.6 | M14: =SUM(I14:L14) -> 2448228.2 | N14: 2500000 | O14: =S13 -> 97992.52 | R14: -4703.81 | S14: =SUM(O14:R14) -> 93288.71 | U14: =Y13 -> 335.64 | Y14: =SUM(U14:X14) -> 335.64 | AA14: =AE13 -> 51688.47 | AE14: =SUM(AA14:AD14) -> 51688.47 | AS14: =SUM(C14,I14,O14,U14,AA14,) -> 2184227.3 | AT14: =SUM(D14,J14,P14,V14,AB14,) -> 1769324.3 | AU14: =SUM(E14,K14,Q14,W14,AC14,) -> 0 | AV14: =SUM(F14,L14,R14,X14,AD14,) -> -120800.89 | AX14: =SUM(G14,M14,S14,Y14,AE14,) -> 3832750.8 | AY14: =SUM(H14,N14,T14,Z14,AF14,) -> 6300000 | AZ14: =AX14+AY14 -> 10132751 | BD14: ITAU | BF14: 1988314.3 | BH14: 1988314.3
B15: =B14+1 -> 44180 | C15: =G14 -> 1239209.7 | D15: 10251.03 | F15: -11250.05 | G15: =SUM(C15:F15) -> 1238210.7 | H15: 3800000 | I15: =M14 -> 2448228.2 | L15: -308622.69 | M15: =SUM(I15:L15) -> 2139605.5 | N15: 2500000 | O15: =S14 -> 93288.71 | R15: -704.6 | S15: =SUM(O15:R15) -> 92584.11 | U15: =Y14 -> 335.64 | Y15: =SUM(U15:X15) -> 335.64 | AA15: =AE14 -> 51688.47 | AE15: =SUM(AA15:AD15) -> 51688.47 | AS15: =SUM(C15,I15,O15,U15,AA15,) -> 3832750.8 | AT15: =SUM(D15,J15,P15,V15,AB15,) -> 10251.03 | AU15: =SUM(E15,K15,Q15,W15,AC15,) -> 0 | AV15: =SUM(F15,L15,R15,X15,AD15,) -> -320577.34 | AX15: =SUM(G15,M15,S15,Y15,AE15,) -> 3522424.5 | AY15: =SUM(H15,N15,T15,Z15,AF15,) -> 6300000 | AZ15: =AX15+AY15 -> 9822424.5 | BD15: DESPESAS | BF15: -10196.65 | BH15: -10196.65
B16: =B15+1 -> 44181 | C16: =G15 -> 1238210.7 | F16: -1187301.7 | G16: =SUM(C16:F16) -> 50909.01 | H16: 3800000 | I16: =M15 -> 2139605.5 | J16: 53228.4 | L16: -6202.99 | M16: =SUM(I16:L16) -> 2186630.9 | N16: 2500000 | O16: =S15 -> 92584.11 | S16: =SUM(O16:R16) -> 92584.11 | U16: =Y15 -> 335.64 | Y16: =SUM(U16:X16) -> 335.64 | AA16: =AE15 -> 51688.47 | AD16: -8755.4 | AE16: =SUM(AA16:AD16) -> 42933.07 | AS16: =SUM(C16,I16,O16,U16,AA16,) -> 3522424.5 | AT16: =SUM(D16,J16,P16,V16,AB16,) -> 53228.4 | AU16: =SUM(E16,K16,Q16,W16,AC16,) -> 0 | AV16: =SUM(F16,L16,R16,X16,AD16,) -> -1202260.1 | AX16: =SUM(G16,M16,S16,Y16,AE16,) -> 2373392.8 | AY16: =SUM(H16,N16,T16,Z16,AF16,) -> 6300000 | AZ16: =AX16+AY16 -> 8673392.8 | BD16: RECEITA | BF16: 663301.19 | BH16: 663301.19
B17: =B16+1 -> 44182 | C17: =G16 -> 50909.01 | D17: 4478.23 | F17: -76441.37 | G17: =SUM(C17:F17) -> -21054.13 | H17: 3800000 | I17: =M16 -> 2186630.9 | J17: 884193.57 | L17: -893162.29 | M17: =SUM(I17:L17) -> 2177662.2 | N17: 2500000 | O17: =S16 -> 92584.11 | R17: -80000 | S17: =SUM(O17:R17) -> 12584.11 | U17: =Y16 -> 335.64 | Y17: =SUM(U17:X17) -> 335.64 | AA17: =AE16 -> 42933.07 | AE17: =SUM(AA17:AD17) -> 42933.07 | AS17: =SUM(C17,I17,O17,U17,AA17,) -> 2373392.8 | AT17: =SUM(D17,J17,P17,V17,AB17,) -> 888671.8 | AU17: =SUM(E17,K17,Q17,W17,AC17,) -> 0 | AV17: =SUM(F17,L17,R17,X17,AD17,) -> -1049603.7 | AX17: =SUM(G17,M17,S17,Y17,AE17,) -> 2212460.9 | AY17: =SUM(H17,N17,T17,Z17,AF17,) -> 6300000 | AZ17: =AX17+AY17 -> 8512460.9 | BD17: SALDO INICIAL | BF17: 1335209.8 | BH17: 1335209.8
B18: =B17+1 -> 44183 | C18: =G17 -> -21054.13 | D18: 188826.81 | F18: -663193.6 | G18: =SUM(C18:F18) -> -495420.92 | H18: 3800000 | I18: =M17 -> 2177662.2 | J18: 814753.14 | L18: -78572.96 | M18: =SUM(I18:L18) -> 2913842.4 | N18: 2500000 | O18: =S17 -> 12584.11 | S18: =SUM(O18:R18) -> 12584.11 | U18: =Y17 -> 335.64 | Y18: =SUM(U18:X18) -> 335.64 | AA18: =AE17 -> 42933.07 | AE18: =SUM(AA18:AD18) -> 42933.07 | AS18: =SUM(C18,I18,O18,U18,AA18,) -> 2212460.9 | AT18: =SUM(D18,J18,P18,V18,AB18,) -> 1003579.9 | AU18: =SUM(E18,K18,Q18,W18,AC18,) -> 0 | AV18: =SUM(F18,L18,R18,X18,AD18,) -> -741766.56 | AX18: =SUM(G18,M18,S18,Y18,AE18,) -> 2474274.3 | AY18: =SUM(H18,N18,T18,Z18,AF18,) -> 6300000 | AZ18: =AX18+AY18 -> 8774274.3 | BD18: SANTANDER | BF18: 6809.8 | BH18: 6809.8
B19: =B18+3 -> 44186 | C19: =G18 -> -495420.92 | D19: 527175.93 | E19: 740000 | F19: -478547.62 | G19: =SUM(C19:F19) -> 293207.39 | H19: 3800000 | I19: =M18 -> 2913842.4 | J19: 553750.7 | K19: -1000000 | L19: -88946.66 | M19: =SUM(I19:L19) -> 2378646.4 | N19: 2500000 | O19: =S18 -> 12584.11 | P19: 95189.74 | R19: -4467.86 | S19: =SUM(O19:R19) -> 103305.99 | U19: =Y18 -> 335.64 | Y19: =SUM(U19:X19) -> 335.64 | AA19: =AE18 -> 42933.07 | AC19: 260000 | AE19: =SUM(AA19:AD19) -> 302933.07 | AS19: =SUM(C19,I19,O19,U19,AA19,) -> 2474274.3 | AT19: =SUM(D19,J19,P19,V19,AB19,) -> 1176116.4 | AU19: =SUM(E19,K19,Q19,W19,AC19,) -> 0 | AV19: =SUM(F19,L19,R19,X19,AD19,) -> -571962.14 | AX19: =SUM(G19,M19,S19,Y19,AE19,) -> 3078428.5 | AY19: =SUM(H19,N19,T19,Z19,AF19,) -> 6300000 | AZ19: =AX19+AY19 -> 9378428.5 | BD19: DESPESAS | BF19: -1094.4 | BH19: -1094.4
B20: =B19+1 -> 44187 | C20: =G19 -> 293207.39 | D20: 350141.95 | F20: -55721.49 | G20: =SUM(C20:F20) -> 587627.85 | H20: 3800000 | I20: =M19 -> 2378646.4 | J20: 33267.86 | L20: -18470.89 | M20: =SUM(I20:L20) -> 2393443.4 | N20: 2500000 | O20: =S19 -> 103305.99 | R20: -3590.98 | S20: =SUM(O20:R20) -> 99715.01 | U20: =Y19 -> 335.64 | Y20: =SUM(U20:X20) -> 335.64 | AA20: =AE19 -> 302933.07 | AB20: 43696.53 | AD20: -260364.98 | AE20: =SUM(AA20:AD20) -> 86264.62 | AS20: =SUM(C20,I20,O20,U20,AA20,) -> 3078428.5 | AT20: =SUM(D20,J20,P20,V20,AB20,) -> 427106.34 | AU20: =SUM(E20,K20,Q20,W20,AC20,) -> 0 | AV20: =SUM(F20,L20,R20,X20,AD20,) -> -338148.34 | AX20: =SUM(G20,M20,S20,Y20,AE20,) -> 3167386.5 | AY20: =SUM(H20,N20,T20,Z20,AF20,) -> 6300000 | AZ20: =AX20+AY20 -> 9467386.5 | BD20: SALDO INICIAL | BF20: 7904.2 | BH20: 7904.2
B21: =B20+1 -> 44188 | C21: =G20 -> 587627.85 | D21: 41783.76 | F21: -138.72 | G21: =SUM(C21:F21) -> 629272.89 | H21: 3800000 | I21: =M20 -> 2393443.4 | J21: 212577.98 | M21: =SUM(I21:L21) -> 2606021.4 | N21: 2500000 | O21: =S20 -> 99715.01 | P21: 81.92 | S21: =SUM(O21:R21) -> 99796.93 | U21: =Y20 -> 335.64 | Y21: =SUM(U21:X21) -> 335.64 | AA21: =AE20 -> 86264.62 | AE21: =SUM(AA21:AD21) -> 86264.62 | AS21: =SUM(C21,I21,O21,U21,AA21,) -> 3167386.5 | AT21: =SUM(D21,J21,P21,V21,AB21,) -> 254443.66 | AU21: =SUM(E21,K21,Q21,W21,AC21,) -> 0 | AV21: =SUM(F21,L21,R21,X21,AD21,) -> -138.72 | AX21: =SUM(G21,M21,S21,Y21,AE21,) -> 3421691.5 | AY21: =SUM(H21,N21,T21,Z21,AF21,) -> 6300000 | AZ21: =AX21+AY21 -> 9721691.5 | BD21: (vazio)
B22: =B21+1 -> 44189 | C22: =G21 -> 629272.89 | D22: 324875.07 | F22: -60000 | G22: =SUM(C22:F22) -> 894147.96 | H22: 3800000 | I22: =M21 -> 2606021.4 | M22: =SUM(I22:L22) -> 2606021.4 | N22: 2500000 | O22: =S21 -> 99796.93 | P22: 81.92 | S22: =SUM(O22:R22) -> 99878.85 | U22: =Y21 -> 335.64 | Y22: =SUM(U22:X22) -> 335.64 | AA22: =AE21 -> 86264.62 | AE22: =SUM(AA22:AD22) -> 86264.62 | AS22: =SUM(C22,I22,O22,U22,AA22,) -> 3421691.5 | AT22: =SUM(D22,J22,P22,V22,AB22,) -> 324956.99 | AU22: =SUM(E22,K22,Q22,W22,AC22,) -> 0 | AV22: =SUM(F22,L22,R22,X22,AD22,) -> -60000 | AX22: =SUM(G22,M22,S22,Y22,AE22,) -> 3686648.5 | AY22: =SUM(H22,N22,T22,Z22,AF22,) -> 6300000 | AZ22: =AX22+AY22 -> 9986648.5 | BD22: DESPESAS
B23: =B22+4 -> 44193 | C23: =G22 -> 894147.96 | D23: 462678.1 | F23: -246712.73 | G23: =SUM(C23:F23) -> 1110113.3 | H23: 3800000 | I23: =M22 -> 2606021.4 | L23: -243988.47 | M23: =SUM(I23:L23) -> 2362032.9 | N23: 2500000 | O23: =S22 -> 99878.85 | R23: -3428.09 | S23: =SUM(O23:R23) -> 96450.76 | U23: =Y22 -> 335.64 | Y23: =SUM(U23:X23) -> 335.64 | AA23: =AE22 -> 86264.62 | AD23: -9133.24 | AE23: =SUM(AA23:AD23) -> 77131.38 | AS23: =SUM(C23,I23,O23,U23,AA23,) -> 3686648.5 | AT23: =SUM(D23,J23,P23,V23,AB23,) -> 462678.1 | AU23: =SUM(E23,K23,Q23,W23,AC23,) -> 0 | AV23: =SUM(F23,L23,R23,X23,AD23,) -> -503262.53 | AX23: =SUM(G23,M23,S23,Y23,AE23,) -> 3646064 | AY23: =SUM(H23,N23,T23,Z23,AF23,) -> 6300000 | AZ23: =AX23+AY23 -> 9946064 | BD23: #N/D
B24: =B23+1 -> 44194 | C24: =G23 -> 1110113.3 | D24: 45385.53 | F24: -149121.85 | G24: =SUM(C24:F24) -> 1006377 | H24: 3800000 | I24: =M23 -> 2362032.9 | L24: -165 | M24: =SUM(I24:L24) -> 2361867.9 | N24: 2500000 | O24: =S23 -> 96450.76 | S24: =SUM(O24:R24) -> 96450.76 | U24: =Y23 -> 335.64 | Y24: =SUM(U24:X24) -> 335.64 | AA24: =AE23 -> 77131.38 | AE24: =SUM(AA24:AD24) -> 77131.38 | AS24: =SUM(C24,I24,O24,U24,AA24,) -> 3646064 | AT24: =SUM(D24,J24,P24,V24,AB24,) -> 45385.53 | AU24: =SUM(E24,K24,Q24,W24,AC24,) -> 0 | AV24: =SUM(F24,L24,R24,X24,AD24,) -> -149286.85 | AX24: =SUM(G24,M24,S24,Y24,AE24,) -> 3542162.7 | AY24: =SUM(H24,N24,T24,Z24,AF24,) -> 6300000 | AZ24: =AX24+AY24 -> 9842162.7 | BD24: Total Geral | BF24: 4541690.6 | BH24: 4541690.6
B25: =B24+1 -> 44195 | C25: =G24 -> 1006377 | D25: 37433.69 | F25: -35336.74 | G25: =SUM(C25:F25) -> 1008474 | H25: 3800000 | I25: =M24 -> 2361867.9 | J25: 330127.77 | L25: -360077.33 | M25: =SUM(I25:L25) -> 2331918.4 | N25: 2500000 | O25: =S24 -> 96450.76 | P25: 240834.73 | S25: =SUM(O25:R25) -> 337285.49 | U25: =Y24 -> 335.64 | Y25: =SUM(U25:X25) -> 335.64 | AA25: =AE24 -> 77131.38 | AE25: =SUM(AA25:AD25) -> 77131.38 | AS25: =SUM(C25,I25,O25,U25,AA25,) -> 3542162.7 | AT25: =SUM(D25,J25,P25,V25,AB25,) -> 608396.19 | AU25: =SUM(E25,K25,Q25,W25,AC25,) -> 0 | AV25: =SUM(F25,L25,R25,X25,AD25,) -> -395414.07 | AX25: =SUM(G25,M25,S25,Y25,AE25,) -> 3755144.8 | AY25: =SUM(H25,N25,T25,Z25,AF25,) -> 6300000 | AZ25: =AX25+AY25 -> 10055145
B26: =B25+1 -> 44196 | C26: =G25 -> 1008474 | G26: =SUM(C26:F26) -> 1008474 | H26: 3800000 | I26: =M25 -> 2331918.4 | J26: =106756.36+107508.93 -> 214265.29 | M26: =SUM(I26:L26) -> 2546183.6 | N26: 2500000 | O26: =S25 -> 337285.49 | S26: =SUM(O26:R26) -> 337285.49 | U26: =Y25 -> 335.64 | Y26: =SUM(U26:X26) -> 335.64 | AA26: =AE25 -> 77131.38 | AE26: =SUM(AA26:AD26) -> 77131.38 | AS26: =SUM(C26,I26,O26,U26,AA26,) -> 3755144.8 | AT26: =SUM(D26,J26,P26,V26,AB26,) -> 214265.29 | AU26: =SUM(E26,K26,Q26,W26,AC26,) -> 0 | AV26: =SUM(F26,L26,R26,X26,AD26,) -> 0 | AX26: =SUM(G26,M26,S26,Y26,AE26,) -> 3969410.1 | AY26: =SUM(H26,N26,T26,Z26,AF26,) -> 6300000 | AZ26: =AX26+AY26 -> 10269410
B27: =B26+4 -> 44200 | C27: =G26 -> 1008474 | D27: 217048.98 | F27: -237325.38 | G27: =SUM(C27:F27) -> 988197.56 | H27: 3800000 | I27: =M26 -> 2546183.6 | J27: 389097.9 | L27: -1779947.4 | M27: =SUM(I27:L27) -> 1155334.1 | N27: 2500000 | O27: =S26 -> 337285.49 | P27: 26162.55 | R27: -2600 | S27: =SUM(O27:R27) -> 360848.04 | U27: =Y26 -> 335.64 | V27: 458774.3 | Y27: =SUM(U27:X27) -> 459109.94 | AA27: =AE26 -> 77131.38 | AB27: 0.6 | AE27: =SUM(AA27:AD27) -> 77131.98 | AS27: =SUM(C27,I27,O27,U27,AA27,) -> 3969410.1 | AT27: =SUM(D27,J27,P27,V27,AB27,) -> 1091084.3 | AU27: =SUM(E27,K27,Q27,W27,AC27,) -> 0 | AV27: =SUM(F27,L27,R27,X27,AD27,) -> -2019872.8 | AX27: =SUM(G27,M27,S27,Y27,AE27,) -> 3040621.6 | AY27: =SUM(H27,N27,T27,Z27,AF27,) -> 6300000 | AZ27: =AX27+AY27 -> 9340621.6
B28: =B27+1 -> 44201 | C28: =G27 -> 988197.56 | D28: 1351.1 | F28: -759334.44 | G28: =SUM(C28:F28) -> 230214.22 | H28: 3800000 | I28: =M27 -> 1155334.1 | L28: -214032.36 | M28: =SUM(I28:L28) -> 941301.75 | N28: 2500000 | O28: =S27 -> 360848.04 | S28: =SUM(O28:R28) -> 360848.04 | U28: =Y27 -> 459109.94 | X28: -54.95 | Y28: =SUM(U28:X28) -> 459054.99 | AA28: =AE27 -> 77131.98 | AE28: =SUM(AA28:AD28) -> 77131.98 | AS28: =SUM(C28,I28,O28,U28,AA28,) -> 3040621.6 | AT28: =SUM(D28,J28,P28,V28,AB28,) -> 1351.1 | AU28: =SUM(E28,K28,Q28,W28,AC28,) -> 0 | AV28: =SUM(F28,L28,R28,X28,AD28,) -> -973421.75 | AX28: =SUM(G28,M28,S28,Y28,AE28,) -> 2068551 | AY28: =SUM(H28,N28,T28,Z28,AF28,) -> 6300000 | AZ28: =AX28+AY28 -> 8368551
B29: =B28+1 -> 44202 | C29: =G28 -> 230214.22 | D29: =119338.75+163732.17 -> 283070.92 | F29: -58313.83 | G29: =SUM(C29:F29) -> 454971.31 | H29: 3800000 | I29: =M28 -> 941301.75 | L29: -52555.57 | M29: =SUM(I29:L29) -> 888746.18 | N29: 2500000 | O29: =S28 -> 360848.04 | R29: -522.5 | S29: =SUM(O29:R29) -> 360325.54 | U29: =Y28 -> 459054.99 | Y29: =SUM(U29:X29) -> 459054.99 | AA29: =AE28 -> 77131.98 | AE29: =SUM(AA29:AD29) -> 77131.98 | AS29: =SUM(C29,I29,O29,U29,AA29,) -> 2068551 | AT29: =SUM(D29,J29,P29,V29,AB29,) -> 283070.92 | AU29: =SUM(E29,K29,Q29,W29,AC29,) -> 0 | AV29: =SUM(F29,L29,R29,X29,AD29,) -> -111391.9 | AX29: =SUM(G29,M29,S29,Y29,AE29,) -> 2240230 | AY29: =SUM(H29,N29,T29,Z29,AF29,) -> 6300000 | AZ29: =AX29+AY29 -> 8540230
B30: =B29+1 -> 44203 | C30: =G29 -> 454971.31 | D30: 322579.04 | G30: =SUM(C30:F30) -> 777550.35 | H30: 3800000 | I30: =M29 -> 888746.18 | L30: -412305.85 | M30: =SUM(I30:L30) -> 476440.33 | N30: 2500000 | O30: =S29 -> 360325.54 | S30: =SUM(O30:R30) -> 360325.54 | U30: =Y29 -> 459054.99 | Y30: =SUM(U30:X30) -> 459054.99 | AA30: =AE29 -> 77131.98 | AE30: =SUM(AA30:AD30) -> 77131.98 | AS30: =SUM(C30,I30,O30,U30,AA30,) -> 2240230 | AT30: =SUM(D30,J30,P30,V30,AB30,) -> 322579.04 | AU30: =SUM(E30,K30,Q30,W30,AC30,) -> 0 | AV30: =SUM(F30,L30,R30,X30,AD30,) -> -412305.85 | AX30: =SUM(G30,M30,S30,Y30,AE30,) -> 2150503.2 | AY30: =SUM(H30,N30,T30,Z30,AF30,) -> 6300000 | AZ30: =AX30+AY30 -> 8450503.2
B31: =B30+1 -> 44204 | C31: =G30 -> 777550.35 | D31: 50372.93 | F31: -5552.87 | G31: =SUM(C31:F31) -> 822370.41 | H31: 3800000 | I31: =M30 -> 476440.33 | J31: 136082.5 | M31: =SUM(I31:L31) -> 612522.83 | N31: 2500000 | O31: =S30 -> 360325.54 | S31: =SUM(O31:R31) -> 360325.54 | U31: =Y30 -> 459054.99 | Y31: =SUM(U31:X31) -> 459054.99 | AA31: =AE30 -> 77131.98 | AE31: =SUM(AA31:AD31) -> 77131.98 | AS31: =SUM(C31,I31,O31,U31,AA31,) -> 2150503.2 | AT31: =SUM(D31,J31,P31,V31,AB31,) -> 186455.43 | AU31: =SUM(E31,K31,Q31,W31,AC31,) -> 0 | AV31: =SUM(F31,L31,R31,X31,AD31,) -> -5552.87 | AX31: =SUM(G31,M31,S31,Y31,AE31,) -> 2331405.8 | AY31: =SUM(H31,N31,T31,Z31,AF31,) -> 6300000 | AZ31: =AX31+AY31 -> 8631405.8
B32: =B31+3 -> 44207 | C32: =G31 -> 822370.41 | D32: 461960.48 | F32: -299985.12 | G32: =SUM(C32:F32) -> 984345.77 | H32: 3800000 | I32: =M31 -> 612522.83 | L32: -82130.02 | M32: =SUM(I32:L32) -> 530392.81 | N32: 2500000 | O32: =S31 -> 360325.54 | R32: -1440 | S32: =SUM(O32:R32) -> 358885.54 | U32: =Y31 -> 459054.99 | V32: 57042.31 | Y32: =SUM(U32:X32) -> 516097.3 | AA32: =AE31 -> 77131.98 | AD32: -8531.53 | AE32: =SUM(AA32:AD32) -> 68600.45 | AS32: =SUM(C32,I32,O32,U32,AA32,) -> 2331405.8 | AT32: =SUM(D32,J32,P32,V32,AB32,) -> 519002.79 | AU32: =SUM(E32,K32,Q32,W32,AC32,) -> 0 | AV32: =SUM(F32,L32,R32,X32,AD32,) -> -392086.67 | AX32: =SUM(G32,M32,S32,Y32,AE32,) -> 2458321.9 | AY32: =SUM(H32,N32,T32,Z32,AF32,) -> 6300000 | AZ32: =AX32+AY32 -> 8758321.9
B33: =B32+1 -> 44208 | C33: =G32 -> 984345.77 | D33: 244010 | F33: -46159.84 | G33: =SUM(C33:F33) -> 1182195.9 | H33: 3800000 | I33: =M32 -> 530392.81 | J33: 94050.03 | L33: -60294.29 | M33: =SUM(I33:L33) -> 564148.55 | N33: 2500000 | O33: =S32 -> 358885.54 | Q33: 516000 | S33: =SUM(O33:R33) -> 874885.54 | U33: =Y32 -> 516097.3 | W33: -516000 | Y33: =SUM(U33:X33) -> 97.3 | AA33: =AE32 -> 68600.45 | AD33: -7566.43 | AE33: =SUM(AA33:AD33) -> 61034.02 | AS33: =SUM(C33,I33,O33,U33,AA33,) -> 2458321.9 | AT33: =SUM(D33,J33,P33,V33,AB33,) -> 338060.03 | AU33: =SUM(E33,K33,Q33,W33,AC33,) -> 0 | AV33: =SUM(F33,L33,R33,X33,AD33,) -> -114020.56 | AX33: =SUM(G33,M33,S33,Y33,AE33,) -> 2682361.3 | AY33: =SUM(H33,N33,T33,Z33,AF33,) -> 6300000 | AZ33: =AX33+AY33 -> 8982361.3
B34: =B33+1 -> 44209 | C34: =G33 -> 1182195.9 | D34: 142960.28 | E34: =800000-300000 -> 500000 | F34: -2692.59 | G34: =SUM(C34:F34) -> 1822463.6 | H34: 3800000 | I34: =M33 -> 564148.55 | L34: -4559.35 | M34: =SUM(I34:L34) -> 559589.2 | N34: 2500000 | O34: =S33 -> 874885.54 | Q34: -800000 | S34: =SUM(O34:R34) -> 74885.54 | U34: =Y33 -> 97.3 | Y34: =SUM(U34:X34) -> 97.3 | AA34: =AE33 -> 61034.02 | AC34: 300000 | AD34: -435 | AE34: =SUM(AA34:AD34) -> 360599.02 | AS34: =SUM(C34,I34,O34,U34,AA34,) -> 2682361.3 | AT34: =SUM(D34,J34,P34,V34,AB34,) -> 142960.28 | AU34: =SUM(E34,K34,Q34,W34,AC34,) -> 0 | AV34: =SUM(F34,L34,R34,X34,AD34,) -> -7686.94 | AX34: =SUM(G34,M34,S34,Y34,AE34,) -> 2817634.7 | AY34: =SUM(H34,N34,T34,Z34,AF34,) -> 6300000 | AZ34: =AX34+AY34 -> 9117634.7
B35: =B34+1 -> 44210 | C35: =G34 -> 1822463.6 | D35: 2406759.4 | F35: -5057.31 | G35: =SUM(C35:F35) -> 4224165.7 | H35: 3800000 | I35: =M34 -> 559589.2 | J35: 375.68 | L35: -58718.61 | M35: =SUM(I35:L35) -> 501246.27 | N35: 2500000 | O35: =S34 -> 74885.54 | P35: =188.16*2 -> 376.32 | S35: =SUM(O35:R35) -> 75261.86 | U35: =Y34 -> 97.3 | Y35: =SUM(U35:X35) -> 97.3 | AA35: =AE34 -> 360599.02 | AE35: =SUM(AA35:AD35) -> 360599.02 | AS35: =SUM(C35,I35,O35,U35,AA35,) -> 2817634.7 | AT35: =SUM(D35,J35,P35,V35,AB35,) -> 2407511.4 | AU35: =SUM(E35,K35,Q35,W35,AC35,) -> 0 | AV35: =SUM(F35,L35,R35,X35,AD35,) -> -63775.92 | AX35: =SUM(G35,M35,S35,Y35,AE35,) -> 5161370.1 | AY35: =SUM(H35,N35,T35,Z35,AF35,) -> 6300000 | AZ35: =AX35+AY35 -> 11461370
B36: =B35+1 -> 44211 | C36: =G35 -> 4224165.7 | D36: =2858.78 -> 2858.78 | F36: -3825.99 | G36: =SUM(C36:F36) -> 4223198.5 | H36: 3800000 | I36: =M35 -> 501246.27 | L36: -265899.16 | M36: =SUM(I36:L36) -> 235347.11 | N36: 2500000 | O36: =S35 -> 75261.86 | S36: =SUM(O36:R36) -> 75261.86 | U36: =Y35 -> 97.3 | Y36: =SUM(U36:X36) -> 97.3 | AA36: =AE35 -> 360599.02 | AE36: =SUM(AA36:AD36) -> 360599.02 | AS36: =SUM(C36,I36,O36,U36,AA36,) -> 5161370.1 | AT36: =SUM(D36,J36,P36,V36,AB36,) -> 2858.78 | AU36: =SUM(E36,K36,Q36,W36,AC36,) -> 0 | AV36: =SUM(F36,L36,R36,X36,AD36,) -> -269725.15 | AX36: =SUM(G36,M36,S36,Y36,AE36,) -> 4894503.8 | AY36: =SUM(H36,N36,T36,Z36,AF36,) -> 6300000 | AZ36: =AX36+AY36 -> 11194504
B37: =B36+3 -> 44214 | C37: =G36 -> 4223198.5 | D37: =44963.89+8658.6+11580.8 -> 65203.29 | F37: -13956.6 | G37: =SUM(C37:F37) -> 4274445.2 | H37: 3800000 | I37: =M36 -> 235347.11 | L37: -79739.64 | M37: =SUM(I37:L37) -> 155607.47 | N37: 2500000 | O37: =S36 -> 75261.86 | S37: =SUM(O37:R37) -> 75261.86 | U37: =Y36 -> 97.3 | Y37: =SUM(U37:X37) -> 97.3 | AA37: =AE36 -> 360599.02 | AD37: -158.36 | AE37: =SUM(AA37:AD37) -> 360440.66 | AS37: =SUM(C37,I37,O37,U37,AA37,) -> 4894503.8 | AT37: =SUM(D37,J37,P37,V37,AB37,) -> 65203.29 | AU37: =SUM(E37,K37,Q37,W37,AC37,) -> 0 | AV37: =SUM(F37,L37,R37,X37,AD37,) -> -93854.6 | AX37: =SUM(G37,M37,S37,Y37,AE37,) -> 4865852.4 | AY37: =SUM(H37,N37,T37,Z37,AF37,) -> 6300000 | AZ37: =AX37+AY37 -> 11165852
B38: =B37+1 -> 44215 | C38: =G37 -> 4274445.2 | D38: 35990.84 | F38: -490613.49 | G38: =SUM(C38:F38) -> 3819822.5 | H38: 3800000 | I38: =M37 -> 155607.47 | L38: -32668.15 | M38: =SUM(I38:L38) -> 122939.32 | N38: 2500000 | O38: =S37 -> 75261.86 | R38: =-632.4-348 -> -980.4 | S38: =SUM(O38:R38) -> 74281.46 | U38: =Y37 -> 97.3 | Y38: =SUM(U38:X38) -> 97.3 | AA38: =AE37 -> 360440.66 | AD38: -12797.53 | AE38: =SUM(AA38:AD38) -> 347643.13 | AS38: =SUM(C38,I38,O38,U38,AA38,) -> 4865852.4 | AT38: =SUM(D38,J38,P38,V38,AB38,) -> 35990.84 | AU38: =SUM(E38,K38,Q38,W38,AC38,) -> 0 | AV38: =SUM(F38,L38,R38,X38,AD38,) -> -537059.57 | AX38: =SUM(G38,M38,S38,Y38,AE38,) -> 4364783.7 | AY38: =SUM(H38,N38,T38,Z38,AF38,) -> 6300000 | AZ38: =AX38+AY38 -> 10664784
B39: =B38+1 -> 44216 | C39: =G38 -> 3819822.5 | F39: -994587.75 | G39: =SUM(C39:F39) -> 2825234.8 | H39: 3800000 | I39: =M38 -> 122939.32 | L39: -2694.53 | M39: =SUM(I39:L39) -> 120244.79 | N39: 2500000 | O39: =S38 -> 74281.46 | S39: =SUM(O39:R39) -> 74281.46 | U39: =Y38 -> 97.3 | Y39: =SUM(U39:X39) -> 97.3 | AA39: =AE38 -> 347643.13 | AD39: -20374.2 | AE39: =SUM(AA39:AD39) -> 327268.93 | AS39: =SUM(C39,I39,O39,U39,AA39,) -> 4364783.7 | AT39: =SUM(D39,J39,P39,V39,AB39,) -> 0 | AU39: =SUM(E39,K39,Q39,W39,AC39,) -> 0 | AV39: =SUM(F39,L39,R39,X39,AD39,) -> -1017656.5 | AX39: =SUM(G39,M39,S39,Y39,AE39,) -> 3347127.2 | AY39: =SUM(H39,N39,T39,Z39,AF39,) -> 6300000 | AZ39: =AX39+AY39 -> 9647127.2
B40: =B39+1 -> 44217 | C40: =G39 -> 2825234.8 | D40: =22692.82*2+84283.33 -> 129668.97 | F40: -204.25 | G40: =SUM(C40:F40) -> 2954699.5 | H40: 3800000 | I40: =M39 -> 120244.79 | L40: -23095.26 | M40: =SUM(I40:L40) -> 97149.53 | N40: 2500000 | O40: =S39 -> 74281.46 | S40: =SUM(O40:R40) -> 74281.46 | U40: =Y39 -> 97.3 | Y40: =SUM(U40:X40) -> 97.3 | AA40: =AE39 -> 327268.93 | AD40: -257401.79 | AE40: =SUM(AA40:AD40) -> 69867.14 | AS40: =SUM(C40,I40,O40,U40,AA40,) -> 3347127.2 | AT40: =SUM(D40,J40,P40,V40,AB40,) -> 129668.97 | AU40: =SUM(E40,K40,Q40,W40,AC40,) -> 0 | AV40: =SUM(F40,L40,R40,X40,AD40,) -> -280701.3 | AX40: =SUM(G40,M40,S40,Y40,AE40,) -> 3196094.9 | AY40: =SUM(H40,N40,T40,Z40,AF40,) -> 6300000 | AZ40: =AX40+AY40 -> 9496094.9
B41: =B40+1 -> 44218 | C41: =G40 -> 2954699.5 | D41: 129429.97 | F41: -83051.9 | G41: =SUM(C41:F41) -> 3001077.5 | H41: 3800000 | I41: =M40 -> 97149.53 | J41: 32810.62 | M41: =SUM(I41:L41) -> 129960.15 | N41: 2500000 | O41: =S40 -> 74281.46 | S41: =SUM(O41:R41) -> 74281.46 | U41: =Y40 -> 97.3 | Y41: =SUM(U41:X41) -> 97.3 | AA41: =AE40 -> 69867.14 | AE41: =SUM(AA41:AD41) -> 69867.14 | AS41: =SUM(C41,I41,O41,U41,AA41,) -> 3196094.9 | AT41: =SUM(D41,J41,P41,V41,AB41,) -> 162240.59 | AU41: =SUM(E41,K41,Q41,W41,AC41,) -> 0 | AV41: =SUM(F41,L41,R41,X41,AD41,) -> -83051.9 | AX41: =SUM(G41,M41,S41,Y41,AE41,) -> 3275283.6 | AY41: =SUM(H41,N41,T41,Z41,AF41,) -> 6300000 | AZ41: =AX41+AY41 -> 9575283.6
B42: =B41+3 -> 44221 | C42: =G41 -> 3001077.5 | F42: -385062.3 | G42: =SUM(C42:F42) -> 2616015.2 | H42: 3800000 | I42: =M41 -> 129960.15 | L42: -41119.32 | M42: =SUM(I42:L42) -> 88840.83 | N42: 2500000 | O42: =S41 -> 74281.46 | R42: -84 | S42: =SUM(O42:R42) -> 74197.46 | U42: =Y41 -> 97.3 | Y42: =SUM(U42:X42) -> 97.3 | AA42: =AE41 -> 69867.14 | AD42: -97.91 | AE42: =SUM(AA42:AD42) -> 69769.23 | AS42: =SUM(C42,I42,O42,U42,AA42,) -> 3275283.6 | AT42: =SUM(D42,J42,P42,V42,AB42,) -> 0 | AU42: =SUM(E42,K42,Q42,W42,AC42,) -> 0 | AV42: =SUM(F42,L42,R42,X42,AD42,) -> -426363.53 | AX42: =SUM(G42,M42,S42,Y42,AE42,) -> 2848920.1 | AY42: =SUM(H42,N42,T42,Z42,AF42,) -> 6300000 | AZ42: =AX42+AY42 -> 9148920.1
B43: =B42+1 -> 44222 | C43: =G42 -> 2616015.2 | F43: -500487.56 | G43: =SUM(C43:F43) -> 2115527.7 | H43: 3800000 | I43: =M42 -> 88840.83 | L43: -14033.65 | M43: =SUM(I43:L43) -> 74807.18 | N43: 2500000 | O43: =S42 -> 74197.46 | R43: -2000 | S43: =SUM(O43:R43) -> 72197.46 | U43: =Y42 -> 97.3 | Y43: =SUM(U43:X43) -> 97.3 | AA43: =AE42 -> 69769.23 | AD43: -795.85 | AE43: =SUM(AA43:AD43) -> 68973.38 | AS43: =SUM(C43,I43,O43,U43,AA43,) -> 2848920.1 | AT43: =SUM(D43,J43,P43,V43,AB43,) -> 0 | AU43: =SUM(E43,K43,Q43,W43,AC43,) -> 0 | AV43: =SUM(F43,L43,R43,X43,AD43,) -> -517317.06 | AX43: =SUM(G43,M43,S43,Y43,AE43,) -> 2331603 | AY43: =SUM(H43,N43,T43,Z43,AF43,) -> 6300000 | AZ43: =AX43+AY43 -> 8631603
B44: =B43+1 -> 44223 | C44: =G43 -> 2115527.7 | D44: 6627.66 | G44: =SUM(C44:F44) -> 2122155.3 | H44: 3800000 | I44: =M43 -> 74807.18 | L44: -165 | M44: =SUM(I44:L44) -> 74642.18 | N44: 2500000 | O44: =S43 -> 72197.46 | R44: -3875.75 | S44: =SUM(O44:R44) -> 68321.71 | U44: =Y43 -> 97.3 | Y44: =SUM(U44:X44) -> 97.3 | AA44: =AE43 -> 68973.38 | AB44: 0.72 | AE44: =SUM(AA44:AD44) -> 68974.1 | AS44: =SUM(C44,I44,O44,U44,AA44,) -> 2331603 | AT44: =SUM(D44,J44,P44,V44,AB44,) -> 6628.38 | AU44: =SUM(E44,K44,Q44,W44,AC44,) -> 0 | AV44: =SUM(F44,L44,R44,X44,AD44,) -> -4040.75 | AX44: =SUM(G44,M44,S44,Y44,AE44,) -> 2334190.6 | AY44: =SUM(H44,N44,T44,Z44,AF44,) -> 6300000 | AZ44: =AX44+AY44 -> 8634190.6
B45: =B44+1 -> 44224 | C45: =G44 -> 2122155.3 | D45: 5.68 | G45: =SUM(C45:F45) -> 2122161 | H45: 3800000 | I45: =M44 -> 74642.18 | L45: -56695.58 | M45: =SUM(I45:L45) -> 17946.6 | N45: 2500000 | O45: =S44 -> 68321.71 | S45: =SUM(O45:R45) -> 68321.71 | U45: =Y44 -> 97.3 | Y45: =SUM(U45:X45) -> 97.3 | AA45: =AE44 -> 68974.1 | AE45: =SUM(AA45:AD45) -> 68974.1 | AS45: =SUM(C45,I45,O45,U45,AA45,) -> 2334190.6 | AT45: =SUM(D45,J45,P45,V45,AB45,) -> 5.68 | AU45: =SUM(E45,K45,Q45,W45,AC45,) -> 0 | AV45: =SUM(F45,L45,R45,X45,AD45,) -> -56695.58 | AX45: =SUM(G45,M45,S45,Y45,AE45,) -> 2277500.7 | AY45: =SUM(H45,N45,T45,Z45,AF45,) -> 6300000 | AZ45: =AX45+AY45 -> 8577500.7
B46: =B45+1 -> 44225 | C46: =G45 -> 2122161 | D46: 27759.97 | F46: -16683 | G46: =SUM(C46:F46) -> 2133238 | H46: 3800000 | I46: =M45 -> 17946.6 | J46: 445819.75 | L46: -15000 | M46: =SUM(I46:L46) -> 448766.35 | N46: 2500000 | O46: =S45 -> 68321.71 | S46: =SUM(O46:R46) -> 68321.71 | U46: =Y45 -> 97.3 | V46: 22646.46 | Y46: =SUM(U46:X46) -> 22743.76 | AA46: =AE45 -> 68974.1 | AE46: =SUM(AA46:AD46) -> 68974.1 | AS46: =SUM(C46,I46,O46,U46,AA46,) -> 2277500.7 | AT46: =SUM(D46,J46,P46,V46,AB46,) -> 496226.18 | AU46: =SUM(E46,K46,Q46,W46,AC46,) -> 0 | AV46: =SUM(F46,L46,R46,X46,AD46,) -> -31683 | AX46: =SUM(G46,M46,S46,Y46,AE46,) -> 2742043.9 | AY46: =SUM(H46,N46,T46,Z46,AF46,) -> 6300000 | AZ46: =AX46+AY46 -> 9042043.9
B47: =B46+3 -> 44228 | C47: =G46 -> 2133238 | D47: 79324 | E47: -1840000 | F47: -138245.03 | G47: =SUM(C47:F47) -> 234316.96 | H47: 3800000 | I47: =M46 -> 448766.35 | J47: 68805.48 | K47: 1840000 | L47: -2325008.4 | M47: =SUM(I47:L47) -> 32563.47 | N47: 2500000 | O47: =S46 -> 68321.71 | P47: 23427.69 | R47: -7167.99 | S47: =SUM(O47:R47) -> 84581.41 | U47: =Y46 -> 22743.76 | V47: 384519.4 | Y47: =SUM(U47:X47) -> 407263.16 | AA47: =AE46 -> 68974.1 | AE47: =SUM(AA47:AD47) -> 68974.1 | AS47: =SUM(C47,I47,O47,U47,AA47,) -> 2742043.9 | AT47: =SUM(D47,J47,P47,V47,AB47,) -> 556076.57 | AU47: =SUM(E47,K47,Q47,W47,AC47,) -> 0 | AV47: =SUM(F47,L47,R47,X47,AD47,) -> -2470421.4 | AX47: =SUM(G47,M47,S47,Y47,AE47,) -> 827699.1 | AY47: =SUM(H47,N47,T47,Z47,AF47,) -> 6300000 | AZ47: =AX47+AY47 -> 7127699.1
B48: =B47+1 -> 44229 | C48: =G47 -> 234316.96 | E48: =460000-230000 -> 230000 | F48: -104466.66 | G48: =SUM(C48:F48) -> 359850.3 | H48: 3800000 | I48: =M47 -> 32563.47 | J48: 103.01 | K48: 230000 | L48: -260291.31 | M48: =SUM(I48:L48) -> 2375.17 | N48: 2500000 | O48: =S47 -> 84581.41 | Q48: =407000-460000 -> -53000 | R48: -24075.53 | S48: =SUM(O48:R48) -> 7505.88 | U48: =Y47 -> 407263.16 | W48: -407000 | X48: -54.95 | Y48: =SUM(U48:X48) -> 208.21 | AA48: =AE47 -> 68974.1 | AD48: -39063.98 | AE48: =SUM(AA48:AD48) -> 29910.12 | AS48: =SUM(C48,I48,O48,U48,AA48,) -> 827699.1 | AT48: =SUM(D48,J48,P48,V48,AB48,) -> 103.01 | AU48: =SUM(E48,K48,Q48,W48,AC48,) -> 0 | AV48: =SUM(F48,L48,R48,X48,AD48,) -> -427952.43 | AX48: =SUM(G48,M48,S48,Y48,AE48,) -> 399849.68 | AY48: =SUM(H48,N48,T48,Z48,AF48,) -> 6300000 | AZ48: =AX48+AY48 -> 6699849.7
B49: =B48+1 -> 44230 | C49: =G48 -> 359850.3 | D49: 237406.72 | G49: =SUM(C49:F49) -> 597257.02 | H49: 3800000 | I49: =M48 -> 2375.17 | J49: 47155.87 | M49: =SUM(I49:L49) -> 49531.04 | N49: 2500000 | O49: =S48 -> 7505.88 | P49: 220674.3 | S49: =SUM(O49:R49) -> 228180.18 | U49: =Y48 -> 208.21 | X49: -1.2 | Y49: =SUM(U49:X49) -> 207.01 | AA49: =AE48 -> 29910.12 | AE49: =SUM(AA49:AD49) -> 29910.12 | AS49: =SUM(C49,I49,O49,U49,AA49,) -> 399849.68 | AT49: =SUM(D49,J49,P49,V49,AB49,) -> 505236.89 | AU49: =SUM(E49,K49,Q49,W49,AC49,) -> 0 | AV49: =SUM(F49,L49,R49,X49,AD49,) -> -1.2 | AX49: =SUM(G49,M49,S49,Y49,AE49,) -> 905085.37 | AY49: =SUM(H49,N49,T49,Z49,AF49,) -> 6300000 | AZ49: =AX49+AY49 -> 7205085.4
B50: =B49+1 -> 44231 | C50: =G49 -> 597257.02 | D50: 61364.69 | F50: -16253.06 | G50: =SUM(C50:F50) -> 642368.65 | H50: 3800000 | I50: =M49 -> 49531.04 | L50: -19201.99 | M50: =SUM(I50:L50) -> 30329.05 | N50: 2500000 | O50: =S49 -> 228180.18 | S50: =SUM(O50:R50) -> 228180.18 | U50: =Y49 -> 207.01 | Y50: =SUM(U50:X50) -> 207.01 | AA50: =AE49 -> 29910.12 | AE50: =SUM(AA50:AD50) -> 29910.12 | AS50: =SUM(C50,I50,O50,U50,AA50,) -> 905085.37 | AT50: =SUM(D50,J50,P50,V50,AB50,) -> 61364.69 | AU50: =SUM(E50,K50,Q50,W50,AC50,) -> 0 | AV50: =SUM(F50,L50,R50,X50,AD50,) -> -35455.05 | AX50: =SUM(G50,M50,S50,Y50,AE50,) -> 930995.01 | AY50: =SUM(H50,N50,T50,Z50,AF50,) -> 6300000 | AZ50: =AX50+AY50 -> 7230995
B51: =B50+1 -> 44232 | C51: =G50 -> 642368.65 | E51: 220000 | F51: -298604.46 | G51: =SUM(C51:F51) -> 563764.19 | H51: 3800000 | I51: =M50 -> 30329.05 | J51: 38956 | L51: -7308.36 | M51: =SUM(I51:L51) -> 61976.69 | N51: 2500000 | O51: =S50 -> 228180.18 | Q51: -220000 | R51: =-10.45-27 -> -37.45 | S51: =SUM(O51:R51) -> 8142.73 | U51: =Y50 -> 207.01 | Y51: =SUM(U51:X51) -> 207.01 | AA51: =AE50 -> 29910.12 | AE51: =SUM(AA51:AD51) -> 29910.12 | AS51: =SUM(C51,I51,O51,U51,AA51,) -> 930995.01 | AT51: =SUM(D51,J51,P51,V51,AB51,) -> 38956 | AU51: =SUM(E51,K51,Q51,W51,AC51,) -> 0 | AV51: =SUM(F51,L51,R51,X51,AD51,) -> -305950.27 | AX51: =SUM(G51,M51,S51,Y51,AE51,) -> 664000.74 | AY51: =SUM(H51,N51,T51,Z51,AF51,) -> 6300000 | AZ51: =AX51+AY51 -> 6964000.7
B52: =B51+3 -> 44235 | C52: =G51 -> 563764.19 | D52: 8894.54 | F52: -366045.06 | G52: =SUM(C52:F52) -> 206613.67 | H52: 3800000 | I52: =M51 -> 61976.69 | L52: -47501.51 | M52: =SUM(I52:L52) -> 14475.18 | N52: 2500000 | O52: =S51 -> 8142.73 | Q52: 43000 | S52: =SUM(O52:R52) -> 51142.73 | U52: =Y51 -> 207.01 | V52: 43103.43 | W52: -43000 | Y52: =SUM(U52:X52) -> 310.44 | AA52: =AE51 -> 29910.12 | AE52: =SUM(AA52:AD52) -> 29910.12 | AS52: =SUM(C52,I52,O52,U52,AA52,) -> 664000.74 | AT52: =SUM(D52,J52,P52,V52,AB52,) -> 51997.97 | AU52: =SUM(E52,K52,Q52,W52,AC52,) -> 0 | AV52: =SUM(F52,L52,R52,X52,AD52,) -> -413546.57 | AX52: =SUM(G52,M52,S52,Y52,AE52,) -> 302452.14 | AY52: =SUM(H52,N52,T52,Z52,AF52,) -> 6300000 | AZ52: =AX52+AY52 -> 6602452.1
B53: =B52+1 -> 44236 | C53: =G52 -> 206613.67 | D53: 208003.41 | E53: -100000 | F53: =-108002.75+55467.2 -> -52535.55 | G53: =SUM(C53:F53) -> 262081.53 | H53: 3800000 | I53: =M52 -> 14475.18 | J53: 375 | K53: 100000 | L53: -88510.34 | M53: =SUM(I53:L53) -> 26339.84 | N53: 2500000 | O53: =S52 -> 51142.73 | R53: -15130.02 | S53: =SUM(O53:R53) -> 36012.71 | U53: =Y52 -> 310.44 | X53: -1.2 | Y53: =SUM(U53:X53) -> 309.24 | AA53: =AE52 -> 29910.12 | AD53: -1976.1 | AE53: =SUM(AA53:AD53) -> 27934.02 | AS53: =SUM(C53,I53,O53,U53,AA53,) -> 302452.14 | AT53: =SUM(D53,J53,P53,V53,AB53,) -> 208378.41 | AU53: =SUM(E53,K53,Q53,W53,AC53,) -> 0 | AV53: =SUM(F53,L53,R53,X53,AD53,) -> -158153.21 | AX53: =SUM(G53,M53,S53,Y53,AE53,) -> 352677.34 | AY53: =SUM(H53,N53,T53,Z53,AF53,) -> 6300000 | AZ53: =AX53+AY53 -> 6652677.3
B54: =B53+1 -> 44237 | C54: =G53 -> 262081.53 | D54: 699965.96 | F54: -44281.21 | G54: =SUM(C54:F54) -> 917766.28 | H54: 3800000 | I54: =M53 -> 26339.84 | J54: 557.32 | M54: =SUM(I54:L54) -> 26897.16 | N54: 2500000 | O54: =S53 -> 36012.71 | P54: 65.06 | S54: =SUM(O54:R54) -> 36077.77 | U54: =Y53 -> 309.24 | Y54: =SUM(U54:X54) -> 309.24 | AA54: =AE53 -> 27934.02 | AD54: -293.85 | AE54: =SUM(AA54:AD54) -> 27640.17 | AS54: =SUM(C54,I54,O54,U54,AA54,) -> 352677.34 | AT54: =SUM(D54,J54,P54,V54,AB54,) -> 700588.34 | AU54: =SUM(E54,K54,Q54,W54,AC54,) -> 0 | AV54: =SUM(F54,L54,R54,X54,AD54,) -> -44575.06 | AX54: =SUM(G54,M54,S54,Y54,AE54,) -> 1008690.6 | AY54: =SUM(H54,N54,T54,Z54,AF54,) -> 6300000 | AZ54: =AX54+AY54 -> 7308690.6
B55: =B54+1 -> 44238 | C55: =G54 -> 917766.28 | D55: 2093799.7 | E55: -100000 | F55: -4025.52 | G55: =SUM(C55:F55) -> 2907540.5 | H55: 3800000 | I55: =M54 -> 26897.16 | K55: 100000 | L55: -24914.89 | M55: =SUM(I55:L55) -> 101982.27 | N55: 2500000 | O55: =S54 -> 36077.77 | S55: =SUM(O55:R55) -> 36077.77 | U55: =Y54 -> 309.24 | Y55: =SUM(U55:X55) -> 309.24 | AA55: =AE54 -> 27640.17 | AE55: =SUM(AA55:AD55) -> 27640.17 | AS55: =SUM(C55,I55,O55,U55,AA55,) -> 1008690.6 | AT55: =SUM(D55,J55,P55,V55,AB55,) -> 2093799.7 | AU55: =SUM(E55,K55,Q55,W55,AC55,) -> 0 | AV55: =SUM(F55,L55,R55,X55,AD55,) -> -28940.41 | AX55: =SUM(G55,M55,S55,Y55,AE55,) -> 3073549.9 | AY55: =SUM(H55,N55,T55,Z55,AF55,) -> 6300000 | AZ55: =AX55+AY55 -> 9373549.9
B56: =B55+1 -> 44239 | C56: =G55 -> 2907540.5 | E56: -250000 | F56: -20507.82 | G56: =SUM(C56:F56) -> 2637032.6 | H56: 3800000 | I56: =M55 -> 101982.27 | K56: 250000 | L56: -303399.09 | M56: =SUM(I56:L56) -> 48583.18 | N56: 2500000 | O56: =S55 -> 36077.77 | P56: 1027 | S56: =SUM(O56:R56) -> 37104.77 | U56: =Y55 -> 309.24 | Y56: =SUM(U56:X56) -> 309.24 | AA56: =AE55 -> 27640.17 | AD56: -680 | AE56: =SUM(AA56:AD56) -> 26960.17 | AS56: =SUM(C56,I56,O56,U56,AA56,) -> 3073549.9 | AT56: =SUM(D56,J56,P56,V56,AB56,) -> 1027 | AU56: =SUM(E56,K56,Q56,W56,AC56,) -> 0 | AV56: =SUM(F56,L56,R56,X56,AD56,) -> -324586.91 | AX56: =SUM(G56,M56,S56,Y56,AE56,) -> 2749990 | AY56: =SUM(H56,N56,T56,Z56,AF56,) -> 6300000 | AZ56: =AX56+AY56 -> 9049990
B57: =B56+3 -> 44242 | C57: =G56 -> 2637032.6 | G57: =SUM(C57:F57) -> 2637032.6 | H57: 3800000 | I57: =M56 -> 48583.18 | M57: =SUM(I57:L57) -> 48583.18 | N57: 2500000 | O57: =S56 -> 37104.77 | S57: =SUM(O57:R57) -> 37104.77 | U57: =Y56 -> 309.24 | Y57: =SUM(U57:X57) -> 309.24 | AA57: =AE56 -> 26960.17 | AE57: =SUM(AA57:AD57) -> 26960.17 | AS57: =SUM(C57,I57,O57,U57,AA57,) -> 2749990 | AT57: =SUM(D57,J57,P57,V57,AB57,) -> 0 | AU57: =SUM(E57,K57,Q57,W57,AC57,) -> 0 | AV57: =SUM(F57,L57,R57,X57,AD57,) -> 0 | AX57: =SUM(G57,M57,S57,Y57,AE57,) -> 2749990 | AY57: =SUM(H57,N57,T57,Z57,AF57,) -> 6300000 | AZ57: =AX57+AY57 -> 9049990
B58: =B57+1 -> 44243 | C58: =G57 -> 2637032.6 | G58: =SUM(C58:F58) -> 2637032.6 | H58: 3800000 | I58: =M57 -> 48583.18 | M58: =SUM(I58:L58) -> 48583.18 | N58: 2500000 | O58: =S57 -> 37104.77 | R58: -4942.37 | S58: =SUM(O58:R58) -> 32162.4 | U58: =Y57 -> 309.24 | Y58: =SUM(U58:X58) -> 309.24 | AA58: =AE57 -> 26960.17 | AE58: =SUM(AA58:AD58) -> 26960.17 | AS58: =SUM(C58,I58,O58,U58,AA58,) -> 2749990 | AT58: =SUM(D58,J58,P58,V58,AB58,) -> 0 | AU58: =SUM(E58,K58,Q58,W58,AC58,) -> 0 | AV58: =SUM(F58,L58,R58,X58,AD58,) -> -4942.37 | AX58: =SUM(G58,M58,S58,Y58,AE58,) -> 2745047.6 | AY58: =SUM(H58,N58,T58,Z58,AF58,) -> 6300000 | AZ58: =AX58+AY58 -> 9045047.6
B59: =B58+1 -> 44244 | C59: =G58 -> 2637032.6 | D59: =35990.84+96121.46 -> 132112.3 | E59: -280000 | F59: =-320470.23+280000 -> -40470.23 | G59: =SUM(C59:F59) -> 2448674.7 | H59: 3800000 | I59: =M58 -> 48583.18 | K59: 280000 | L59: -319403.29 | M59: =SUM(I59:L59) -> 9179.89 | N59: 2500000 | O59: =S58 -> 32162.4 | P59: =2122.44 -> 2122.44 | R59: =-7784.74+1233.04 -> -6551.7 | S59: =SUM(O59:R59) -> 27733.14 | U59: =Y58 -> 309.24 | Y59: =SUM(U59:X59) -> 309.24 | AA59: =AE58 -> 26960.17 | AD59: -393.21 | AE59: =SUM(AA59:AD59) -> 26566.96 | AS59: =SUM(C59,I59,O59,U59,AA59,) -> 2745047.6 | AT59: =SUM(D59,J59,P59,V59,AB59,) -> 134234.74 | AU59: =SUM(E59,K59,Q59,W59,AC59,) -> 0 | AV59: =SUM(F59,L59,R59,X59,AD59,) -> -366818.43 | AX59: =SUM(G59,M59,S59,Y59,AE59,) -> 2512463.9 | AY59: =SUM(H59,N59,T59,Z59,AF59,) -> 6300000 | AZ59: =AX59+AY59 -> 8812463.9
B60: =B59+1 -> 44245 | C60: =G59 -> 2448674.7 | F60: -16460.95 | G60: =SUM(C60:F60) -> 2432213.8 | H60: 3800000 | I60: =M59 -> 9179.89 | J60: 242903.51 | L60: -11589.74 | M60: =SUM(I60:L60) -> 240493.66 | N60: 2500000 | O60: =S59 -> 27733.14 | S60: =SUM(O60:R60) -> 27733.14 | U60: =Y59 -> 309.24 | Y60: =SUM(U60:X60) -> 309.24 | AA60: =AE59 -> 26566.96 | AE60: =SUM(AA60:AD60) -> 26566.96 | AS60: =SUM(C60,I60,O60,U60,AA60,) -> 2512463.9 | AT60: =SUM(D60,J60,P60,V60,AB60,) -> 242903.51 | AU60: =SUM(E60,K60,Q60,W60,AC60,) -> 0 | AV60: =SUM(F60,L60,R60,X60,AD60,) -> -28050.69 | AX60: =SUM(G60,M60,S60,Y60,AE60,) -> 2727316.8 | AY60: =SUM(H60,N60,T60,Z60,AF60,) -> 6300000 | AZ60: =AX60+AY60 -> 9027316.8
B61: =B60+1 -> 44246 | C61: =G60 -> 2432213.8 | D61: 117730.02 | E61: -250000 | F61: -742881.34 | G61: =SUM(C61:F61) -> 1557062.4 | H61: 3800000 | I61: =M60 -> 240493.66 | L61: -10231.8 | M61: =SUM(I61:L61) -> 230261.86 | N61: 2500000 | O61: =S60 -> 27733.14 | P61: 30642.58 | S61: =SUM(O61:R61) -> 58375.72 | U61: =Y60 -> 309.24 | Y61: =SUM(U61:X61) -> 309.24 | AA61: =AE60 -> 26566.96 | AC61: 250000.23 | AE61: =SUM(AA61:AD61) -> 276567.19 | AS61: =SUM(C61,I61,O61,U61,AA61,) -> 2727316.8 | AT61: =SUM(D61,J61,P61,V61,AB61,) -> 148372.6 | AU61: =SUM(E61,K61,Q61,W61,AC61,) -> 0.23 | AV61: =SUM(F61,L61,R61,X61,AD61,) -> -753113.14 | AX61: =SUM(G61,M61,S61,Y61,AE61,) -> 2122576.5 | AY61: =SUM(H61,N61,T61,Z61,AF61,) -> 6300000 | AZ61: =AX61+AY61 -> 8422576.5
B62: =B61+3 -> 44249 | C62: =G61 -> 1557062.4 | D62: 112133.82 | F62: -1290053.5 | G62: =SUM(C62:F62) -> 379142.79 | H62: 3800000 | I62: =M61 -> 230261.86 | L62: -41286.31 | M62: =SUM(I62:L62) -> 188975.55 | N62: 2500000 | O62: =S61 -> 58375.72 | P62: 1982.51 | S62: =SUM(O62:R62) -> 60358.23 | U62: =Y61 -> 309.24 | Y62: =SUM(U62:X62) -> 309.24 | AA62: =AE61 -> 276567.19 | AD62: -254934.89 | AE62: =SUM(AA62:AD62) -> 21632.3 | AS62: =SUM(C62,I62,O62,U62,AA62,) -> 2122576.5 | AT62: =SUM(D62,J62,P62,V62,AB62,) -> 114116.33 | AU62: =SUM(E62,K62,Q62,W62,AC62,) -> 0 | AV62: =SUM(F62,L62,R62,X62,AD62,) -> -1586274.7 | AX62: =SUM(G62,M62,S62,Y62,AE62,) -> 650418.11 | AY62: =SUM(H62,N62,T62,Z62,AF62,) -> 6300000 | AZ62: =AX62+AY62 -> 6950418.1
B63: =B62+1 -> 44250 | C63: =G62 -> 379142.79 | D63: =59494.01+67808.64 -> 127302.65 | F63: -537891.26 | G63: =SUM(C63:F63) -> -31445.82 | H63: 3800000 | I63: =M62 -> 188975.55 | L63: -3772.5 | M63: =SUM(I63:L63) -> 185203.05 | N63: 2500000 | O63: =S62 -> 60358.23 | R63: -35 | S63: =SUM(O63:R63) -> 60323.23 | U63: =Y62 -> 309.24 | Y63: =SUM(U63:X63) -> 309.24 | AA63: =AE62 -> 21632.3 | AE63: =SUM(AA63:AD63) -> 21632.3 | AS63: =SUM(C63,I63,O63,U63,AA63,) -> 650418.11 | AT63: =SUM(D63,J63,P63,V63,AB63,) -> 127302.65 | AU63: =SUM(E63,K63,Q63,W63,AC63,) -> 0 | AV63: =SUM(F63,L63,R63,X63,AD63,) -> -541698.76 | AX63: =SUM(G63,M63,S63,Y63,AE63,) -> 236022 | AY63: =SUM(H63,N63,T63,Z63,AF63,) -> 6300000 | AZ63: =AX63+AY63 -> 6536022
B64: =B63+1 -> 44251 | C64: =G63 -> -31445.82 | D64: 61751.79 | E64: 200000 | F64: -81130.89 | G64: =SUM(C64:F64) -> 149175.08 | H64: 3800000 | I64: =M63 -> 185203.05 | J64: 1073980.7 | K64: -200000 | L64: =-23056.13-6.87 -> -23063 | M64: =SUM(I64:L64) -> 1036120.8 | N64: 2500000 | O64: =S63 -> 60323.23 | R64: -14296.27 | S64: =SUM(O64:R64) -> 46026.96 | U64: =Y63 -> 309.24 | Y64: =SUM(U64:X64) -> 309.24 | AA64: =AE63 -> 21632.3 | AE64: =SUM(AA64:AD64) -> 21632.3 | AS64: =SUM(C64,I64,O64,U64,AA64,) -> 236022 | AT64: =SUM(D64,J64,P64,V64,AB64,) -> 1135732.5 | AU64: =SUM(E64,K64,Q64,W64,AC64,) -> 0 | AV64: =SUM(F64,L64,R64,X64,AD64,) -> -118490.16 | AX64: =SUM(G64,M64,S64,Y64,AE64,) -> 1253264.4 | AY64: =SUM(H64,N64,T64,Z64,AF64,) -> 6300000 | AZ64: =AX64+AY64 -> 7553264.4
B65: =B64+1 -> 44252 | C65: =G64 -> 149175.08 | D65: 236468.33 | F65: -39955.71 | G65: =SUM(C65:F65) -> 345687.7 | H65: 3800000 | I65: =M64 -> 1036120.8 | L65: -60110.27 | M65: =SUM(I65:L65) -> 976010.52 | N65: 2500000 | O65: =S64 -> 46026.96 | P65: 880.1 | R65: -136.35 | S65: =SUM(O65:R65) -> 46770.71 | U65: =Y64 -> 309.24 | Y65: =SUM(U65:X65) -> 309.24 | AA65: =AE64 -> 21632.3 | AE65: =SUM(AA65:AD65) -> 21632.3 | AS65: =SUM(C65,I65,O65,U65,AA65,) -> 1253264.4 | AT65: =SUM(D65,J65,P65,V65,AB65,) -> 237348.43 | AU65: =SUM(E65,K65,Q65,W65,AC65,) -> 0 | AV65: =SUM(F65,L65,R65,X65,AD65,) -> -100202.33 | AX65: =SUM(G65,M65,S65,Y65,AE65,) -> 1390410.5 | AY65: =SUM(H65,N65,T65,Z65,AF65,) -> 6300000 | AZ65: =AX65+AY65 -> 7690410.5
B66: =B65+1 -> 44253 | C66: =G65 -> 345687.7 | F66: -61346.01 | G66: =SUM(C66:F66) -> 284341.69 | H66: 3800000 | I66: =M65 -> 976010.52 | J66: 427343.52 | L66: -13909.42 | M66: =SUM(I66:L66) -> 1389444.6 | N66: 2500000 | O66: =S65 -> 46770.71 | P66: 2074.44 | Q66: 100 | S66: =SUM(O66:R66) -> 48945.15 | U66: =Y65 -> 309.24 | X66: -100 | Y66: =SUM(U66:X66) -> 209.24 | AA66: =AE65 -> 21632.3 | AE66: =SUM(AA66:AD66) -> 21632.3 | AS66: =SUM(C66,I66,O66,U66,AA66,) -> 1390410.5 | AT66: =SUM(D66,J66,P66,V66,AB66,) -> 429417.96 | AU66: =SUM(E66,K66,Q66,W66,AC66,) -> 100 | AV66: =SUM(F66,L66,R66,X66,AD66,) -> -75355.43 | AX66: =SUM(G66,M66,S66,Y66,AE66,) -> 1744573 | AY66: =SUM(H66,N66,T66,Z66,AF66,) -> 6300000 | AZ66: =AX66+AY66 -> 8044573
B67: =B66+3 -> 44256 | C67: =G66 -> 284341.69 | D67: 204099.89 | E67: -500000 | F67: -178389.12 | G67: =SUM(C67:F67) -> -189947.54 | H67: 4300000 | I67: =M66 -> 1389444.6 | J67: 258.35 | K67: 500000 | L67: -1785113.2 | M67: =SUM(I67:L67) -> 104589.78 | N67: 4000000 | O67: =S66 -> 48945.15 | P67: 3838.06 | S67: =SUM(O67:R67) -> 52783.21 | U67: =Y66 -> 209.24 | X67: -1.2 | Y67: =SUM(U67:X67) -> 208.04 | AA67: =AE66 -> 21632.3 | AE67: =SUM(AA67:AD67) -> 21632.3 | AS67: =SUM(C67,I67,O67,U67,AA67,) -> 1744573 | AT67: =SUM(D67,J67,P67,V67,AB67,) -> 208196.3 | AU67: =SUM(E67,K67,Q67,W67,AC67,) -> 0 | AV67: =SUM(F67,L67,R67,X67,AD67,) -> -1963503.5 | AX67: =SUM(G67,M67,S67,Y67,AE67,) -> -10734.21 | AY67: =SUM(H67,N67,T67,Z67,AF67,) -> 8300000 | AZ67: =AX67+AY67 -> 8289265.8
B68: =B67+1 -> 44257 | C68: =G67 -> -189947.54 | D68: 100928.36 | E68: =50000-300000 -> -250000 | F68: -187916.96 | G68: =SUM(C68:F68) -> -526936.14 | H68: 4300000 | I68: =M67 -> 104589.78 | K68: 300000 | L68: -251156.47 | M68: =SUM(I68:L68) -> 153433.31 | N68: 4000000 | O68: =S67 -> 52783.21 | P68: 128740.06 | Q68: -50000 | S68: =SUM(O68:R68) -> 131523.27 | U68: =Y67 -> 208.04 | X68: -54.95 | Y68: =SUM(U68:X68) -> 153.09 | AA68: =AE67 -> 21632.3 | AE68: =SUM(AA68:AD68) -> 21632.3 | AS68: =SUM(C68,I68,O68,U68,AA68,) -> -10734.21 | AT68: =SUM(D68,J68,P68,V68,AB68,) -> 229668.42 | AU68: =SUM(E68,K68,Q68,W68,AC68,) -> 0 | AV68: =SUM(F68,L68,R68,X68,AD68,) -> -439128.38 | AX68: =SUM(G68,M68,S68,Y68,AE68,) -> -220194.17 | AY68: =SUM(H68,N68,T68,Z68,AF68,) -> 8300000 | AZ68: =AX68+AY68 -> 8079805.8
B69: =B68+1 -> 44258 | C69: =G68 -> -526936.14 | D69: 95602.04 | E69: 130000 | F69: -39789.78 | G69: =SUM(C69:F69) -> -341123.88 | H69: 4300000 | I69: =M68 -> 153433.31 | J69: 46922.51 | L69: -66125.03 | M69: =SUM(I69:L69) -> 134230.79 | N69: 4000000 | O69: =S68 -> 131523.27 | Q69: -130000 | R69: -444.37 | S69: =SUM(O69:R69) -> 1078.9 | U69: =Y68 -> 153.09 | Y69: =SUM(U69:X69) -> 153.09 | AA69: =AE68 -> 21632.3 | AD69: -3684.19 | AE69: =SUM(AA69:AD69) -> 17948.11 | AS69: =SUM(C69,I69,O69,U69,AA69,) -> -220194.17 | AT69: =SUM(D69,J69,P69,V69,AB69,) -> 142524.55 | AU69: =SUM(E69,K69,Q69,W69,AC69,) -> 0 | AV69: =SUM(F69,L69,R69,X69,AD69,) -> -110043.37 | AX69: =SUM(G69,M69,S69,Y69,AE69,) -> -187712.99 | AY69: =SUM(H69,N69,T69,Z69,AF69,) -> 8300000 | AZ69: =AX69+AY69 -> 8112287
B70: =B69+1 -> 44259 | C70: =G69 -> -341123.88 | D70: 216.51 | F70: -565315.44 | G70: =SUM(C70:F70) -> -906222.81 | H70: 4300000 | I70: =M69 -> 134230.79 | L70: -18057.1 | M70: =SUM(I70:L70) -> 116173.69 | N70: 4000000 | O70: =S69 -> 1078.9 | P70: 120.23 | S70: =SUM(O70:R70) -> 1199.13 | U70: =Y69 -> 153.09 | Y70: =SUM(U70:X70) -> 153.09 | AA70: =AE69 -> 17948.11 | AE70: =SUM(AA70:AD70) -> 17948.11 | AS70: =SUM(C70,I70,O70,U70,AA70,) -> -187712.99 | AT70: =SUM(D70,J70,P70,V70,AB70,) -> 336.74 | AU70: =SUM(E70,K70,Q70,W70,AC70,) -> 0 | AV70: =SUM(F70,L70,R70,X70,AD70,) -> -583372.54 | AX70: =SUM(G70,M70,S70,Y70,AE70,) -> -770748.79 | AY70: =SUM(H70,N70,T70,Z70,AF70,) -> 8300000 | AZ70: =AX70+AY70 -> 7529251.2
B71: =B70+1 -> 44260 | C71: =G70 -> -906222.81 | D71: 59880.22 | F71: -826159.98 | G71: =SUM(C71:F71) -> -1672502.6 | H71: 4300000 | I71: =M70 -> 116173.69 | J71: 32106.86 | L71: -19967.63 | M71: =SUM(I71:L71) -> 128312.92 | N71: 4000000 | O71: =S70 -> 1199.13 | S71: =SUM(O71:R71) -> 1199.13 | U71: =Y70 -> 153.09 | Y71: =SUM(U71:X71) -> 153.09 | AA71: =AE70 -> 17948.11 | AE71: =SUM(AA71:AD71) -> 17948.11 | AS71: =SUM(C71,I71,O71,U71,AA71,) -> -770748.79 | AT71: =SUM(D71,J71,P71,V71,AB71,) -> 91987.08 | AU71: =SUM(E71,K71,Q71,W71,AC71,) -> 0 | AV71: =SUM(F71,L71,R71,X71,AD71,) -> -846127.61 | AX71: =SUM(G71,M71,S71,Y71,AE71,) -> -1524889.3 | AY71: =SUM(H71,N71,T71,Z71,AF71,) -> 8300000 | AZ71: =AX71+AY71 -> 6775110.7
B72: =B71+3 -> 44263 | C72: =G71 -> -1672502.6 | E72: -235000 | F72: =-346393.57+200000+35000 -> -111393.57 | G72: =SUM(C72:F72) -> -2018896.1 | H72: 4300000 | I72: =M71 -> 128312.92 | J72: 242903.54 | K72: 200000 | L72: -581659.8 | M72: =SUM(I72:L72) -> -10443.34 | N72: 4000000 | O72: =S71 -> 1199.13 | P72: 346.02 | Q72: 35000 | R72: -10292 | S72: =SUM(O72:R72) -> 26253.15 | U72: =Y71 -> 153.09 | Y72: =SUM(U72:X72) -> 153.09 | AA72: =AE71 -> 17948.11 | AE72: =SUM(AA72:AD72) -> 17948.11 | AS72: =SUM(C72,I72,O72,U72,AA72,) -> -1524889.3 | AT72: =SUM(D72,J72,P72,V72,AB72,) -> 243249.56 | AU72: =SUM(E72,K72,Q72,W72,AC72,) -> 0 | AV72: =SUM(F72,L72,R72,X72,AD72,) -> -703345.37 | AX72: =SUM(G72,M72,S72,Y72,AE72,) -> -1984985.1 | AY72: =SUM(H72,N72,T72,Z72,AF72,) -> 8300000 | AZ72: =AX72+AY72 -> 6315014.9
B73: =B72+1 -> 44264 | C73: =G72 -> -2018896.1 | D73: =116386.27+14548.28 -> 130934.55 | E73: -90000 | F73: =-243592.26+90000 -> -153592.26 | G73: =SUM(C73:F73) -> -2131553.8 | H73: 4300000 | I73: =M72 -> -10443.34 | K73: 90000 | L73: -71457.39 | M73: =SUM(I73:L73) -> 8099.27 | N73: 4000000 | O73: =S72 -> 26253.15 | S73: =SUM(O73:R73) -> 26253.15 | U73: =Y72 -> 153.09 | Y73: =SUM(U73:X73) -> 153.09 | AA73: =AE72 -> 17948.11 | AE73: =SUM(AA73:AD73) -> 17948.11 | AS73: =SUM(C73,I73,O73,U73,AA73,) -> -1984985.1 | AT73: =SUM(D73,J73,P73,V73,AB73,) -> 130934.55 | AU73: =SUM(E73,K73,Q73,W73,AC73,) -> 0 | AV73: =SUM(F73,L73,R73,X73,AD73,) -> -225049.65 | AX73: =SUM(G73,M73,S73,Y73,AE73,) -> -2079100.2 | AY73: =SUM(H73,N73,T73,Z73,AF73,) -> 8300000 | AZ73: =AX73+AY73 -> 6220899.8
B74: =B73+1 -> 44265 | C74: =G73 -> -2131553.8 | D74: 134509.42 | G74: =SUM(C74:F74) -> -1997044.4 | H74: 4300000 | I74: =M73 -> 8099.27 | J74: 375 | M74: =SUM(I74:L74) -> 8474.27 | N74: 4000000 | O74: =S73 -> 26253.15 | S74: =SUM(O74:R74) -> 26253.15 | U74: =Y73 -> 153.09 | Y74: =SUM(U74:X74) -> 153.09 | AA74: =AE73 -> 17948.11 | AD74: -220.96 | AE74: =SUM(AA74:AD74) -> 17727.15 | AS74: =SUM(C74,I74,O74,U74,AA74,) -> -2079100.2 | AT74: =SUM(D74,J74,P74,V74,AB74,) -> 134884.42 | AU74: =SUM(E74,K74,Q74,W74,AC74,) -> 0 | AV74: =SUM(F74,L74,R74,X74,AD74,) -> -220.96 | AX74: =SUM(G74,M74,S74,Y74,AE74,) -> -1944436.8 | AY74: =SUM(H74,N74,T74,Z74,AF74,) -> 8300000 | AZ74: =AX74+AY74 -> 6355563.2
B75: =B74+1 -> 44266 | C75: =G74 -> -1997044.4 | D75: 194220.75 | E75: -910000 | F75: -2.16 | G75: =SUM(C75:F75) -> -2712825.8 | H75: 4300000 | I75: =M74 -> 8474.27 | K75: 910000 | L75: -905326.08 | M75: =SUM(I75:L75) -> 13148.19 | N75: 4000000 | O75: =S74 -> 26253.15 | S75: =SUM(O75:R75) -> 26253.15 | U75: =Y74 -> 153.09 | Y75: =SUM(U75:X75) -> 153.09 | AA75: =AE74 -> 17727.15 | AE75: =SUM(AA75:AD75) -> 17727.15 | AS75: =SUM(C75,I75,O75,U75,AA75,) -> -1944436.8 | AT75: =SUM(D75,J75,P75,V75,AB75,) -> 194220.75 | AU75: =SUM(E75,K75,Q75,W75,AC75,) -> 0 | AV75: =SUM(F75,L75,R75,X75,AD75,) -> -905328.24 | AX75: =SUM(G75,M75,S75,Y75,AE75,) -> -2655544.3 | AY75: =SUM(H75,N75,T75,Z75,AF75,) -> 8300000 | AZ75: =AX75+AY75 -> 5644455.7
B76: =B75+1 -> 44267 | C76: =G75 -> -2712825.8 | D76: 147370.98 | F76: -56953.62 | G76: =SUM(C76:F76) -> -2622408.5 | H76: 4300000 | I76: =M75 -> 13148.19 | L76: -1400 | M76: =SUM(I76:L76) -> 11748.19 | N76: 4000000 | O76: =S75 -> 26253.15 | R76: -1568.4 | S76: =SUM(O76:R76) -> 24684.75 | U76: =Y75 -> 153.09 | Y76: =SUM(U76:X76) -> 153.09 | AA76: =AE75 -> 17727.15 | AE76: =SUM(AA76:AD76) -> 17727.15 | AS76: =SUM(C76,I76,O76,U76,AA76,) -> -2655544.3 | AT76: =SUM(D76,J76,P76,V76,AB76,) -> 147370.98 | AU76: =SUM(E76,K76,Q76,W76,AC76,) -> 0 | AV76: =SUM(F76,L76,R76,X76,AD76,) -> -59922.02 | AX76: =SUM(G76,M76,S76,Y76,AE76,) -> -2568095.3 | AY76: =SUM(H76,N76,T76,Z76,AF76,) -> 8300000 | AZ76: =AX76+AY76 -> 5731904.7
B77: =B76+3 -> 44270 | C77: =G76 -> -2622408.5 | E77: -350000 | F77: -83929.17 | G77: =SUM(C77:F77) -> -3056337.6 | H77: 4300000 | I77: =M76 -> 11748.19 | K77: 350000 | L77: -341677.8 | M77: =SUM(I77:L77) -> 20070.39 | N77: 4000000 | O77: =S76 -> 24684.75 | P77: 45.61 | R77: -830 | S77: =SUM(O77:R77) -> 23900.36 | U77: =Y76 -> 153.09 | Y77: =SUM(U77:X77) -> 153.09 | AA77: =AE76 -> 17727.15 | AD77: -3699.76 | AE77: =SUM(AA77:AD77) -> 14027.39 | AS77: =SUM(C77,I77,O77,U77,AA77,) -> -2568095.3 | AT77: =SUM(D77,J77,P77,V77,AB77,) -> 45.61 | AU77: =SUM(E77,K77,Q77,W77,AC77,) -> 0 | AV77: =SUM(F77,L77,R77,X77,AD77,) -> -430136.73 | AX77: =SUM(G77,M77,S77,Y77,AE77,) -> -2998186.4 | AY77: =SUM(H77,N77,T77,Z77,AF77,) -> 8300000 | AZ77: =AX77+AY77 -> 5301813.6
B78: =B77+1 -> 44271 | C78: =G77 -> -3056337.6 | D78: 23042.05 | F78: -29634.31 | G78: =SUM(C78:F78) -> -3062929.9 | H78: 4300000 | I78: =M77 -> 20070.39 | L78: -5122.1 | M78: =SUM(I78:L78) -> 14948.29 | N78: 4000000 | O78: =S77 -> 23900.36 | P78: 513.5 | S78: =SUM(O78:R78) -> 24413.86 | U78: =Y77 -> 153.09 | Y78: =SUM(U78:X78) -> 153.09 | AA78: =AE77 -> 14027.39 | AE78: =SUM(AA78:AD78) -> 14027.39 | AS78: =SUM(C78,I78,O78,U78,AA78,) -> -2998186.4 | AT78: =SUM(D78,J78,P78,V78,AB78,) -> 23555.55 | AU78: =SUM(E78,K78,Q78,W78,AC78,) -> 0 | AV78: =SUM(F78,L78,R78,X78,AD78,) -> -34756.41 | AX78: =SUM(G78,M78,S78,Y78,AE78,) -> -3009387.3 | AY78: =SUM(H78,N78,T78,Z78,AF78,) -> 8300000 | AZ78: =AX78+AY78 -> 5290612.7
B79: =B78+1 -> 44272 | C79: =G78 -> -3062929.9 | D79: 35640 | E79: 650000 | F79: -12676.23 | G79: =SUM(C79:F79) -> -2389966.1 | H79: 4300000 | I79: =M78 -> 14948.29 | J79: 668221.8 | K79: -600000 | L79: -13186.4 | M79: =SUM(I79:L79) -> 69983.69 | N79: 4000000 | O79: =S78 -> 24413.86 | P79: 27159.27 | Q79: -50000 | R79: -178.45 | S79: =SUM(O79:R79) -> 1394.68 | U79: =Y78 -> 153.09 | Y79: =SUM(U79:X79) -> 153.09 | AA79: =AE78 -> 14027.39 | AE79: =SUM(AA79:AD79) -> 14027.39 | AS79: =SUM(C79,I79,O79,U79,AA79,) -> -3009387.3 | AT79: =SUM(D79,J79,P79,V79,AB79,) -> 731021.07 | AU79: =SUM(E79,K79,Q79,W79,AC79,) -> 0 | AV79: =SUM(F79,L79,R79,X79,AD79,) -> -26041.08 | AX79: =SUM(G79,M79,S79,Y79,AE79,) -> -2304407.3 | AY79: =SUM(H79,N79,T79,Z79,AF79,) -> 8300000 | AZ79: =AX79+AY79 -> 5995592.7
B80: =B79+1 -> 44273 | C80: =G79 -> -2389966.1 | G80: =SUM(C80:F80) -> -2389966.1 | H80: 4300000 | I80: =M79 -> 69983.69 | L80: -32938.09 | M80: =SUM(I80:L80) -> 37045.6 | N80: 4000000 | O80: =S79 -> 1394.68 | S80: =SUM(O80:R80) -> 1394.68 | U80: =Y79 -> 153.09 | Y80: =SUM(U80:X80) -> 153.09 | AA80: =AE79 -> 14027.39 | AE80: =SUM(AA80:AD80) -> 14027.39 | AS80: =SUM(C80,I80,O80,U80,AA80,) -> -2304407.3 | AT80: =SUM(D80,J80,P80,V80,AB80,) -> 0 | AU80: =SUM(E80,K80,Q80,W80,AC80,) -> 0 | AV80: =SUM(F80,L80,R80,X80,AD80,) -> -32938.09 | AX80: =SUM(G80,M80,S80,Y80,AE80,) -> -2337345.4 | AY80: =SUM(H80,N80,T80,Z80,AF80,) -> 8300000 | AZ80: =AX80+AY80 -> 5962654.6
B81: =B80+1 -> 44274 | C81: =G80 -> -2389966.1 | D81: 48072.66 | E81: 150000 | F81: -1018349.1 | G81: =SUM(C81:F81) -> -3210242.5 | H81: 4300000 | I81: =M80 -> 37045.6 | J81: =56751.28+107293.91 -> 164045.19 | K81: -150000 | L81: -38226.63 | M81: =SUM(I81:L81) -> 12864.16 | N81: 4000000 | O81: =S80 -> 1394.68 | S81: =SUM(O81:R81) -> 1394.68 | U81: =Y80 -> 153.09 | Y81: =SUM(U81:X81) -> 153.09 | AA81: =AE80 -> 14027.39 | AE81: =SUM(AA81:AD81) -> 14027.39 | AS81: =SUM(C81,I81,O81,U81,AA81,) -> -2337345.4 | AT81: =SUM(D81,J81,P81,V81,AB81,) -> 212117.85 | AU81: =SUM(E81,K81,Q81,W81,AC81,) -> 0 | AV81: =SUM(F81,L81,R81,X81,AD81,) -> -1056575.7 | AX81: =SUM(G81,M81,S81,Y81,AE81,) -> -3181803.2 | AY81: =SUM(H81,N81,T81,Z81,AF81,) -> 8300000 | AZ81: =AX81+AY81 -> 5118196.8
B82: =B81+3 -> 44277 | C82: =G81 -> -3210242.5 | D82: 413387.13 | E82: =-240000-28000 -> -268000 | F82: -44025.05 | G82: =SUM(C82:F82) -> -3108880.5 | H82: 4300000 | I82: =M81 -> 12864.16 | K82: 28000 | L82: -40135.26 | M82: =SUM(I82:L82) -> 728.9 | N82: 4000000 | O82: =S81 -> 1394.68 | S82: =SUM(O82:R82) -> 1394.68 | U82: =Y81 -> 153.09 | Y82: =SUM(U82:X82) -> 153.09 | AA82: =AE81 -> 14027.39 | AC82: 240000 | AD82: =-240000-12467.45 -> -252467.45 | AE82: =SUM(AA82:AD82) -> 1559.94 | AS82: =SUM(C82,I82,O82,U82,AA82,) -> -3181803.2 | AT82: =SUM(D82,J82,P82,V82,AB82,) -> 413387.13 | AU82: =SUM(E82,K82,Q82,W82,AC82,) -> 0 | AV82: =SUM(F82,L82,R82,X82,AD82,) -> -336627.76 | AX82: =SUM(G82,M82,S82,Y82,AE82,) -> -3105043.8 | AY82: =SUM(H82,N82,T82,Z82,AF82,) -> 8300000 | AZ82: =AX82+AY82 -> 5194956.2
B83: =B82+1 -> 44278 | C83: =G82 -> -3108880.5 | D83: 150611.29 | E83: -2000 | F83: -6529.97 | G83: =SUM(C83:F83) -> -2966799.1 | H83: 4300000 | I83: =M82 -> 728.9 | K83: 2000 | L83: -1145.04 | M83: =SUM(I83:L83) -> 1583.86 | N83: 4000000 | O83: =S82 -> 1394.68 | S83: =SUM(O83:R83) -> 1394.68 | U83: =Y82 -> 153.09 | Y83: =SUM(U83:X83) -> 153.09 | AA83: =AE82 -> 1559.94 | AE83: =SUM(AA83:AD83) -> 1559.94 | AS83: =SUM(C83,I83,O83,U83,AA83,) -> -3105043.8 | AT83: =SUM(D83,J83,P83,V83,AB83,) -> 150611.29 | AU83: =SUM(E83,K83,Q83,W83,AC83,) -> 0 | AV83: =SUM(F83,L83,R83,X83,AD83,) -> -7675.01 | AX83: =SUM(G83,M83,S83,Y83,AE83,) -> -2962107.6 | AY83: =SUM(H83,N83,T83,Z83,AF83,) -> 8300000 | AZ83: =AX83+AY83 -> 5337892.4
B84: =B83+1 -> 44279 | C84: -2966799.1 | D84: 70726.6 | E84: 30000 | F84: -10714.65 | G84: -2876787.2 | H84: 4300000 | I84: 1583.86 | J84: 769563.62 | L84: -651.43 | M84: 770496.05 | N84: 4000000 | O84: 1394.68 | P84: 30314.9 | Q84: -30000 | S84: 1709.58 | U84: 153.09 | Y84: 153.09 | AA84: 1559.94 | AE84: 1559.94 | AS84: -2962107.6 | AT84: 870605.12 | AU84: 0 | AV84: -11366.08 | AX84: -2102868.5 | AY84: 6300030 | AZ84: 4197161.5
B85: =B84+1 -> 44280 | C85: =G84 -> -2876787.2 | E85: 700000 | F85: -110836.8 | G85: =SUM(C85:F85) -> -2287624 | H85: 4300000 | I85: =M84 -> 770496.05 | J85: 300 | K85: -700000 | L85: -49757.27 | M85: =SUM(I85:L85) -> 21038.78 | N85: 4000000 | O85: =S84 -> 1709.58 | R85: -84 | S85: =SUM(O85:R85) -> 1625.58 | U85: =Y84 -> 153.09 | Y85: =SUM(U85:X85) -> 153.09 | AA85: =AE84 -> 1559.94 | AD85: -231.67 | AE85: =SUM(AA85:AD85) -> 1328.27 | AS85: =SUM(C85,I85,O85,U85,AA85,) -> -2102868.5 | AT85: =SUM(D85,J85,P85,V85,AB85,) -> 300 | AU85: =SUM(E85,K85,Q85,W85,AC85,) -> 0 | AV85: =SUM(F85,L85,R85,X85,AD85,) -> -160909.74 | AX85: =SUM(G85,M85,S85,Y85,AE85,) -> -2263478.3 | AY85: =SUM(H85,N85,T85,Z85,AF85,) -> 8300000 | AZ85: =AX85+AY85 -> 6036521.7
B86: =B85+1 -> 44281 | C86: =G85 -> -2287624 | D86: 153171.73 | E86: 370000 | F86: -29853.1 | G86: =SUM(C86:F86) -> -1794305.4 | H86: 4300000 | I86: =M85 -> 21038.78 | J86: 360026.43 | K86: -370000 | L86: -7087.79 | M86: =SUM(I86:L86) -> 3977.42 | N86: 4000000 | O86: =S85 -> 1625.58 | S86: =SUM(O86:R86) -> 1625.58 | U86: =Y85 -> 153.09 | Y86: =SUM(U86:X86) -> 153.09 | AA86: =AE85 -> 1328.27 | AE86: =SUM(AA86:AD86) -> 1328.27 | AS86: =SUM(C86,I86,O86,U86,AA86,) -> -2263478.3 | AT86: =SUM(D86,J86,P86,V86,AB86,) -> 513198.16 | AU86: =SUM(E86,K86,Q86,W86,AC86,) -> 0 | AV86: =SUM(F86,L86,R86,X86,AD86,) -> -36940.89 | AX86: =SUM(G86,M86,S86,Y86,AE86,) -> -1787221 | AY86: =SUM(H86,N86,T86,Z86,AF86,) -> 8300000 | AZ86: =AX86+AY86 -> 6512779
B87: =B86+3 -> 44284 | C87: =G86 -> -1794305.4 | E87: -580000 | F87: =-1724300.08+580000 -> -1144300.1 | G87: =SUM(C87:F87) -> -3518605.4 | H87: 4300000 | I87: =M86 -> 3977.42 | J87: 515113.21 | K87: 580000 | L87: -1090531.4 | M87: =SUM(I87:L87) -> 8559.2 | N87: 4000000 | O87: =S86 -> 1625.58 | P87: 614.4 | S87: =SUM(O87:R87) -> 2239.98 | U87: =Y86 -> 153.09 | Y87: =SUM(U87:X87) -> 153.09 | AA87: =AE86 -> 1328.27 | AD87: -21.6 | AE87: =SUM(AA87:AD87) -> 1306.67 | AS87: =SUM(C87,I87,O87,U87,AA87,) -> -1787221 | AT87: =SUM(D87,J87,P87,V87,AB87,) -> 515727.61 | AU87: =SUM(E87,K87,Q87,W87,AC87,) -> 0 | AV87: =SUM(F87,L87,R87,X87,AD87,) -> -2234853.1 | AX87: =SUM(G87,M87,S87,Y87,AE87,) -> -3506346.5 | AY87: =SUM(H87,N87,T87,Z87,AF87,) -> 8300000 | AZ87: =AX87+AY87 -> 4793653.5
B88: =B87+1 -> 44285 | C88: =G87 -> -3518605.4 | D88: =53971+10177.92 -> 64148.92 | E88: -170000 | F88: -22888.69 | G88: =SUM(C88:F88) -> -3647345.2 | H88: 4300000 | I88: =M87 -> 8559.2 | K88: 170000 | L88: -175362.55 | M88: =SUM(I88:L88) -> 3196.65 | N88: 4000000 | O88: =S87 -> 2239.98 | P88: 200752.9 | S88: =SUM(O88:R88) -> 202992.88 | U88: =Y87 -> 153.09 | Y88: =SUM(U88:X88) -> 153.09 | AA88: =AE87 -> 1306.67 | AE88: =SUM(AA88:AD88) -> 1306.67 | AS88: =SUM(C88,I88,O88,U88,AA88,) -> -3506346.5 | AT88: =SUM(D88,J88,P88,V88,AB88,) -> 264901.82 | AU88: =SUM(E88,K88,Q88,W88,AC88,) -> 0 | AV88: =SUM(F88,L88,R88,X88,AD88,) -> -198251.24 | AX88: =SUM(G88,M88,S88,Y88,AE88,) -> -3439695.9 | AY88: =SUM(H88,N88,T88,Z88,AF88,) -> 8300000 | AZ88: =AX88+AY88 -> 4860304.1
B89: =B88+1 -> 44286 | C89: =G88 -> -3647345.2 | D89: =519216.92-200000 -> 319216.92 | E89: 200000 | F89: -401677.45 | G89: =SUM(C89:F89) -> -3529805.7 | H89: 4300000 | I89: =M88 -> 3196.65 | J89: 107532.53 | L89: -91299.52 | M89: =SUM(I89:L89) -> 19429.66 | N89: 4000000 | O89: =S88 -> 202992.88 | Q89: -200000 | R89: =-550-255 -> -805 | S89: =SUM(O89:R89) -> 2187.88 | U89: =Y88 -> 153.09 | Y89: =SUM(U89:X89) -> 153.09 | AA89: =AE88 -> 1306.67 | AD89: -846 | AE89: =SUM(AA89:AD89) -> 460.67 | AS89: =SUM(C89,I89,O89,U89,AA89,) -> -3439695.9 | AT89: =SUM(D89,J89,P89,V89,AB89,) -> 426749.45 | AU89: =SUM(E89,K89,Q89,W89,AC89,) -> 0 | AV89: =SUM(F89,L89,R89,X89,AD89,) -> -494627.97 | AX89: =SUM(G89,M89,S89,Y89,AE89,) -> -3507574.4 | AY89: =SUM(H89,N89,T89,Z89,AF89,) -> 8300000 | AZ89: =AX89+AY89 -> 4792425.6
B90: =B89+1 -> 44287 | C90: =G89 -> -3529805.7 | D90: 2966.51 | F90: -218156.22 | G90: =SUM(C90:F90) -> -3744995.4 | H90: 4300000 | I90: =M89 -> 19429.66 | J90: 258.35 | L90: -1846455.3 | M90: =SUM(I90:L90) -> -1826767.3 | N90: 4000000 | O90: =S89 -> 2187.88 | P90: 676.16 | R90: =-2811.86 -> -2811.86 | S90: =SUM(O90:R90) -> 52.18 | U90: =Y89 -> 153.09 | V90: 274662.34 | Y90: =SUM(U90:X90) -> 274815.43 | AA90: =AE89 -> 460.67 | AE90: =SUM(AA90:AD90) -> 460.67 | AS90: =SUM(C90,I90,O90,U90,AA90,) -> -3507574.4 | AT90: =SUM(D90,J90,P90,V90,AB90,) -> 278563.36 | AU90: =SUM(E90,K90,Q90,W90,AC90,) -> 0 | AV90: =SUM(F90,L90,R90,X90,AD90,) -> -2067423.4 | AX90: =SUM(G90,M90,S90,Y90,AE90,) -> -5296434.5 | AY90: =SUM(H90,N90,T90,Z90,AF90,) -> 8300000 | AZ90: =AX90+AY90 -> 3003565.5
B91: =B90+4 -> 44291 | C91: =G90 -> -3744995.4 | D91: 1756.44 | E91: 600000 | F91: -204136.46 | G91: =SUM(C91:F91) -> -3347375.5 | H91: 4300000 | I91: =M90 -> -1826767.3 | L91: -590470.89 | M91: =SUM(I91:L91) -> -2417238.2 | N91: 4000000 | O91: =S90 -> 52.18 | P91: =880.1+30 -> 910.1 | Q91: 42000 | R91: -14782.33 | S91: =SUM(O91:R91) -> 28179.95 | U91: =Y90 -> 274815.43 | V91: 367693.04 | W91: =-642000 -> -642000 | X91: -54.95 | Y91: =SUM(U91:X91) -> 453.52 | AA91: =AE90 -> 460.67 | AE91: =SUM(AA91:AD91) -> 460.67 | AS91: =SUM(C91,I91,O91,U91,AA91,) -> -5296434.5 | AT91: =SUM(D91,J91,P91,V91,AB91,) -> 370359.58 | AU91: =SUM(E91,K91,Q91,W91,AC91,) -> 0 | AV91: =SUM(F91,L91,R91,X91,AD91,) -> -809444.63 | AX91: =SUM(G91,M91,S91,Y91,AE91,) -> -5735519.5 | AY91: =SUM(H91,N91,T91,Z91,AF91,) -> 8300000 | AZ91: =AX91+AY91 -> 2564480.5 | BA91: =AVERAGE(AV90:AV110) -> -327464.61
B92: =B91+1 -> 44292 | C92: =G91 -> -3347375.5 | D92: 61152.66 | E92: -270000 | F92: -54194.57 | G92: =SUM(C92:F92) -> -3610417.4 | H92: 4300000 | I92: =M91 -> -2417238.2 | K92: 270000 | L92: -277655.94 | M92: =SUM(I92:L92) -> -2424894.2 | N92: 4000000 | O92: =S91 -> 28179.95 | R92: -14387.5 | S92: =SUM(O92:R92) -> 13792.45 | U92: =Y91 -> 453.52 | X92: -1.2 | Y92: =SUM(U92:X92) -> 452.32 | AA92: =AE91 -> 460.67 | AE92: =SUM(AA92:AD92) -> 460.67 | AS92: =SUM(C92,I92,O92,U92,AA92,) -> -5735519.5 | AT92: =SUM(D92,J92,P92,V92,AB92,) -> 61152.66 | AU92: =SUM(E92,K92,Q92,W92,AC92,) -> 0 | AV92: =SUM(F92,L92,R92,X92,AD92,) -> -346239.21 | AX92: =SUM(G92,M92,S92,Y92,AE92,) -> -6020606.1 | AY92: =SUM(H92,N92,T92,Z92,AF92,) -> 8300000 | AZ92: =AX92+AY92 -> 2279393.9 | BA92: =SUM(AV90:AV110) -> -6876756.8
B93: =B92+1 -> 44293 | C93: =G92 -> -3610417.4 | D93: 146585.64 | E93: 20000 | F93: -338639.94 | G93: =SUM(C93:F93) -> -3782471.7 | H93: 4300000 | I93: =M92 -> -2424894.2 | J93: 36946.49 | K93: -20000 | L93: =-15107.73-4380.28 -> -19488.01 | M93: =SUM(I93:L93) -> -2427435.7 | N93: 4000000 | O93: =S92 -> 13792.45 | R93: -551 | S93: =SUM(O93:R93) -> 13241.45 | U93: =Y92 -> 452.32 | Y93: =SUM(U93:X93) -> 452.32 | AA93: =AE92 -> 460.67 | AE93: =SUM(AA93:AD93) -> 460.67 | AS93: =SUM(C93,I93,O93,U93,AA93,) -> -6020606.1 | AT93: =SUM(D93,J93,P93,V93,AB93,) -> 183532.13 | AU93: =SUM(E93,K93,Q93,W93,AC93,) -> 0 | AV93: =SUM(F93,L93,R93,X93,AD93,) -> -358678.95 | AX93: =SUM(G93,M93,S93,Y93,AE93,) -> -6195752.9 | AY93: =SUM(H93,N93,T93,Z93,AF93,) -> 8300000 | AZ93: =AX93+AY93 -> 2104247.1 | BC93: Pagamentos em banco | BD93: Valor
B94: =B93+1 -> 44294 | C94: =G93 -> -3782471.7 | D94: =53971+55600.49 -> 109571.49 | E94: 400000 | F94: -3250.94 | G94: =SUM(C94:F94) -> -3276151.1 | H94: 4300000 | I94: =M93 -> -2427435.7 | J94: =70894.33+57205.15+282920.21+18996.18+9403.59+19378.1+3918.16 -> 462715.72 | K94: -400000 | L94: -77671.41 | M94: =SUM(I94:L94) -> -2442391.4 | N94: 4000000 | O94: =S93 -> 13241.45 | S94: =SUM(O94:R94) -> 13241.45 | U94: =Y93 -> 452.32 | Y94: =SUM(U94:X94) -> 452.32 | AA94: =AE93 -> 460.67 | AE94: =SUM(AA94:AD94) -> 460.67 | AS94: =SUM(C94,I94,O94,U94,AA94,) -> -6195752.9 | AT94: =SUM(D94,J94,P94,V94,AB94,) -> 572287.21 | AU94: =SUM(E94,K94,Q94,W94,AC94,) -> 0 | AV94: =SUM(F94,L94,R94,X94,AD94,) -> -80922.35 | AX94: =SUM(G94,M94,S94,Y94,AE94,) -> -5704388 | AY94: =SUM(H94,N94,T94,Z94,AF94,) -> 8300000 | AZ94: =AX94+AY94 -> 2595612 | BC94: Abril | BD94: -6876756.8
B95: =B94+1 -> 44295 | C95: =G94 -> -3276151.1 | D95: 4478.27 | F95: -159150.33 | G95: =SUM(C95:F95) -> -3430823.2 | H95: 4300000 | I95: =M94 -> -2442391.4 | J95: 32037.25 | L95: -11611.62 | M95: =SUM(I95:L95) -> -2421965.7 | N95: 4000000 | O95: =S94 -> 13241.45 | P95: 651.84 | S95: =SUM(O95:R95) -> 13893.29 | U95: =Y94 -> 452.32 | Y95: =SUM(U95:X95) -> 452.32 | AA95: =AE94 -> 460.67 | AE95: =SUM(AA95:AD95) -> 460.67 | AS95: =SUM(C95,I95,O95,U95,AA95,) -> -5704388 | AT95: =SUM(D95,J95,P95,V95,AB95,) -> 37167.36 | AU95: =SUM(E95,K95,Q95,W95,AC95,) -> 0 | AV95: =SUM(F95,L95,R95,X95,AD95,) -> -170761.95 | AX95: =SUM(G95,M95,S95,Y95,AE95,) -> -5837982.6 | AY95: =SUM(H95,N95,T95,Z95,AF95,) -> 8300000 | AZ95: =AX95+AY95 -> 2462017.4 | BC95: Maio | BD95: -7595608.4
B96: =B95+3 -> 44298 | C96: =G95 -> -3430823.2 | D96: 1133454.1 | F96: -201731.12 | G96: =SUM(C96:F96) -> -2499100.2 | H96: 4300000 | I96: =M95 -> -2421965.7 | J96: 20023.84 | L96: -51693 | M96: =SUM(I96:L96) -> -2453634.9 | N96: 4000000 | O96: =S95 -> 13893.29 | P96: 50.96 | Q96: 14000 | R96: -6821.6 | S96: =SUM(O96:R96) -> 21122.65 | U96: =Y95 -> 452.32 | V96: 13874.79 | W96: -14000 | Y96: =SUM(U96:X96) -> 327.11 | AA96: =AE95 -> 460.67 | AD96: -295 | AE96: =SUM(AA96:AD96) -> 165.67 | AS96: =SUM(C96,I96,O96,U96,AA96,) -> -5837982.6 | AT96: =SUM(D96,J96,P96,V96,AB96,) -> 1167403.7 | AU96: =SUM(E96,K96,Q96,W96,AC96,) -> 0 | AV96: =SUM(F96,L96,R96,X96,AD96,) -> -260540.72 | AX96: =SUM(G96,M96,S96,Y96,AE96,) -> -4931119.7 | AY96: =SUM(H96,N96,T96,Z96,AF96,) -> 8300000 | AZ96: =AX96+AY96 -> 3368880.3 | BC96: Junho | BD96: -6486036.7
B97: =B96+1 -> 44299 | C97: =G96 -> -2499100.2 | E97: -50000 | F97: -9724.14 | G97: =SUM(C97:F97) -> -2558824.3 | H97: 4300000 | I97: =M96 -> -2453634.9 | K97: 50000 | L97: -58029.76 | M97: =SUM(I97:L97) -> -2461664.7 | N97: 4000000 | O97: =S96 -> 21122.65 | R97: -2419.58 | S97: =SUM(O97:R97) -> 18703.07 | U97: =Y96 -> 327.11 | X97: -1.2 | Y97: =SUM(U97:X97) -> 325.91 | AA97: =AE96 -> 165.67 | AE97: =SUM(AA97:AD97) -> 165.67 | AS97: =SUM(C97,I97,O97,U97,AA97,) -> -4931119.7 | AT97: =SUM(D97,J97,P97,V97,AB97,) -> 0 | AU97: =SUM(E97,K97,Q97,W97,AC97,) -> 0 | AV97: =SUM(F97,L97,R97,X97,AD97,) -> -70174.68 | AX97: =SUM(G97,M97,S97,Y97,AE97,) -> -5001294.3 | AY97: =SUM(H97,N97,T97,Z97,AF97,) -> 8300000 | AZ97: =AX97+AY97 -> 3298705.7 | BC97: Total | BD97: =BD96+BD95+BD94 -> -20958402
B98: =B97+1 -> 44300 | C98: =G97 -> -2558824.3 | D98: 15586.61 | F98: =-15673+68.5 -> -15604.5 | G98: =SUM(C98:F98) -> -2558842.2 | H98: 4300000 | I98: =M97 -> -2461664.7 | L98: -12296.46 | M98: =SUM(I98:L98) -> -2473961.1 | N98: 4000000 | O98: =S97 -> 18703.07 | S98: =SUM(O98:R98) -> 18703.07 | U98: =Y97 -> 325.91 | Y98: =SUM(U98:X98) -> 325.91 | AA98: =AE97 -> 165.67 | AE98: =SUM(AA98:AD98) -> 165.67 | AS98: =SUM(C98,I98,O98,U98,AA98,) -> -5001294.3 | AT98: =SUM(D98,J98,P98,V98,AB98,) -> 15586.61 | AU98: =SUM(E98,K98,Q98,W98,AC98,) -> 0 | AV98: =SUM(F98,L98,R98,X98,AD98,) -> -27900.96 | AX98: =SUM(G98,M98,S98,Y98,AE98,) -> -5013608.7 | AY98: =SUM(H98,N98,T98,Z98,AF98,) -> 8300000 | AZ98: =AX98+AY98 -> 3286391.3 | BC98: Media | BD98: =BD97/3 -> -6986134
B99: =B98+1 -> 44301 | C99: =G98 -> -2558842.2 | E99: -370000 | F99: -24740.19 | G99: =SUM(C99:F99) -> -2953582.4 | H99: 4300000 | I99: =M98 -> -2473961.1 | K99: 370000 | L99: -367155.42 | M99: =SUM(I99:L99) -> -2471116.5 | N99: 4000000 | O99: =S98 -> 18703.07 | R99: -5853.61 | S99: =SUM(O99:R99) -> 12849.46 | U99: =Y98 -> 325.91 | V99: 82009.88 | Y99: =SUM(U99:X99) -> 82335.79 | AA99: =AE98 -> 165.67 | AE99: =SUM(AA99:AD99) -> 165.67 | AS99: =SUM(C99,I99,O99,U99,AA99,) -> -5013608.7 | AT99: =SUM(D99,J99,P99,V99,AB99,) -> 82009.88 | AU99: =SUM(E99,K99,Q99,W99,AC99,) -> 0 | AV99: =SUM(F99,L99,R99,X99,AD99,) -> -397749.22 | AX99: =SUM(G99,M99,S99,Y99,AE99,) -> -5329348 | AY99: =SUM(H99,N99,T99,Z99,AF99,) -> 8300000 | AZ99: =AX99+AY99 -> 2970652
B100: =B99+1 -> 44302 | C100: =G99 -> -2953582.4 | D100: 101011.55 | F100: -14136.42 | G100: =SUM(C100:F100) -> -2866707.3 | H100: 4300000 | I100: =M99 -> -2471116.5 | L100: -116 | M100: =SUM(I100:L100) -> -2471232.5 | N100: 4000000 | O100: =S99 -> 12849.46 | P100: 7241.09 | Q100: 82000 | S100: =SUM(O100:R100) -> 102090.55 | U100: =Y99 -> 82335.79 | W100: -82000 | X100: -1.2 | Y100: =SUM(U100:X100) -> 334.59 | AA100: =AE99 -> 165.67 | AE100: =SUM(AA100:AD100) -> 165.67 | AS100: =SUM(C100,I100,O100,U100,AA100,) -> -5329348 | AT100: =SUM(D100,J100,P100,V100,AB100,) -> 108252.64 | AU100: =SUM(E100,K100,Q100,W100,AC100,) -> 0 | AV100: =SUM(F100,L100,R100,X100,AD100,) -> -14253.62 | AX100: =SUM(G100,M100,S100,Y100,AE100,) -> -5235349 | AY100: =SUM(H100,N100,T100,Z100,AF100,) -> 8300000 | AZ100: =AX100+AY100 -> 3064651 | BC100: =BA92+BA133+BA110 -> -20958402
...
